Workbook

Sheet 0. README
A1: NOVATECH ELECTRONICS | SUPPLY CHAIN ANALYTICS PROJECT
A2: An end to end inventory analytics model | Built by Kavish Shah
B4: ABOUT THIS PROJECT
B5: NovaTech Electronics is a fictional consumer electronics distributor created for this analysis.
B6: The model covers 500 SKUs across 10 categories, 3 regional distribution centers, and 10 suppliers,
B7: with 24 months of monthly demand history including holiday seasonality and year over year growth.
B8: Every analytical number in this workbook is a live Excel formula. Change an input and the entire model recalculates.
B10: HOW THE TABS FLOW
B11: 1. Master Data: the 500 SKU backbone (cost, lead time, supplier, stock position).
B12: 2. Demand History: 24 months of demand per SKU with visible Q4 spikes.
B13: 3. Demand Forecast: method matched to demand pattern, MAPE backtested over 6 months.
B14: 4. ABC XYZ Analysis: value concentration vs predictability, with the 9 box strategy matrix.
B15: 5. Replenishment Model: safety stock, reorder points, EOQ and order flags for all 500 SKUs.
B16: 6. Inventory Health: aging, turns, and the excess capital report.
... B30: The methodology, formulas, and analytical logic are exactly what I would apply to real company data.

Sheet 1. Master Data
A1: MASTER DATA | 500 SKUs
A2: Single source of truth: identity, sourcing, cost, lead time, status, stock position.
A4: SKU | B4: Product Name | C4: Category | D4: DC | E4: Supplier | F4: Unit Cost | G4: Lead Time Days | H4: Status | I4: On Hand | J4: Days Since Move | K4: Annual Usage
A5: NT10001 | B5: Nova X427 128GB | C5: Smartphones | D5: West DC | E5: Shenzhen Onyx Electronics | F5: 865 | G5: 17 | H5: Active | I5: 124 | J5: 53 | K5: 1141
A6: NT10002 | B6: Pulse 962 Dual SIM | C6: Smartphones | D6: East DC | E6: Pacific Semis | F6: 701 | G6: 44 | H6: Active | I6: 146 | J6: 48 | K6: 634
A7: NT10003 | B7: Nova Lite 936 64GB | C7: Smartphones | D7: West DC | E7: Shenzhen Onyx Electronics | F7: 261 | G7: 21 | H7: Active | I7: 181 | J7: 25 | K7: 1450
A8: NT10004 | B8: Nova Lite 315 64GB | C8: Smartphones | D8: West DC | E8: Pacific Semis | F8: 606 | G8: 39 | H8: Active | I8: 177 | J8: 29 | K8: 804
A9: NT10005 | B9: Pulse 753 Dual SIM | C9: Smartphones | D9: Central DC | E9: Shenzhen Onyx Electronics | F9: 598 | G9: 25 | H9: Active | I9: 61 | J9: 43 | K9: 422
A10: NT10006 | B10: Edge 244 5G 128GB | C10: Smartphones | D10: Central DC | E10: Pacific Semis | F10: 627 | G10: 35 | H10: Active | I10: 150 | J10: 68 | K10: 794
A11: NT10007 | B11: Pulse 667 Dual SIM | C11: Smartphones | D11: Central DC | E11: Pacific Semis | F11: 685 | G11: 36 | H11: Active | I11: 86 | J11: 16 | K11: 413
A12: NT10008 | B12: Edge 637 5G 128GB | C12: Smartphones | D12: West DC | E12: Pacific Semis | F12: 827 | G12: 41 | H12: Active | I12: 370 | J12: 69 | K12: 1629
A13: NT10009 | B13: Nova X689 128GB | C13: Smartphones | D13: West DC | E13: Shenzhen Onyx Electronics | F13: 382 | G13: 26 | H13: Active | I13: 86 | J13: 53 | K13: 593
A14: NT10010 | B14: Nova X834 128GB | C14: Smartphones | D14: West DC | E14: Pacific Semis | F14: 395 | G14: 42 | H14: Active | I14: 608 | J14: 30 | K14: 2758
A15: NT10011 | B15: Edge 790 5G 128GB | C15: Smartphones | D15: Central DC | E15: Pacific Semis | F15: 507 | G15: 43 | H15: Active | I15: 251 | J15: 53 | K15: 1094
A16: NT10012 | B16: Pulse 918 Dual SIM | C16: Smartphones | D16: East DC | E16: Pacific Semis | F16: 693 | G16: 41 | H16: Active | I16: 29 | J16: 6 | K16: 121
... A504: NT10500 | B504: Phone Case Clear V670 | C504: Accessories | D504: East DC | E504: Hanoi Assembly Works | F504: 28 | G504: 22 | H504: Active | I504: 277 | J504: 10 | K504: 2962
A506: FORMULA REFERENCE
A507: Static base data. Every other sheet links here or to Demand History, so changing a value here flows through the whole model.
A508: Annual Usage equals the sum of the last 12 months in Demand History (verified live on the ABC XYZ sheet).

Sheet 2. Demand History
A1: DEMAND HISTORY | 24 MONTHS
A2: Monthly unit demand per SKU, Jun 2024 to May 2026. Watch the Q4 holiday spikes.
A4: SKU | B4: Product Name | C4: Jun 24 | D4: Jul 24 | E4: Aug 24 | F4: Sep 24 | G4: Oct 24 | H4: Nov 24 | I4: Dec 24 | J4: Jan 25 | K4: Feb 25 | L4: Mar 25 | M4: Apr 25 | N4: May 25 | O4: Jun 25 | P4: Jul 25 | Q4: Aug 25 | R4: Sep 25 | S4: Oct 25 | T4: Nov 25 | U4: Dec 25 | V4: Jan 26 | W4: Feb 26 | X4: Mar 26 | Y4: Apr 26 | Z4: May 26 | AA4: Annual Last 12
A5: NT10001 | B5: Nova X427 128GB | C5: 82 | D5: 89 | E5: 71 | F5: 96 | G5: 90 | H5: 106 | I5: 164 | J5: 64 | K5: 75 | L5: 85 | M5: 87 | N5: 88 | O5: 99 | P5: 72 | Q5: 84 | R5: 87 | S5: 102 | T5: 148 | U5: 166 | V5: 60 | W5: 61 | X5: 85 | Y5: 98 | Z5: 79 | AA5: =SUM(O5:Z5) -> 1141
A6: NT10002 | B6: Pulse 962 Dual SIM | C6: 48 | D6: 49 | E6: 43 | F6: 46 | G6: 56 | H6: 71 | I6: 92 | J6: 34 | K6: 47 | L6: 44 | M6: 43 | N6: 53 | O6: 42 | P6: 49 | Q6: 40 | R6: 53 | S6: 60 | T6: 74 | U6: 89 | V6: 37 | W6: 35 | X6: 48 | Y6: 49 | Z6: 58 | AA6: =SUM(O6:Z6) -> 634
A7: NT10003 | B7: Nova Lite 936 64GB | C7: 106 | D7: 102 | E7: 91 | F7: 98 | G7: 129 | H7: 148 | I7: 206 | J7: 82 | K7: 82 | L7: 89 | M7: 109 | N7: 111 | O7: 109 | P7: 107 | Q7: 98 | R7: 110 | S7: 130 | T7: 174 | U7: 217 | V7: 87 | W7: 95 | X7: 92 | Y7: 109 | Z7: 122 | AA7: =SUM(O7:Z7) -> 1450
A8: NT10004 | B8: Nova Lite 315 64GB | C8: 57 | D8: 59 | E8: 49 | F8: 55 | G8: 65 | H8: 87 | I8: 98 | J8: 45 | K8: 45 | L8: 59 | M8: 67 | N8: 64 | O8: 61 | P8: 52 | Q8: 53 | R8: 61 | S8: 75 | T8: 92 | U8: 132 | V8: 37 | W8: 54 | X8: 69 | Y8: 53 | Z8: 65 | AA8: =SUM(O8:Z8) -> 804
A9: NT10005 | B9: Pulse 753 Dual SIM | C9: 29 | D9: 29 | E9: 30 | F9: 29 | G9: 36 | H9: 47 | I9: 59 | J9: 22 | K9: 26 | L9: 26 | M9: 31 | N9: 32 | O9: 30 | P9: 30 | Q9: 29 | R9: 30 | S9: 35 | T9: 49 | U9: 61 | V9: 26 | W9: 29 | X9: 32 | Y9: 35 | Z9: 36 | AA9: =SUM(O9:Z9) -> 422
A10: NT10006 | B10: Edge 244 5G 128GB | C10: 53 | D10: 49 | E10: 46 | F10: 66 | G10: 71 | H10: 79 | I10: 100 | J10: 49 | K10: 52 | L10: 55 | M10: 66 | N10: 63 | O10: 59 | P10: 63 | Q10: 60 | R10: 60 | S10: 66 | T10: 96 | U10: 107 | V10: 35 | W10: 57 | X10: 51 | Y10: 63 | Z10: 77 | AA10: =SUM(O10:Z10) -> 794
A11: NT10007 | B11: Pulse 667 Dual SIM | C11: 33 | D11: 31 | E11: 21 | F11: 27 | G11: 30 | H11: 45 | I11: 60 | J11: 24 | K11: 23 | L11: 30 | M11: 30 | N11: 30 | O11: 31 | P11: 28 | Q11: 31 | R11: 31 | S11: 34 | T11: 44 | U11: 69 | V11: 26 | W11: 22 | X11: 31 | Y11: 36 | Z11: 30 | AA11: =SUM(O11:Z11) -> 413
A12: NT10008 | B12: Edge 637 5G 128GB | C12: 117 | D12: 116 | E12: 98 | F12: 127 | G12: 145 | H12: 195 | I12: 240 | J12: 99 | K12: 99 | L12: 122 | M12: 120 | N12: 140 | O12: 87 | P12: 122 | Q12: 106 | R12: 114 | S12: 158 | T12: 208 | U12: 254 | V12: 86 | W12: 94 | X12: 120 | Y12: 136 | Z12: 144 | AA12: =SUM(O12:Z12) -> 1629
A13: NT10009 | B13: Nova X689 128GB | C13: 41 | D13: 42 | E13: 40 | F13: 40 | G13: 44 | H13: 64 | I13: 79 | J13: 31 | K13: 33 | L13: 37 | M13: 41 | N13: 40 | O13: 38 | P13: 45 | Q13: 42 | R13: 49 | S13: 58 | T13: 63 | U13: 82 | V13: 32 | W13: 43 | X13: 43 | Y13: 45 | Z13: 53 | AA13: =SUM(O13:Z13) -> 593
A14: NT10010 | B14: Nova X834 128GB | C14: 202 | D14: 193 | E14: 178 | F14: 188 | G14: 212 | H14: 301 | I14: 371 | J14: 168 | K14: 178 | L14: 158 | M14: 189 | N14: 211 | O14: 199 | P14: 220 | Q14: 213 | R14: 192 | S14: 220 | T14: 296 | U14: 435 | V14: 164 | W14: 177 | X14: 227 | Y14: 198 | Z14: 217 | AA14: =SUM(O14:Z14) -> 2758
A15: NT10011 | B15: Edge 790 5G 128GB | C15: 77 | D15: 86 | E15: 83 | F15: 77 | G15: 88 | H15: 88 | I15: 134 | J15: 61 | K15: 65 | L15: 83 | M15: 83 | N15: 84 | O15: 78 | P15: 98 | Q15: 71 | R15: 71 | S15: 84 | T15: 122 | U15: 172 | V15: 63 | W15: 75 | X15: 85 | Y15: 84 | Z15: 91 | AA15: =SUM(O15:Z15) -> 1094
A16: NT10012 | B16: Pulse 918 Dual SIM | C16: 7 | D16: 9 | E16: 8 | F16: 8 | G16: 9 | H16: 11 | I16: 16 | J16: 6 | K16: 8 | L16: 8 | M16: 10 | N16: 10 | O16: 8 | P16: 8 | Q16: 10 | R16: 10 | S16: 11 | T16: 14 | U16: 16 | V16: 6 | W16: 8 | X16: 8 | Y16: 11 | Z16: 11 | AA16: =SUM(O16:Z16) -> 121
... A504: NT10500 | B504: Phone Case Clear V670 | C504: 223 | D504: 234 | E504: 209 | F504: 243 | G504: 238 | H504: 237 | I504: 211 | J504: 232 | K504: 262 | L504: 256 | M504: 236 | N504: 235 | O504: 257 | P504: 255 | Q504: 267 | R504: 231 | S504: 250 | T504: 249 | U504: 221 | V504: 233 | W504: 251 | X504: 225 | Y504: 254 | Z504: 269 | AA504: =SUM(O504:Z504) -> 2962
B505: TOTAL MONTHLY DEMAND | C505: =SUM(C5:C504) -> 65396 | D505: =SUM(D5:D504) -> 63137 | E505: =SUM(E5:E504) -> 60661 | F505: =SUM(F5:F504) -> 62809 | G505: =SUM(G5:G504) -> 68866 | H505: =SUM(H5:H504) -> 81077 | I505: =SUM(I5:I504) -> 91895 | J505: =SUM(J5:J504) -> 56009 | ... Z505: =SUM(Z5:Z504) -> 71104
A527: FORMULA REFERENCE
A528: Annual Last 12 = SUM of Jun 25 through May 26.
A529: The totals row feeds the demand trend chart. Q4 peaks (Nov, Dec) and the Jan dip are visible: classic consumer electronics seasonality.

Sheet 3. Demand Forecast
A1: DEMAND FORECAST | METHOD MATCHED TO PATTERN
A2: Seasonal SKUs use Seasonal Naive, stable SKUs use Moving Average. MAPE backtested over the last 6 months.
A4: SKU | B4: Product Name | C4: Category | D4: Seasonal | E4: Method | F4: Avg Monthly | G4: Std Dev | H4: CV | I4: YoY Growth | J4: Forecast Jun 26 | K4: MAPE | L4: Err Dec | M4: Err Jan | N4: Err Feb | O4: Err Mar | P4: Err Apr | Q4: Err May
A5: ='2. Demand History'!A5 -> NT10001 | B5: ='2. Demand History'!B5 -> Nova X427 128GB | C5: ='1. Master Data'!C5 -> Smartphones | D5: Yes | E5: =IF(D5="Yes","Seasonal Naive","Moving Avg 3") -> Seasonal Naive | F5: =ROUND(AVERAGE('2. Demand History'!O5:Z5),1) -> 95.1 | G5: =ROUND(STDEV('2. Demand History'!O5:Z5),1) -> 32.2 | H5: =IF(F5=0,0,ROUND(G5/F5,2)) -> 0.34 | I5: =ROUND(SUM('2. Demand History'!O5:Z5)/MAX(SUM('2. Demand History'!C5:N5),1),2) -> 1.04 | J5: =IF(D5="Yes",ROUND('2. Demand History'!O5*I5,0),ROUND(AVERAGE('2. Demand History'!X5:Z5),0)) -> 103 | K5: =ROUND(AVERAGE(L5:Q5),3) -> 0.089 | L5: =ROUND(ABS('2. Demand History'!U5-IF($D5="Yes",'2. Demand History'!I5,AVERAGE('2. Demand History'!R5:T5)))/MAX('2. Demand History'!U5,1),3) -> 0.012 | M5: =ROUND(ABS('2. Demand History'!V5-IF($D5="Yes",'2. Demand History'!J5,AVERAGE('2. Demand History'!S5:U5)))/MAX('2. Demand History'!V5,1),3) -> 0.067 | N5: =ROUND(ABS('2. Demand History'!W5-IF($D5="Yes",'2. Demand History'!K5,AVERAGE('2. Demand History'!T5:V5)))/MAX('2. Demand History'!W5,1),3) -> 0.23 | O5: =ROUND(ABS('2. Demand History'!X5-IF($D5="Yes",'2. Demand History'!L5,AVERAGE('2. Demand History'!U5:W5)))/MAX('2. Demand History'!X5,1),3) -> 0 | P5: =ROUND(ABS('2. Demand History'!Y5-IF($D5="Yes",'2. Demand History'!M5,AVERAGE('2. Demand History'!V5:X5)))/MAX('2. Demand History'!Y5,1),3) -> 0.112 | Q5: =ROUND(ABS('2. Demand History'!Z5-IF($D5="Yes",'2. Demand History'!N5,AVERAGE('2. Demand History'!W5:Y5)))/MAX('2. Demand History'!Z5,1),3) -> 0.114
A6: ='2. Demand History'!A6 -> NT10002 | B6: ='2. Demand History'!B6 -> Pulse 962 Dual SIM | C6: ='1. Master Data'!C6 -> Smartphones | D6: Yes | E6: =IF(D6="Yes","Seasonal Naive","Moving Avg 3") -> Seasonal Naive | F6: =ROUND(AVERAGE('2. Demand History'!O6:Z6),1) -> 52.8 | G6: =ROUND(STDEV('2. Demand History'!O6:Z6),1) -> 15.8 | H6: =IF(F6=0,0,ROUND(G6/F6,2)) -> 0.3 | I6: =ROUND(SUM('2. Demand History'!O6:Z6)/MAX(SUM('2. Demand History'!C6:N6),1),2) -> 1.01 | J6: =IF(D6="Yes",ROUND('2. Demand History'!O6*I6,0),ROUND(AVERAGE('2. Demand History'!X6:Z6),0)) -> 42 | K6: =ROUND(AVERAGE(L6:Q6),3) -> 0.125 | L6: =ROUND(ABS('2. Demand History'!U6-IF($D6="Yes",'2. Demand History'!I6,AVERAGE('2. Demand History'!R6:T6)))/MAX('2. Demand History'!U6,1),3) -> 0.034 | M6: =ROUND(ABS('2. Demand History'!V6-IF($D6="Yes",'2. Demand History'!J6,AVERAGE('2. Demand History'!S6:U6)))/MAX('2. Demand History'!V6,1),3) -> 0.081 | N6: =ROUND(ABS('2. Demand History'!W6-IF($D6="Yes",'2. Demand History'!K6,AVERAGE('2. Demand History'!T6:V6)))/MAX('2. Demand History'!W6,1),3) -> 0.343 | O6: =ROUND(ABS('2. Demand History'!X6-IF($D6="Yes",'2. Demand History'!L6,AVERAGE('2. Demand History'!U6:W6)))/MAX('2. Demand History'!X6,1),3) -> 0.083 | P6: =ROUND(ABS('2. Demand History'!Y6-IF($D6="Yes",'2. Demand History'!M6,AVERAGE('2. Demand History'!V6:X6)))/MAX('2. Demand History'!Y6,1),3) -> 0.122 | Q6: =ROUND(ABS('2. Demand History'!Z6-IF($D6="Yes",'2. Demand History'!N6,AVERAGE('2. Demand History'!W6:Y6)))/MAX('2. Demand History'!Z6,1),3) -> 0.086
A7: ='2. Demand History'!A7 -> NT10003 | B7: ='2. Demand History'!B7 -> Nova Lite 936 64GB | C7: ='1. Master Data'!C7 -> Smartphones | D7: Yes | E7: =IF(D7="Yes","Seasonal Naive","Moving Avg 3") -> Seasonal Naive | F7: =ROUND(AVERAGE('2. Demand History'!O7:Z7),1) -> 120.8 | G7: =ROUND(STDEV('2. Demand History'!O7:Z7),1) -> 38 | H7: =IF(F7=0,0,ROUND(G7/F7,2)) -> 0.31 | I7: =ROUND(SUM('2. Demand History'!O7:Z7)/MAX(SUM('2. Demand History'!C7:N7),1),2) -> 1.07 | J7: =IF(D7="Yes",ROUND('2. Demand History'!O7*I7,0),ROUND(AVERAGE('2. Demand History'!X7:Z7),0)) -> 117 | K7: =ROUND(AVERAGE(L7:Q7),3) -> 0.061 | L7: =ROUND(ABS('2. Demand History'!U7-IF($D7="Yes",'2. Demand History'!I7,AVERAGE('2. Demand History'!R7:T7)))/MAX('2. Demand History'!U7,1),3) -> 0.051 | M7: =ROUND(ABS('2. Demand History'!V7-IF($D7="Yes",'2. Demand History'!J7,AVERAGE('2. Demand History'!S7:U7)))/MAX('2. Demand History'!V7,1),3) -> 0.057 | N7: =ROUND(ABS('2. Demand History'!W7-IF($D7="Yes",'2. Demand History'!K7,AVERAGE('2. Demand History'!T7:V7)))/MAX('2. Demand History'!W7,1),3) -> 0.137 | O7: =ROUND(ABS('2. Demand History'!X7-IF($D7="Yes",'2. Demand History'!L7,AVERAGE('2. Demand History'!U7:W7)))/MAX('2. Demand History'!X7,1),3) -> 0.033 | P7: =ROUND(ABS('2. Demand History'!Y7-IF($D7="Yes",'2. Demand History'!M7,AVERAGE('2. Demand History'!V7:X7)))/MAX('2. Demand History'!Y7,1),3) -> 0 | Q7: =ROUND(ABS('2. Demand History'!Z7-IF($D7="Yes",'2. Demand History'!N7,AVERAGE('2. Demand History'!W7:Y7)))/MAX('2. Demand History'!Z7,1),3) -> 0.09
A8: ='2. Demand History'!A8 -> NT10004 | B8: ='2. Demand History'!B8 -> Nova Lite 315 64GB | C8: ='1. Master Data'!C8 -> Smartphones | D8: Yes | E8: =IF(D8="Yes","Seasonal Naive","Moving Avg 3") -> Seasonal Naive | F8: =ROUND(AVERAGE('2. Demand History'!O8:Z8),1) -> 67 | G8: =ROUND(STDEV('2. Demand History'!O8:Z8),1) -> 24.6 | H8: =IF(F8=0,0,ROUND(G8/F8,2)) -> 0.37 | I8: =ROUND(SUM('2. Demand History'!O8:Z8)/MAX(SUM('2. Demand History'!C8:N8),1),2) -> 1.07 | J8: =IF(D8="Yes",ROUND('2. Demand History'!O8*I8,0),ROUND(AVERAGE('2. Demand History'!X8:Z8),0)) -> 65 | K8: =ROUND(AVERAGE(L8:Q8),3) -> 0.178 | L8: =ROUND(ABS('2. Demand History'!U8-IF($D8="Yes",'2. Demand History'!I8,AVERAGE('2. Demand History'!R8:T8)))/MAX('2. Demand History'!U8,1),3) -> 0.258 | M8: =ROUND(ABS('2. Demand History'!V8-IF($D8="Yes",'2. Demand History'!J8,AVERAGE('2. Demand History'!S8:U8)))/MAX('2. Demand History'!V8,1),3) -> 0.216 | N8: =ROUND(ABS('2. Demand History'!W8-IF($D8="Yes",'2. Demand History'!K8,AVERAGE('2. Demand History'!T8:V8)))/MAX('2. Demand History'!W8,1),3) -> 0.167 | O8: =ROUND(ABS('2. Demand History'!X8-IF($D8="Yes",'2. Demand History'!L8,AVERAGE('2. Demand History'!U8:W8)))/MAX('2. Demand History'!X8,1),3) -> 0.145 | P8: =ROUND(ABS('2. Demand History'!Y8-IF($D8="Yes",'2. Demand History'!M8,AVERAGE('2. Demand History'!V8:X8)))/MAX('2. Demand History'!Y8,1),3) -> 0.264 | Q8: =ROUND(ABS('2. Demand History'!Z8-IF($D8="Yes",'2. Demand History'!N8,AVERAGE('2. Demand History'!W8:Y8)))/MAX('2. Demand History'!Z8,1),3) -> 0.015
A9: ='2. Demand History'!A9 -> NT10005 | B9: ='2. Demand History'!B9 -> Pulse 753 Dual SIM | C9: ='1. Master Data'!C9 -> Smartphones | D9: Yes | E9: =IF(D9="Yes","Seasonal Naive","Moving Avg 3") -> Seasonal Naive | F9: =ROUND(AVERAGE('2. Demand History'!O9:Z9),1) -> 35.2 | G9: =ROUND(STDEV('2. Demand History'!O9:Z9),1) -> 10 | H9: =IF(F9=0,0,ROUND(G9/F9,2)) -> 0.28 | I9: =ROUND(SUM('2. Demand History'!O9:Z9)/MAX(SUM('2. Demand History'!C9:N9),1),2) -> 1.07 | J9: =IF(D9="Yes",ROUND('2. Demand History'!O9*I9,0),ROUND(AVERAGE('2. Demand History'!X9:Z9),0)) -> 32 | K9: =ROUND(AVERAGE(L9:Q9),3) -> 0.117 | L9: =ROUND(ABS('2. Demand History'!U9-IF($D9="Yes",'2. Demand History'!I9,AVERAGE('2. Demand History'!R9:T9)))/MAX('2. Demand History'!U9,1),3) -> 0.033 | M9: =ROUND(ABS('2. Demand History'!V9-IF($D9="Yes",'2. Demand History'!J9,AVERAGE('2. Demand History'!S9:U9)))/MAX('2. Demand History'!V9,1),3) -> 0.154 | N9: =ROUND(ABS('2. Demand History'!W9-IF($D9="Yes",'2. Demand History'!K9,AVERAGE('2. Demand History'!T9:V9)))/MAX('2. Demand History'!W9,1),3) -> 0.103 | O9: =ROUND(ABS('2. Demand History'!X9-IF($D9="Yes",'2. Demand History'!L9,AVERAGE('2. Demand History'!U9:W9)))/MAX('2. Demand History'!X9,1),3) -> 0.188 | P9: =ROUND(ABS('2. Demand History'!Y9-IF($D9="Yes",'2. Demand History'!M9,AVERAGE('2. Demand History'!V9:X9)))/MAX('2. Demand History'!Y9,1),3) -> 0.114 | Q9: =ROUND(ABS('2. Demand History'!Z9-IF($D9="Yes",'2. Demand History'!N9,AVERAGE('2. Demand History'!W9:Y9)))/MAX('2. Demand History'!Z9,1),3) -> 0.111
A10: ='2. Demand History'!A10 -> NT10006 | B10: ='2. Demand History'!B10 -> Edge 244 5G 128GB | C10: ='1. Master Data'!C10 -> Smartphones | D10: Yes | E10: =IF(D10="Yes","Seasonal Naive","Moving Avg 3") -> Seasonal Naive | F10: =ROUND(AVERAGE('2. Demand History'!O10:Z10),1) -> 66.2 | G10: =ROUND(STDEV('2. Demand History'!O10:Z10),1) -> 19.3 | H10: =IF(F10=0,0,ROUND(G10/F10,2)) -> 0.29 | I10: =ROUND(SUM('2. Demand History'!O10:Z10)/MAX(SUM('2. Demand History'!C10:N10),1),2) -> 1.06 | J10: =IF(D10="Yes",ROUND('2. Demand History'!O10*I10,0),ROUND(AVERAGE('2. Demand History'!X10:Z10),0)) -> 63 | K10: =ROUND(AVERAGE(L10:Q10),3) -> 0.144 | L10: =ROUND(ABS('2. Demand History'!U10-IF($D10="Yes",'2. Demand History'!I10,AVERAGE('2. Demand History'!R10:T10)))/MAX('2. Demand History'!U10,1),3) -> 0.065 | M10: =ROUND(ABS('2. Demand History'!V10-IF($D10="Yes",'2. Demand History'!J10,AVERAGE('2. Demand History'!S10:U10)))/MAX('2. Demand History'!V10,1),3) -> 0.4 | N10: =ROUND(ABS('2. Demand History'!W10-IF($D10="Yes",'2. Demand History'!K10,AVERAGE('2. Demand History'!T10:V10)))/MAX('2. Demand History'!W10,1),3) -> 0.088 | O10: =ROUND(ABS('2. Demand History'!X10-IF($D10="Yes",'2. Demand History'!L10,AVERAGE('2. Demand History'!U10:W10)))/MAX('2. Demand History'!X10,1),3) -> 0.078 | P10: =ROUND(ABS('2. Demand History'!Y10-IF($D10="Yes",'2. Demand History'!M10,AVERAGE('2. Demand History'!V10:X10)))/MAX('2. Demand History'!Y10,1),3) -> 0.048 | Q10: =ROUND(ABS('2. Demand History'!Z10-IF($D10="Yes",'2. Demand History'!N10,AVERAGE('2. Demand History'!W10:Y10)))/MAX('2. Demand History'!Z10,1),3) -> 0.182
A11: ='2. Demand History'!A11 -> NT10007 | B11: ='2. Demand History'!B11 -> Pulse 667 Dual SIM | C11: ='1. Master Data'!C11 -> Smartphones | D11: Yes | E11: =IF(D11="Yes","Seasonal Naive","Moving Avg 3") -> Seasonal Naive | F11: =ROUND(AVERAGE('2. Demand History'!O11:Z11),1) -> 34.4 | G11: =ROUND(STDEV('2. Demand History'!O11:Z11),1) -> 12.1 | H11: =IF(F11=0,0,ROUND(G11/F11,2)) -> 0.35 | I11: =ROUND(SUM('2. Demand History'!O11:Z11)/MAX(SUM('2. Demand History'!C11:N11),1),2) -> 1.08 | J11: =IF(D11="Yes",ROUND('2. Demand History'!O11*I11,0),ROUND(AVERAGE('2. Demand History'!X11:Z11),0)) -> 33 | K11: =ROUND(AVERAGE(L11:Q11),3) -> 0.075 | L11: =ROUND(ABS('2. Demand History'!U11-IF($D11="Yes",'2. Demand History'!I11,AVERAGE('2. Demand History'!R11:T11)))/MAX('2. Demand History'!U11,1),3) -> 0.13 | M11: =ROUND(ABS('2. Demand History'!V11-IF($D11="Yes",'2. Demand History'!J11,AVERAGE('2. Demand History'!S11:U11)))/MAX('2. Demand History'!V11,1),3) -> 0.077 | N11: =ROUND(ABS('2. Demand History'!W11-IF($D11="Yes",'2. Demand History'!K11,AVERAGE('2. Demand History'!T11:V11)))/MAX('2. Demand History'!W11,1),3) -> 0.045 | O11: =ROUND(ABS('2. Demand History'!X11-IF($D11="Yes",'2. Demand History'!L11,AVERAGE('2. Demand History'!U11:W11)))/MAX('2. Demand History'!X11,1),3) -> 0.032 | P11: =ROUND(ABS('2. Demand History'!Y11-IF($D11="Yes",'2. Demand History'!M11,AVERAGE('2. Demand History'!V11:X11)))/MAX('2. Demand History'!Y11,1),3) -> 0.167 | Q11: =ROUND(ABS('2. Demand History'!Z11-IF($D11="Yes",'2. Demand History'!N11,AVERAGE('2. Demand History'!W11:Y11)))/MAX('2. Demand History'!Z11,1),3) -> 0
A12: ='2. Demand History'!A12 -> NT10008 | B12: ='2. Demand History'!B12 -> Edge 637 5G 128GB | C12: ='1. Master Data'!C12 -> Smartphones | D12: Yes | E12: =IF(D12="Yes","Seasonal Naive","Moving Avg 3") -> Seasonal Naive | F12: =ROUND(AVERAGE('2. Demand History'!O12:Z12),1) -> 135.8 | G12: =ROUND(STDEV('2. Demand History'!O12:Z12),1) -> 50.6 | H12: =IF(F12=0,0,ROUND(G12/F12,2)) -> 0.37 | I12: =ROUND(SUM('2. Demand History'!O12:Z12)/MAX(SUM('2. Demand History'!C12:N12),1),2) -> 1.01 | J12: =IF(D12="Yes",ROUND('2. Demand History'!O12*I12,0),ROUND(AVERAGE('2. Demand History'!X12:Z12),0)) -> 88 | K12: =ROUND(AVERAGE(L12:Q12),3) -> 0.07 | L12: =ROUND(ABS('2. Demand History'!U12-IF($D12="Yes",'2. Demand History'!I12,AVERAGE('2. Demand History'!R12:T12)))/MAX('2. Demand History'!U12,1),3) -> 0.055 | M12: =ROUND(ABS('2. Demand History'!V12-IF($D12="Yes",'2. Demand History'!J12,AVERAGE('2. Demand History'!S12:U12)))/MAX('2. Demand History'!V12,1),3) -> 0.151 | N12: =ROUND(ABS('2. Demand History'!W12-IF($D12="Yes",'2. Demand History'!K12,AVERAGE('2. Demand History'!T12:V12)))/MAX('2. Demand History'!W12,1),3) -> 0.053 | O12: =ROUND(ABS('2. Demand History'!X12-IF($D12="Yes",'2. Demand History'!L12,AVERAGE('2. Demand History'!U12:W12)))/MAX('2. Demand History'!X12,1),3) -> 0.017 | P12: =ROUND(ABS('2. Demand History'!Y12-IF($D12="Yes",'2. Demand History'!M12,AVERAGE('2. Demand History'!V12:X12)))/MAX('2. Demand History'!Y12,1),3) -> 0.118 | Q12: =ROUND(ABS('2. Demand History'!Z12-IF($D12="Yes",'2. Demand History'!N12,AVERAGE('2. Demand History'!W12:Y12)))/MAX('2. Demand History'!Z12,1),3) -> 0.028
A13: ='2. Demand History'!A13 -> NT10009 | B13: ='2. Demand History'!B13 -> Nova X689 128GB | C13: ='1. Master Data'!C13 -> Smartphones | D13: Yes | E13: =IF(D13="Yes","Seasonal Naive","Moving Avg 3") -> Seasonal Naive | F13: =ROUND(AVERAGE('2. Demand History'!O13:Z13),1) -> 49.4 | G13: =ROUND(STDEV('2. Demand History'!O13:Z13),1) -> 13.3 | H13: =IF(F13=0,0,ROUND(G13/F13,2)) -> 0.27 | I13: =ROUND(SUM('2. Demand History'!O13:Z13)/MAX(SUM('2. Demand History'!C13:N13),1),2) -> 1.11 | J13: =IF(D13="Yes",ROUND('2. Demand History'!O13*I13,0),ROUND(AVERAGE('2. Demand History'!X13:Z13),0)) -> 42 | K13: =ROUND(AVERAGE(L13:Q13),3) -> 0.129 | L13: =ROUND(ABS('2. Demand History'!U13-IF($D13="Yes",'2. Demand History'!I13,AVERAGE('2. Demand History'!R13:T13)))/MAX('2. Demand History'!U13,1),3) -> 0.037 | M13: =ROUND(ABS('2. Demand History'!V13-IF($D13="Yes",'2. Demand History'!J13,AVERAGE('2. Demand History'!S13:U13)))/MAX('2. Demand History'!V13,1),3) -> 0.031 | N13: =ROUND(ABS('2. Demand History'!W13-IF($D13="Yes",'2. Demand History'!K13,AVERAGE('2. Demand History'!T13:V13)))/MAX('2. Demand History'!W13,1),3) -> 0.233 | O13: =ROUND(ABS('2. Demand History'!X13-IF($D13="Yes",'2. Demand History'!L13,AVERAGE('2. Demand History'!U13:W13)))/MAX('2. Demand History'!X13,1),3) -> 0.14 | P13: =ROUND(ABS('2. Demand History'!Y13-IF($D13="Yes",'2. Demand History'!M13,AVERAGE('2. Demand History'!V13:X13)))/MAX('2. Demand History'!Y13,1),3) -> 0.089 | Q13: =ROUND(ABS('2. Demand History'!Z13-IF($D13="Yes",'2. Demand History'!N13,AVERAGE('2. Demand History'!W13:Y13)))/MAX('2. Demand History'!Z13,1),3) -> 0.245
A14: ='2. Demand History'!A14 -> NT10010 | B14: ='2. Demand History'!B14 -> Nova X834 128GB | C14: ='1. Master Data'!C14 -> Smartphones | D14: Yes | E14: =IF(D14="Yes","Seasonal Naive","Moving Avg 3") -> Seasonal Naive | F14: =ROUND(AVERAGE('2. Demand History'!O14:Z14),1) -> 229.8 | G14: =ROUND(STDEV('2. Demand History'!O14:Z14),1) -> 72.4 | H14: =IF(F14=0,0,ROUND(G14/F14,2)) -> 0.32 | I14: =ROUND(SUM('2. Demand History'!O14:Z14)/MAX(SUM('2. Demand History'!C14:N14),1),2) -> 1.08 | J14: =IF(D14="Yes",ROUND('2. Demand History'!O14*I14,0),ROUND(AVERAGE('2. Demand History'!X14:Z14),0)) -> 215 | K14: =ROUND(AVERAGE(L14:Q14),3) -> 0.092 | L14: =ROUND(ABS('2. Demand History'!U14-IF($D14="Yes",'2. Demand History'!I14,AVERAGE('2. Demand History'!R14:T14)))/MAX('2. Demand History'!U14,1),3) -> 0.147 | M14: =ROUND(ABS('2. Demand History'!V14-IF($D14="Yes",'2. Demand History'!J14,AVERAGE('2. Demand History'!S14:U14)))/MAX('2. Demand History'!V14,1),3) -> 0.024 | N14: =ROUND(ABS('2. Demand History'!W14-IF($D14="Yes",'2. Demand History'!K14,AVERAGE('2. Demand History'!T14:V14)))/MAX('2. Demand History'!W14,1),3) -> 0.006 | O14: =ROUND(ABS('2. Demand History'!X14-IF($D14="Yes",'2. Demand History'!L14,AVERAGE('2. Demand History'!U14:W14)))/MAX('2. Demand History'!X14,1),3) -> 0.304 | P14: =ROUND(ABS('2. Demand History'!Y14-IF($D14="Yes",'2. Demand History'!M14,AVERAGE('2. Demand History'!V14:X14)))/MAX('2. Demand History'!Y14,1),3) -> 0.045 | Q14: =ROUND(ABS('2. Demand History'!Z14-IF($D14="Yes",'2. Demand History'!N14,AVERAGE('2. Demand History'!W14:Y14)))/MAX('2. Demand History'!Z14,1),3) -> 0.028
A15: ='2. Demand History'!A15 -> NT10011 | B15: ='2. Demand History'!B15 -> Edge 790 5G 128GB | C15: ='1. Master Data'!C15 -> Smartphones | D15: Yes | E15: =IF(D15="Yes","Seasonal Naive","Moving Avg 3") -> Seasonal Naive | F15: =ROUND(AVERAGE('2. Demand History'!O15:Z15),1) -> 91.2 | G15: =ROUND(STDEV('2. Demand History'!O15:Z15),1) -> 29.7 | H15: =IF(F15=0,0,ROUND(G15/F15,2)) -> 0.33 | I15: =ROUND(SUM('2. Demand History'!O15:Z15)/MAX(SUM('2. Demand History'!C15:N15),1),2) -> 1.08 | J15: =IF(D15="Yes",ROUND('2. Demand History'!O15*I15,0),ROUND(AVERAGE('2. Demand History'!X15:Z15),0)) -> 84 | K15: =ROUND(AVERAGE(L15:Q15),3) -> 0.083 | L15: =ROUND(ABS('2. Demand History'!U15-IF($D15="Yes",'2. Demand History'!I15,AVERAGE('2. Demand History'!R15:T15)))/MAX('2. Demand History'!U15,1),3) -> 0.221 | M15: =ROUND(ABS('2. Demand History'!V15-IF($D15="Yes",'2. Demand History'!J15,AVERAGE('2. Demand History'!S15:U15)))/MAX('2. Demand History'!V15,1),3) -> 0.032 | N15: =ROUND(ABS('2. Demand History'!W15-IF($D15="Yes",'2. Demand History'!K15,AVERAGE('2. Demand History'!T15:V15)))/MAX('2. Demand History'!W15,1),3) -> 0.133 | O15: =ROUND(ABS('2. Demand History'!X15-IF($D15="Yes",'2. Demand History'!L15,AVERAGE('2. Demand History'!U15:W15)))/MAX('2. Demand History'!X15,1),3) -> 0.024 | P15: =ROUND(ABS('2. Demand History'!Y15-IF($D15="Yes",'2. Demand History'!M15,AVERAGE('2. Demand History'!V15:X15)))/MAX('2. Demand History'!Y15,1),3) -> 0.012 | Q15: =ROUND(ABS('2. Demand History'!Z15-IF($D15="Yes",'2. Demand History'!N15,AVERAGE('2. Demand History'!W15:Y15)))/MAX('2. Demand History'!Z15,1),3) -> 0.077
A16: ='2. Demand History'!A16 -> NT10012 | B16: ='2. Demand History'!B16 -> Pulse 918 Dual SIM | C16: ='1. Master Data'!C16 -> Smartphones | D16: Yes | E16: =IF(D16="Yes","Seasonal Naive","Moving Avg 3") -> Seasonal Naive | F16: =ROUND(AVERAGE('2. Demand History'!O16:Z16),1) -> 10.1 | G16: =ROUND(STDEV('2. Demand History'!O16:Z16),1) -> 2.8 | H16: =IF(F16=0,0,ROUND(G16/F16,2)) -> 0.28 | I16: =ROUND(SUM('2. Demand History'!O16:Z16)/MAX(SUM('2. Demand History'!C16:N16),1),2) -> 1.1 | J16: =IF(D16="Yes",ROUND('2. Demand History'!O16*I16,0),ROUND(AVERAGE('2. Demand History'!X16:Z16),0)) -> 9 | K16: =ROUND(AVERAGE(L16:Q16),3) -> 0.03 | L16: =ROUND(ABS('2. Demand History'!U16-IF($D16="Yes",'2. Demand History'!I16,AVERAGE('2. Demand History'!R16:T16)))/MAX('2. Demand History'!U16,1),3) -> 0 | M16: =ROUND(ABS('2. Demand History'!V16-IF($D16="Yes",'2. Demand History'!J16,AVERAGE('2. Demand History'!S16:U16)))/MAX('2. Demand History'!V16,1),3) -> 0 | N16: =ROUND(ABS('2. Demand History'!W16-IF($D16="Yes",'2. Demand History'!K16,AVERAGE('2. Demand History'!T16:V16)))/MAX('2. Demand History'!W16,1),3) -> 0 | O16: =ROUND(ABS('2. Demand History'!X16-IF($D16="Yes",'2. Demand History'!L16,AVERAGE('2. Demand History'!U16:W16)))/MAX('2. Demand History'!X16,1),3) -> 0 | P16: =ROUND(ABS('2. Demand History'!Y16-IF($D16="Yes",'2. Demand History'!M16,AVERAGE('2. Demand History'!V16:X16)))/MAX('2. Demand History'!Y16,1),3) -> 0.091 | Q16: =ROUND(ABS('2. Demand History'!Z16-IF($D16="Yes",'2. Demand History'!N16,AVERAGE('2. Demand History'!W16:Y16)))/MAX('2. Demand History'!Z16,1),3) -> 0.091
... A504: ='2. Demand History'!A504 -> NT10500 | B504: ='2. Demand History'!B504 -> Phone Case Clear V670 | C504: ='1. Master Data'!C504 -> Accessories | D504: No | E504: =IF(D504="Yes","Seasonal Naive","Moving Avg 3") -> Moving Avg 3 | F504: =ROUND(AVERAGE('2. Demand History'!O504:Z504),1) -> 246.8 | G504: =ROUND(STDEV('2. Demand History'!O504:Z504),1) -> 15.8 | H504: =IF(F504=0,0,ROUND(G504/F504,2)) -> 0.06 | I504: =ROUND(SUM('2. Demand History'!O504:Z504)/MAX(SUM('2. Demand History'!C504:N504),1),2) -> 1.05 | J504: =IF(D504="Yes",ROUND('2. Demand History'!O504*I504,0),ROUND(AVERAGE('2. Demand History'!X504:Z504),0)) -> 249 | K504: =ROUND(AVERAGE(L504:Q504),3) -> 0.068 | L504: =ROUND(ABS('2. Demand History'!U504-IF($D504="Yes",'2. Demand History'!I504,AVERAGE('2. Demand History'!R504:T504)))/MAX('2. Demand History'!U504,1),3) -> 0.101 | M504: =ROUND(ABS('2. Demand History'!V504-IF($D504="Yes",'2. Demand History'!J504,AVERAGE('2. Demand History'!S504:U504)))/MAX('2. Demand History'!V504,1),3) -> 0.03 | N504: =ROUND(ABS('2. Demand History'!W504-IF($D504="Yes",'2. Demand History'!K504,AVERAGE('2. Demand History'!T504:V504)))/MAX('2. Demand History'!W504,1),3) -> 0.066 | O504: =ROUND(ABS('2. Demand History'!X504-IF($D504="Yes",'2. Demand History'!L504,AVERAGE('2. Demand History'!U504:W504)))/MAX('2. Demand History'!X504,1),3) -> 0.044 | P504: =ROUND(ABS('2. Demand History'!Y504-IF($D504="Yes",'2. Demand History'!M504,AVERAGE('2. Demand History'!V504:X504)))/MAX('2. Demand History'!Y504,1),3) -> 0.07 | Q504: =ROUND(ABS('2. Demand History'!Z504-IF($D504="Yes",'2. Demand History'!N504,AVERAGE('2. Demand History'!W504:Y504)))/MAX('2. Demand History'!Z504,1),3) -> 0.095
A506: FORMULA REFERENCE
A507: Method: seasonal SKUs forecast with Seasonal Naive (same month last year times YoY growth). Stable SKUs use a 3 month Moving Average.
A508: Forecast Jun 26 = IF seasonal, Jun 25 demand x YoY growth, ELSE average of Mar to May 26.
A509: MAPE = average of the 6 monthly backtest errors. Err month = ABS(actual minus method forecast) / actual.
A510: Read: green under 10 percent is strong, amber 10 to 25 is workable, red over 25 means the part is erratic. Erratic Z items are managed with a Min Max policy instead of a forecast (see Replenishment).

Sheet 4. ABC XYZ Analysis
A1: ABC XYZ ANALYSIS
A2: ABC ranks value concentration. XYZ measures demand predictability. Together they set the stocking strategy.
A4: SKU | B4: Product Name | C4: Category | D4: DC | E4: Unit Cost | F4: Annual Usage | G4: ACV | H4: Rank | I4: Cum ACV | J4: Cum % | K4: ABC | L4: CV | M4: XYZ | N4: Class
A5: ='1. Master Data'!A76 -> NT10072 | B5: ='1. Master Data'!B76 -> CreatorPro 629 i9 16in | C5: ='1. Master Data'!C76 -> Laptops | D5: ='1. Master Data'!D76 -> East DC | E5: ='1. Master Data'!F76 -> 1121 | F5: ='2. Demand History'!AA76 -> 3089 | G5: =E5*F5 -> 3462769 | H5: =RANK(G5,G$5:G$504,0) -> 1 | I5: =SUMPRODUCT((H$5:H$504<=H5)*G$5:G$504) -> 3462769 | J5: =I5/SUM(G$5:G$504) -> 0.020943102 | K5: =IF(J5<=0.8,"A",IF(J5<=0.95,"B","C")) -> A | L5: ='3. Demand Forecast'!H76 -> 0.31 | M5: =IF(L5<=0.25,"X",IF(L5<=0.6,"Y","Z")) -> Y | N5: =K5&M5 -> AY
A6: ='1. Master Data'!A108 -> NT10104 | B6: ='1. Master Data'!B108 -> VisionLED 501in 4K | C6: ='1. Master Data'!C108 -> TVs | D6: ='1. Master Data'!D108 -> East DC | E6: ='1. Master Data'!F108 -> 1395 | F6: ='2. Demand History'!AA108 -> 2259 | G6: =E6*F6 -> 3151305 | H6: =RANK(G6,G$5:G$504,0) -> 2 | I6: =SUMPRODUCT((H$5:H$504<=H6)*G$5:G$504) -> 6614074 | J6: =I6/SUM(G$5:G$504) -> 0.040002444 | K6: =IF(J6<=0.8,"A",IF(J6<=0.95,"B","C")) -> A | L6: ='3. Demand Forecast'!H108 -> 0.31 | M6: =IF(L6<=0.25,"X",IF(L6<=0.6,"Y","Z")) -> Y | N6: =K6&M6 -> AY
A7: ='1. Master Data'!A32 -> NT10028 | B7: ='1. Master Data'!B32 -> Nova X761 Pro 256GB | C7: ='1. Master Data'!C32 -> Smartphones | D7: ='1. Master Data'!D32 -> East DC | E7: ='1. Master Data'!F32 -> 779 | F7: ='2. Demand History'!AA32 -> 3921 | G7: =E7*F7 -> 3054459 | H7: =RANK(G7,G$5:G$504,0) -> 3 | I7: =SUMPRODUCT((H$5:H$504<=H7)*G$5:G$504) -> 9668533 | J7: =I7/SUM(G$5:G$504) -> 0.058476055 | K7: =IF(J7<=0.8,"A",IF(J7<=0.95,"B","C")) -> A | L7: ='3. Demand Forecast'!H32 -> 0.35 | M7: =IF(L7<=0.25,"X",IF(L7<=0.6,"Y","Z")) -> Y | N7: =K7&M7 -> AY
A8: ='1. Master Data'!A143 -> NT10139 | B8: ='1. Master Data'!B143 -> VisionQ 920in QLED | C8: ='1. Master Data'!C143 -> TVs | D8: ='1. Master Data'!D143 -> Central DC | E8: ='1. Master Data'!F143 -> 1097 | F8: ='2. Demand History'!AA143 -> 2627 | G8: =E8*F8 -> 2881819 | H8: =RANK(G8,G$5:G$504,0) -> 4 | I8: =SUMPRODUCT((H$5:H$504<=H8)*G$5:G$504) -> 12550352 | J8: =I8/SUM(G$5:G$504) -> 0.075905525 | K8: =IF(J8<=0.8,"A",IF(J8<=0.95,"B","C")) -> A | L8: ='3. Demand Forecast'!H143 -> 0.27 | M8: =IF(L8<=0.25,"X",IF(L8<=0.6,"Y","Z")) -> Y | N8: =K8&M8 -> AY
A9: ='1. Master Data'!A55 -> NT10051 | B9: ='1. Master Data'!B55 -> CreatorPro 982 i9 16in | C9: ='1. Master Data'!C55 -> Laptops | D9: ='1. Master Data'!D55 -> Central DC | E9: ='1. Master Data'!F55 -> 1137 | F9: ='2. Demand History'!AA55 -> 2197 | G9: =E9*F9 -> 2497989 | H9: =RANK(G9,G$5:G$504,0) -> 5 | I9: =SUMPRODUCT((H$5:H$504<=H9)*G$5:G$504) -> 15048341 | J9: =I9/SUM(G$5:G$504) -> 0.09101356 | K9: =IF(J9<=0.8,"A",IF(J9<=0.95,"B","C")) -> A | L9: ='3. Demand Forecast'!H55 -> 0.3 | M9: =IF(L9<=0.25,"X",IF(L9<=0.6,"Y","Z")) -> Y | N9: =K9&M9 -> AY
A10: ='1. Master Data'!A30 -> NT10026 | B10: ='1. Master Data'!B30 -> Edge 712 5G 128GB | C10: ='1. Master Data'!C30 -> Smartphones | D10: ='1. Master Data'!D30 -> East DC | E10: ='1. Master Data'!F30 -> 321 | F10: ='2. Demand History'!AA30 -> 6808 | G10: =E10*F10 -> 2185368 | H10: =RANK(G10,G$5:G$504,0) -> 6 | I10: =SUMPRODUCT((H$5:H$504<=H10)*G$5:G$504) -> 17233709 | J10: =I10/SUM(G$5:G$504) -> 0.10423084 | K10: =IF(J10<=0.8,"A",IF(J10<=0.95,"B","C")) -> A | L10: ='3. Demand Forecast'!H30 -> 0.31 | M10: =IF(L10<=0.25,"X",IF(L10<=0.6,"Y","Z")) -> Y | N10: =K10&M10 -> AY
A11: ='1. Master Data'!A400 -> NT10396 | B11: ='1. Master Data'!B400 -> MirrorlessM 229 | C11: ='1. Master Data'!C400 -> Cameras | D11: ='1. Master Data'!D400 -> Central DC | E11: ='1. Master Data'!F400 -> 1120 | F11: ='2. Demand History'!AA400 -> 1911 | G11: =E11*F11 -> 2140320 | H11: =RANK(G11,G$5:G$504,0) -> 7 | I11: =SUMPRODUCT((H$5:H$504<=H11)*G$5:G$504) -> 19374029 | J11: =I11/SUM(G$5:G$504) -> 0.11717566 | K11: =IF(J11<=0.8,"A",IF(J11<=0.95,"B","C")) -> A | L11: ='3. Demand Forecast'!H400 -> 0.25 | M11: =IF(L11<=0.25,"X",IF(L11<=0.6,"Y","Z")) -> X | N11: =K11&M11 -> AX
A12: ='1. Master Data'!A160 -> NT10156 | B12: ='1. Master Data'!B160 -> ClipMic 445 Wireless | C12: ='1. Master Data'!C160 -> Audio | D12: ='1. Master Data'!D160 -> West DC | E12: ='1. Master Data'!F160 -> 250 | F12: ='2. Demand History'!AA160 -> 7215 | G12: =E12*F12 -> 1803750 | H12: =RANK(G12,G$5:G$504,0) -> 8 | I12: =SUMPRODUCT((H$5:H$504<=H12)*G$5:G$504) -> 21177779 | J12: =I12/SUM(G$5:G$504) -> 0.12808489 | K12: =IF(J12<=0.8,"A",IF(J12<=0.95,"B","C")) -> A | L12: ='3. Demand Forecast'!H160 -> 0.27 | M12: =IF(L12<=0.25,"X",IF(L12<=0.6,"Y","Z")) -> Y | N12: =K12&M12 -> AY
A13: ='1. Master Data'!A39 -> NT10035 | B13: ='1. Master Data'!B39 -> Nova X683 Pro 256GB | C13: ='1. Master Data'!C39 -> Smartphones | D13: ='1. Master Data'!D39 -> East DC | E13: ='1. Master Data'!F39 -> 524 | F13: ='2. Demand History'!AA39 -> 3400 | G13: =E13*F13 -> 1781600 | H13: =RANK(G13,G$5:G$504,0) -> 9 | I13: =SUMPRODUCT((H$5:H$504<=H13)*G$5:G$504) -> 22959379 | J13: =I13/SUM(G$5:G$504) -> 0.13886015 | K13: =IF(J13<=0.8,"A",IF(J13<=0.95,"B","C")) -> A | L13: ='3. Demand Forecast'!H39 -> 0.33 | M13: =IF(L13<=0.25,"X",IF(L13<=0.6,"Y","Z")) -> Y | N13: =K13&M13 -> AY
A14: ='1. Master Data'!A336 -> NT10332 | B14: ='1. Master Data'!B336 -> HomeCam 631 1080p | C14: ='1. Master Data'!C336 -> Smart Home | D14: ='1. Master Data'!D336 -> Central DC | E14: ='1. Master Data'!F336 -> 87 | F14: ='2. Demand History'!AA336 -> 20102 | G14: =E14*F14 -> 1748874 | H14: =RANK(G14,G$5:G$504,0) -> 10 | I14: =SUMPRODUCT((H$5:H$504<=H14)*G$5:G$504) -> 24708253 | J14: =I14/SUM(G$5:G$504) -> 0.14943747 | K14: =IF(J14<=0.8,"A",IF(J14<=0.95,"B","C")) -> A | L14: ='3. Demand Forecast'!H336 -> 0.06 | M14: =IF(L14<=0.25,"X",IF(L14<=0.6,"Y","Z")) -> X | N14: =K14&M14 -> AX
A15: ='1. Master Data'!A291 -> NT10287 | B15: ='1. Master Data'!B291 -> ProMouse G661 | C15: ='1. Master Data'!C291 -> Gaming | D15: ='1. Master Data'!D291 -> Central DC | E15: ='1. Master Data'!F291 -> 190 | F15: ='2. Demand History'!AA291 -> 9156 | G15: =E15*F15 -> 1739640 | H15: =RANK(G15,G$5:G$504,0) -> 11 | I15: =SUMPRODUCT((H$5:H$504<=H15)*G$5:G$504) -> 26447893 | J15: =I15/SUM(G$5:G$504) -> 0.15995896 | K15: =IF(J15<=0.8,"A",IF(J15<=0.95,"B","C")) -> A | L15: ='3. Demand Forecast'!H291 -> 0.25 | M15: =IF(L15<=0.25,"X",IF(L15<=0.6,"Y","Z")) -> X | N15: =K15&M15 -> AX
A16: ='1. Master Data'!A70 -> NT10066 | B16: ='1. Master Data'!B70 -> UltraSlim 542 Ryzen 5 | C16: ='1. Master Data'!C70 -> Laptops | D16: ='1. Master Data'!D70 -> East DC | E16: ='1. Master Data'!F70 -> 1410 | F16: ='2. Demand History'!AA70 -> 1134 | G16: =E16*F16 -> 1598940 | H16: =RANK(G16,G$5:G$504,0) -> 12 | I16: =SUMPRODUCT((H$5:H$504<=H16)*G$5:G$504) -> 28046833 | J16: =I16/SUM(G$5:G$504) -> 0.16962947 | K16: =IF(J16<=0.8,"A",IF(J16<=0.95,"B","C")) -> A | L16: ='3. Demand Forecast'!H70 -> 0.3 | M16: =IF(L16<=0.25,"X",IF(L16<=0.6,"Y","Z")) -> Y | N16: =K16&M16 -> AY
A17: ='1. Master Data'!A103 -> NT10099 | B17: ='1. Master Data'!B103 -> WorkMate 633 i3 14in | C17: ='1. Master Data'!C103 -> Laptops | D17: ='1. Master Data'!D103 -> West DC | E17: ='1. Master Data'!F103 -> 1125 | F17: ='2. Demand History'!AA103 -> 1339 | G17: =E17*F17 -> 1506375 | H17: =RANK(G17,G$5:G$504,0) -> 13 | I17: =SUMPRODUCT((H$5:H$504<=H17)*G$5:G$504) -> 29553208 | J17: =I17/SUM(G$5:G$504) -> 0.17874015 | K17: =IF(J17<=0.8,"A",IF(J17<=0.95,"B","C")) -> A | L17: ='3. Demand Forecast'!H103 -> 0.33 | M17: =IF(L17<=0.25,"X",IF(L17<=0.6,"Y","Z")) -> Y | N17: =K17&M17 -> AY
A18: ='1. Master Data'!A129 -> NT10125 | B18: ='1. Master Data'!B129 -> VisionOLED 414in 4K | C18: ='1. Master Data'!C129 -> TVs | D18: ='1. Master Data'!D129 -> East DC | E18: ='1. Master Data'!F129 -> 1001 | F18: ='2. Demand History'!AA129 -> 1453 | G18: =E18*F18 -> 1454453 | H18: =RANK(G18,G$5:G$504,0) -> 14 | I18: =SUMPRODUCT((H$5:H$504<=H18)*G$5:G$504) -> 31007661 | J18: =I18/SUM(G$5:G$504) -> 0.18753679 | K18: =IF(J18<=0.8,"A",IF(J18<=0.95,"B","C")) -> A | L18: ='3. Demand Forecast'!H129 -> 0.29 | M18: =IF(L18<=0.25,"X",IF(L18<=0.6,"Y","Z")) -> Y | N18: =K18&M18 -> AY
A19: ='1. Master Data'!A156 -> NT10152 | B19: ='1. Master Data'!B156 -> StudioPods 426 ANC | C19: ='1. Master Data'!C156 -> Audio | D19: ='1. Master Data'!D156 -> West DC | E19: ='1. Master Data'!F156 -> 236 | F19: ='2. Demand History'!AA156 -> 6116 | G19: =E19*F19 -> 1443376 | H19: =RANK(G19,G$5:G$504,0) -> 15 | I19: =SUMPRODUCT((H$5:H$504<=H19)*G$5:G$504) -> 32451037 | J19: =I19/SUM(G$5:G$504) -> 0.19626645 | K19: =IF(J19<=0.8,"A",IF(J19<=0.95,"B","C")) -> A | L19: ='3. Demand Forecast'!H156 -> 0.27 | M19: =IF(L19<=0.25,"X",IF(L19<=0.6,"Y","Z")) -> Y | N19: =K19&M19 -> AY
A20: ='1. Master Data'!A22 -> NT10018 | B20: ='1. Master Data'!B22 -> Nova X223 Pro 256GB | C20: ='1. Master Data'!C22 -> Smartphones | D20: ='1. Master Data'!D22 -> West DC | E20: ='1. Master Data'!F22 -> 809 | F20: ='2. Demand History'!AA22 -> 1739 | G20: =E20*F20 -> 1406851 | H20: =RANK(G20,G$5:G$504,0) -> 16 | I20: =SUMPRODUCT((H$5:H$504<=H20)*G$5:G$504) -> 33857888 | J20: =I20/SUM(G$5:G$504) -> 0.20477519 | K20: =IF(J20<=0.8,"A",IF(J20<=0.95,"B","C")) -> A | L20: ='3. Demand Forecast'!H22 -> 0.28 | M20: =IF(L20<=0.25,"X",IF(L20<=0.6,"Y","Z")) -> Y | N20: =K20&M20 -> AY
A21: ='1. Master Data'!A48 -> NT10044 | B21: ='1. Master Data'!B48 -> Nova Lite 886 64GB | C21: ='1. Master Data'!C48 -> Smartphones | D21: ='1. Master Data'!D48 -> Central DC | E21: ='1. Master Data'!F48 -> 849 | F21: ='2. Demand History'!AA48 -> 1607 | G21: =E21*F21 -> 1364343 | H21: =RANK(G21,G$5:G$504,0) -> 17 | I21: =SUMPRODUCT((H$5:H$504<=H21)*G$5:G$504) -> 35222231 | J21: =I21/SUM(G$5:G$504) -> 0.21302685 | K21: =IF(J21<=0.8,"A",IF(J21<=0.95,"B","C")) -> A | L21: ='3. Demand Forecast'!H48 -> 0.37 | M21: =IF(L21<=0.25,"X",IF(L21<=0.6,"Y","Z")) -> Y | N21: =K21&M21 -> AY
A22: ='1. Master Data'!A12 -> NT10008 | B22: ='1. Master Data'!B12 -> Edge 637 5G 128GB | C22: ='1. Master Data'!C12 -> Smartphones | D22: ='1. Master Data'!D12 -> West DC | E22: ='1. Master Data'!F12 -> 827 | F22: ='2. Demand History'!AA12 -> 1629 | G22: =E22*F22 -> 1347183 | H22: =RANK(G22,G$5:G$504,0) -> 18 | I22: =SUMPRODUCT((H$5:H$504<=H22)*G$5:G$504) -> 36569414 | J22: =I22/SUM(G$5:G$504) -> 0.22117472 | K22: =IF(J22<=0.8,"A",IF(J22<=0.95,"B","C")) -> A | L22: ='3. Demand Forecast'!H12 -> 0.37 | M22: =IF(L22<=0.25,"X",IF(L22<=0.6,"Y","Z")) -> Y | N22: =K22&M22 -> AY
A23: ='1. Master Data'!A153 -> NT10149 | B23: ='1. Master Data'!B153 -> CinemaMax 755in 8K | C23: ='1. Master Data'!C153 -> TVs | D23: ='1. Master Data'!D153 -> East DC | E23: ='1. Master Data'!F153 -> 1759 | F23: ='2. Demand History'!AA153 -> 763 | G23: =E23*F23 -> 1342117 | H23: =RANK(G23,G$5:G$504,0) -> 19 | I23: =SUMPRODUCT((H$5:H$504<=H23)*G$5:G$504) -> 37911531 | J23: =I23/SUM(G$5:G$504) -> 0.22929195 | K23: =IF(J23<=0.8,"A",IF(J23<=0.95,"B","C")) -> A | L23: ='3. Demand Forecast'!H153 -> 0.27 | M23: =IF(L23<=0.25,"X",IF(L23<=0.6,"Y","Z")) -> Y | N23: =K23&M23 -> AY
A24: ='1. Master Data'!A41 -> NT10037 | B24: ='1. Master Data'!B41 -> Nova X618 128GB | C24: ='1. Master Data'!C41 -> Smartphones | D24: ='1. Master Data'!D41 -> Central DC | E24: ='1. Master Data'!F41 -> 852 | F24: ='2. Demand History'!AA41 -> 1489 | G24: =E24*F24 -> 1268628 | H24: =RANK(G24,G$5:G$504,0) -> 20 | I24: =SUMPRODUCT((H$5:H$504<=H24)*G$5:G$504) -> 39180159 | J24: =I24/SUM(G$5:G$504) -> 0.23696471 | K24: =IF(J24<=0.8,"A",IF(J24<=0.95,"B","C")) -> A | L24: ='3. Demand Forecast'!H41 -> 0.24 | M24: =IF(L24<=0.25,"X",IF(L24<=0.6,"Y","Z")) -> X | N24: =K24&M24 -> AX
A25: ='1. Master Data'!A204 -> NT10200 | B25: ='1. Master Data'!B204 -> WaveBar 886 Soundbar | C25: ='1. Master Data'!C204 -> Audio | D25: ='1. Master Data'!D204 -> East DC | E25: ='1. Master Data'!F204 -> 207 | F25: ='2. Demand History'!AA204 -> 5604 | G25: =E25*F25 -> 1160028 | H25: =RANK(G25,G$5:G$504,0) -> 21 | I25: =SUMPRODUCT((H$5:H$504<=H25)*G$5:G$504) -> 40340187 | J25: =I25/SUM(G$5:G$504) -> 0.24398065 | K25: =IF(J25<=0.8,"A",IF(J25<=0.95,"B","C")) -> A | L25: ='3. Demand Forecast'!H204 -> 0.23 | M25: =IF(L25<=0.25,"X",IF(L25<=0.6,"Y","Z")) -> X | N25: =K25&M25 -> AX
A26: ='1. Master Data'!A246 -> NT10242 | B26: ='1. Master Data'!B246 -> PulseRing 393 | C26: ='1. Master Data'!C246 -> Wearables | D26: ='1. Master Data'!D246 -> East DC | E26: ='1. Master Data'!F246 -> 103 | F26: ='2. Demand History'!AA246 -> 11197 | G26: =E26*F26 -> 1153291 | H26: =RANK(G26,G$5:G$504,0) -> 22 | I26: =SUMPRODUCT((H$5:H$504<=H26)*G$5:G$504) -> 41493478 | J26: =I26/SUM(G$5:G$504) -> 0.25095585 | K26: =IF(J26<=0.8,"A",IF(J26<=0.95,"B","C")) -> A | L26: ='3. Demand Forecast'!H246 -> 0.3 | M26: =IF(L26<=0.25,"X",IF(L26<=0.6,"Y","Z")) -> Y | N26: =K26&M26 -> AY
A27: ='1. Master Data'!A63 -> NT10059 | B27: ='1. Master Data'!B63 -> WorkMate 293 i3 14in | C27: ='1. Master Data'!C63 -> Laptops | D27: ='1. Master Data'!D63 -> West DC | E27: ='1. Master Data'!F63 -> 1383 | F27: ='2. Demand History'!AA63 -> 822 | G27: =E27*F27 -> 1136826 | H27: =RANK(G27,G$5:G$504,0) -> 23 | I27: =SUMPRODUCT((H$5:H$504<=H27)*G$5:G$504) -> 42630304 | J27: =I27/SUM(G$5:G$504) -> 0.25783146 | K27: =IF(J27<=0.8,"A",IF(J27<=0.95,"B","C")) -> A | L27: ='3. Demand Forecast'!H63 -> 0.32 | M27: =IF(L27<=0.25,"X",IF(L27<=0.6,"Y","Z")) -> Y | N27: =K27&M27 -> AY
A28: ='1. Master Data'!A270 -> NT10266 | B28: ='1. Master Data'!B270 -> GameStation Controller 667 | C28: ='1. Master Data'!C270 -> Gaming | D28: ='1. Master Data'!D270 -> West DC | E28: ='1. Master Data'!F270 -> 281 | F28: ='2. Demand History'!AA270 -> 3957 | G28: =E28*F28 -> 1111917 | H28: =RANK(G28,G$5:G$504,0) -> 24 | I28: =SUMPRODUCT((H$5:H$504<=H28)*G$5:G$504) -> 43742221 | J28: =I28/SUM(G$5:G$504) -> 0.26455642 | K28: =IF(J28<=0.8,"A",IF(J28<=0.95,"B","C")) -> A | L28: ='3. Demand Forecast'!H270 -> 0.32 | M28: =IF(L28<=0.25,"X",IF(L28<=0.6,"Y","Z")) -> Y | N28: =K28&M28 -> AY
A29: ='1. Master Data'!A26 -> NT10022 | B29: ='1. Master Data'!B26 -> Pulse 521 Dual SIM | C29: ='1. Master Data'!C26 -> Smartphones | D29: ='1. Master Data'!D26 -> East DC | E29: ='1. Master Data'!F26 -> 782 | F29: ='2. Demand History'!AA26 -> 1417 | G29: =E29*F29 -> 1108094 | H29: =RANK(G29,G$5:G$504,0) -> 25 | I29: =SUMPRODUCT((H$5:H$504<=H29)*G$5:G$504) -> 44850315 | J29: =I29/SUM(G$5:G$504) -> 0.27125826 | K29: =IF(J29<=0.8,"A",IF(J29<=0.95,"B","C")) -> A | L29: ='3. Demand Forecast'!H26 -> 0.31 | M29: =IF(L29<=0.25,"X",IF(L29<=0.6,"Y","Z")) -> Y | N29: =K29&M29 -> AY
A30: ='1. Master Data'!A366 -> NT10362 | B30: ='1. Master Data'!B366 -> MirrorlessM 337 | C30: ='1. Master Data'!C366 -> Cameras | D30: ='1. Master Data'!D366 -> East DC | E30: ='1. Master Data'!F366 -> 1047 | F30: ='2. Demand History'!AA366 -> 1056 | G30: =E30*F30 -> 1105632 | H30: =RANK(G30,G$5:G$504,0) -> 26 | I30: =SUMPRODUCT((H$5:H$504<=H30)*G$5:G$504) -> 45955947 | J30: =I30/SUM(G$5:G$504) -> 0.27794521 | K30: =IF(J30<=0.8,"A",IF(J30<=0.95,"B","C")) -> A | L30: ='3. Demand Forecast'!H366 -> 0.26 | M30: =IF(L30<=0.25,"X",IF(L30<=0.6,"Y","Z")) -> Y | N30: =K30&M30 -> AY
A31: ='1. Master Data'!A285 -> NT10281 | B31: ='1. Master Data'!B285 -> StreamCam S631 | C31: ='1. Master Data'!C285 -> Gaming | D31: ='1. Master Data'!D285 -> West DC | E31: ='1. Master Data'!F285 -> 310 | F31: ='2. Demand History'!AA285 -> 3558 | G31: =E31*F31 -> 1102980 | H31: =RANK(G31,G$5:G$504,0) -> 27 | I31: =SUMPRODUCT((H$5:H$504<=H31)*G$5:G$504) -> 47058927 | J31: =I31/SUM(G$5:G$504) -> 0.28461612 | K31: =IF(J31<=0.8,"A",IF(J31<=0.95,"B","C")) -> A | L31: ='3. Demand Forecast'!H285 -> 0.3 | M31: =IF(L31<=0.25,"X",IF(L31<=0.6,"Y","Z")) -> Y | N31: =K31&M31 -> AY
A32: ='1. Master Data'!A107 -> NT10103 | B32: ='1. Master Data'!B107 -> VisionLED 495in 4K | C32: ='1. Master Data'!C107 -> TVs | D32: ='1. Master Data'!D107 -> East DC | E32: ='1. Master Data'!F107 -> 1280 | F32: ='2. Demand History'!AA107 -> 855 | G32: =E32*F32 -> 1094400 | H32: =RANK(G32,G$5:G$504,0) -> 28 | I32: =SUMPRODUCT((H$5:H$504<=H32)*G$5:G$504) -> 48153327 | J32: =I32/SUM(G$5:G$504) -> 0.29123514 | K32: =IF(J32<=0.8,"A",IF(J32<=0.95,"B","C")) -> A | L32: ='3. Demand Forecast'!H107 -> 0.34 | M32: =IF(L32<=0.25,"X",IF(L32<=0.6,"Y","Z")) -> Y | N32: =K32&M32 -> AY
A33: ='1. Master Data'!A14 -> NT10010 | B33: ='1. Master Data'!B14 -> Nova X834 128GB | C33: ='1. Master Data'!C14 -> Smartphones | D33: ='1. Master Data'!D14 -> West DC | E33: ='1. Master Data'!F14 -> 395 | F33: ='2. Demand History'!AA14 -> 2758 | G33: =E33*F33 -> 1089410 | H33: =RANK(G33,G$5:G$504,0) -> 29 | I33: =SUMPRODUCT((H$5:H$504<=H33)*G$5:G$504) -> 49242737 | J33: =I33/SUM(G$5:G$504) -> 0.29782398 | K33: =IF(J33<=0.8,"A",IF(J33<=0.95,"B","C")) -> A | L33: ='3. Demand Forecast'!H14 -> 0.32 | M33: =IF(L33<=0.25,"X",IF(L33<=0.6,"Y","Z")) -> Y | N33: =K33&M33 -> AY
A34: ='1. Master Data'!A51 -> NT10047 | B34: ='1. Master Data'!B51 -> Edge 345 5G 128GB | C34: ='1. Master Data'!C51 -> Smartphones | D34: ='1. Master Data'!D51 -> West DC | E34: ='1. Master Data'!F51 -> 474 | F34: ='2. Demand History'!AA51 -> 2282 | G34: =E34*F34 -> 1081668 | H34: =RANK(G34,G$5:G$504,0) -> 30 | I34: =SUMPRODUCT((H$5:H$504<=H34)*G$5:G$504) -> 50324405 | J34: =I34/SUM(G$5:G$504) -> 0.30436599 | K34: =IF(J34<=0.8,"A",IF(J34<=0.95,"B","C")) -> A | L34: ='3. Demand Forecast'!H51 -> 0.3 | M34: =IF(L34<=0.25,"X",IF(L34<=0.6,"Y","Z")) -> Y | N34: =K34&M34 -> AY
A35: ='1. Master Data'!A80 -> NT10076 | B35: ='1. Master Data'!B80 -> CreatorPro 809 i9 16in | C35: ='1. Master Data'!C80 -> Laptops | D35: ='1. Master Data'!D80 -> Central DC | E35: ='1. Master Data'!F80 -> 423 | F35: ='2. Demand History'!AA80 -> 2543 | G35: =E35*F35 -> 1075689 | H35: =RANK(G35,G$5:G$504,0) -> 31 | I35: =SUMPRODUCT((H$5:H$504<=H35)*G$5:G$504) -> 51400094 | J35: =I35/SUM(G$5:G$504) -> 0.31087185 | K35: =IF(J35<=0.8,"A",IF(J35<=0.95,"B","C")) -> A | L35: ='3. Demand Forecast'!H80 -> 0.31 | M35: =IF(L35<=0.25,"X",IF(L35<=0.6,"Y","Z")) -> Y | N35: =K35&M35 -> AY
A36: ='1. Master Data'!A33 -> NT10029 | B36: ='1. Master Data'!B33 -> Edge 379 5G 128GB | C36: ='1. Master Data'!C33 -> Smartphones | D36: ='1. Master Data'!D33 -> East DC | E36: ='1. Master Data'!F33 -> 674 | F36: ='2. Demand History'!AA33 -> 1560 | G36: =E36*F36 -> 1051440 | H36: =RANK(G36,G$5:G$504,0) -> 32 | I36: =SUMPRODUCT((H$5:H$504<=H36)*G$5:G$504) -> 52451534 | J36: =I36/SUM(G$5:G$504) -> 0.31723104 | K36: =IF(J36<=0.8,"A",IF(J36<=0.95,"B","C")) -> A | L36: ='3. Demand Forecast'!H33 -> 0.33 | M36: =IF(L36<=0.25,"X",IF(L36<=0.6,"Y","Z")) -> Y | N36: =K36&M36 -> AY
A37: ='1. Master Data'!A68 -> NT10064 | B37: ='1. Master Data'!B68 -> ProBook 948 i7 15in | C37: ='1. Master Data'!C68 -> Laptops | D37: ='1. Master Data'!D68 -> East DC | E37: ='1. Master Data'!F68 -> 1333 | F37: ='2. Demand History'!AA68 -> 788 | G37: =E37*F37 -> 1050404 | H37: =RANK(G37,G$5:G$504,0) -> 33 | I37: =SUMPRODUCT((H$5:H$504<=H37)*G$5:G$504) -> 53501938 | J37: =I37/SUM(G$5:G$504) -> 0.32358397 | K37: =IF(J37<=0.8,"A",IF(J37<=0.95,"B","C")) -> A | L37: ='3. Demand Forecast'!H68 -> 0.31 | M37: =IF(L37<=0.25,"X",IF(L37<=0.6,"Y","Z")) -> Y | N37: =K37&M37 -> AY
A38: ='1. Master Data'!A406 -> NT10402 | B38: ='1. Master Data'!B406 -> NovaTab 904 10in | C38: ='1. Master Data'!C406 -> Tablets | D38: ='1. Master Data'!D406 -> West DC | E38: ='1. Master Data'!F406 -> 220 | F38: ='2. Demand History'!AA406 -> 4768 | G38: =E38*F38 -> 1048960 | H38: =RANK(G38,G$5:G$504,0) -> 34 | I38: =SUMPRODUCT((H$5:H$504<=H38)*G$5:G$504) -> 54550898 | J38: =I38/SUM(G$5:G$504) -> 0.32992816 | K38: =IF(J38<=0.8,"A",IF(J38<=0.95,"B","C")) -> A | L38: ='3. Demand Forecast'!H406 -> 0.27 | M38: =IF(L38<=0.25,"X",IF(L38<=0.6,"Y","Z")) -> Y | N38: =K38&M38 -> AY
A39: ='1. Master Data'!A348 -> NT10344 | B39: ='1. Master Data'!B348 -> LumiBulb 614 RGB | C39: ='1. Master Data'!C348 -> Smart Home | D39: ='1. Master Data'!D348 -> West DC | E39: ='1. Master Data'!F348 -> 100 | F39: ='2. Demand History'!AA348 -> 10331 | G39: =E39*F39 -> 1033100 | H39: =RANK(G39,G$5:G$504,0) -> 35 | I39: =SUMPRODUCT((H$5:H$504<=H39)*G$5:G$504) -> 55583998 | J39: =I39/SUM(G$5:G$504) -> 0.33617643 | K39: =IF(J39<=0.8,"A",IF(J39<=0.95,"B","C")) -> A | L39: ='3. Demand Forecast'!H348 -> 0.07 | M39: =IF(L39<=0.25,"X",IF(L39<=0.6,"Y","Z")) -> X | N39: =K39&M39 -> AX
A40: ='1. Master Data'!A331 -> NT10327 | B40: ='1. Master Data'!B331 -> LumiBulb 401 RGB | C40: ='1. Master Data'!C331 -> Smart Home | D40: ='1. Master Data'!D331 -> East DC | E40: ='1. Master Data'!F331 -> 93 | F40: ='2. Demand History'!AA331 -> 10850 | G40: =E40*F40 -> 1009050 | H40: =RANK(G40,G$5:G$504,0) -> 36 | I40: =SUMPRODUCT((H$5:H$504<=H40)*G$5:G$504) -> 56593048 | J40: =I40/SUM(G$5:G$504) -> 0.34227925 | K40: =IF(J40<=0.8,"A",IF(J40<=0.95,"B","C")) -> A | L40: ='3. Demand Forecast'!H331 -> 0.04 | M40: =IF(L40<=0.25,"X",IF(L40<=0.6,"Y","Z")) -> X | N40: =K40&M40 -> AX
A41: ='1. Master Data'!A138 -> NT10134 | B41: ='1. Master Data'!B138 -> CinemaMax 312in 8K | C41: ='1. Master Data'!C138 -> TVs | D41: ='1. Master Data'!D138 -> Central DC | E41: ='1. Master Data'!F138 -> 1402 | F41: ='2. Demand History'!AA138 -> 715 | G41: =E41*F41 -> 1002430 | H41: =RANK(G41,G$5:G$504,0) -> 37 | I41: =SUMPRODUCT((H$5:H$504<=H41)*G$5:G$504) -> 57595478 | J41: =I41/SUM(G$5:G$504) -> 0.34834202 | K41: =IF(J41<=0.8,"A",IF(J41<=0.95,"B","C")) -> A | L41: ='3. Demand Forecast'!H138 -> 0.31 | M41: =IF(L41<=0.25,"X",IF(L41<=0.6,"Y","Z")) -> Y | N41: =K41&M41 -> AY
A42: ='1. Master Data'!A60 -> NT10056 | B42: ='1. Master Data'!B60 -> ProBook 502 i5 14in | C42: ='1. Master Data'!C60 -> Laptops | D42: ='1. Master Data'!D60 -> West DC | E42: ='1. Master Data'!F60 -> 1457 | F42: ='2. Demand History'!AA60 -> 686 | G42: =E42*F42 -> 999502 | H42: =RANK(G42,G$5:G$504,0) -> 38 | I42: =SUMPRODUCT((H$5:H$504<=H42)*G$5:G$504) -> 58594980 | J42: =I42/SUM(G$5:G$504) -> 0.35438709 | K42: =IF(J42<=0.8,"A",IF(J42<=0.95,"B","C")) -> A | L42: ='3. Demand Forecast'!H60 -> 0.29 | M42: =IF(L42<=0.25,"X",IF(L42<=0.6,"Y","Z")) -> Y | N42: =K42&M42 -> AY
A43: ='1. Master Data'!A96 -> NT10092 | B43: ='1. Master Data'!B96 -> WorkMate 258 i3 14in | C43: ='1. Master Data'!C96 -> Laptops | D43: ='1. Master Data'!D96 -> West DC | E43: ='1. Master Data'!F96 -> 1440 | F43: ='2. Demand History'!AA96 -> 690 | G43: =E43*F43 -> 993600 | H43: =RANK(G43,G$5:G$504,0) -> 39 | I43: =SUMPRODUCT((H$5:H$504<=H43)*G$5:G$504) -> 59588580 | J43: =I43/SUM(G$5:G$504) -> 0.36039646 | K43: =IF(J43<=0.8,"A",IF(J43<=0.95,"B","C")) -> A | L43: ='3. Demand Forecast'!H96 -> 0.29 | M43: =IF(L43<=0.25,"X",IF(L43<=0.6,"Y","Z")) -> Y | N43: =K43&M43 -> AY
A44: ='1. Master Data'!A5 -> NT10001 | B44: ='1. Master Data'!B5 -> Nova X427 128GB | C44: ='1. Master Data'!C5 -> Smartphones | D44: ='1. Master Data'!D5 -> West DC | E44: ='1. Master Data'!F5 -> 865 | F44: ='2. Demand History'!AA5 -> 1141 | G44: =E44*F44 -> 986965 | H44: =RANK(G44,G$5:G$504,0) -> 40 | I44: =SUMPRODUCT((H$5:H$504<=H44)*G$5:G$504) -> 60575545 | J44: =I44/SUM(G$5:G$504) -> 0.3663657 | K44: =IF(J44<=0.8,"A",IF(J44<=0.95,"B","C")) -> A | L44: ='3. Demand Forecast'!H5 -> 0.34 | M44: =IF(L44<=0.25,"X",IF(L44<=0.6,"Y","Z")) -> Y | N44: =K44&M44 -> AY
A45: ='1. Master Data'!A432 -> NT10428 | B45: ='1. Master Data'!B432 -> DrawPad 284 12in | C45: ='1. Master Data'!C432 -> Tablets | D45: ='1. Master Data'!D432 -> East DC | E45: ='1. Master Data'!F432 -> 439 | F45: ='2. Demand History'!AA432 -> 2213 | G45: =E45*F45 -> 971507 | H45: =RANK(G45,G$5:G$504,0) -> 41 | I45: =SUMPRODUCT((H$5:H$504<=H45)*G$5:G$504) -> 61547052 | J45: =I45/SUM(G$5:G$504) -> 0.37224145 | K45: =IF(J45<=0.8,"A",IF(J45<=0.95,"B","C")) -> A | L45: ='3. Demand Forecast'!H432 -> 0.26 | M45: =IF(L45<=0.25,"X",IF(L45<=0.6,"Y","Z")) -> Y | N45: =K45&M45 -> AY
A46: ='1. Master Data'!A147 -> NT10143 | B46: ='1. Master Data'!B147 -> VisionLED 568in 4K | C46: ='1. Master Data'!C147 -> TVs | D46: ='1. Master Data'!D147 -> Central DC | E46: ='1. Master Data'!F147 -> 1356 | F46: ='2. Demand History'!AA147 -> 705 | G46: =E46*F46 -> 955980 | H46: =RANK(G46,G$5:G$504,0) -> 42 | I46: =SUMPRODUCT((H$5:H$504<=H46)*G$5:G$504) -> 62503032 | J46: =I46/SUM(G$5:G$504) -> 0.3780233 | K46: =IF(J46<=0.8,"A",IF(J46<=0.95,"B","C")) -> A | L46: ='3. Demand Forecast'!H147 -> 0.31 | M46: =IF(L46<=0.25,"X",IF(L46<=0.6,"Y","Z")) -> Y | N46: =K46&M46 -> AY
A47: ='1. Master Data'!A149 -> NT10145 | B47: ='1. Master Data'!B149 -> CinemaMax 201in 8K | C47: ='1. Master Data'!C149 -> TVs | D47: ='1. Master Data'!D149 -> East DC | E47: ='1. Master Data'!F149 -> 1435 | F47: ='2. Demand History'!AA149 -> 664 | G47: =E47*F47 -> 952840 | H47: =RANK(G47,G$5:G$504,0) -> 43 | I47: =SUMPRODUCT((H$5:H$504<=H47)*G$5:G$504) -> 63455872 | J47: =I47/SUM(G$5:G$504) -> 0.38378615 | K47: =IF(J47<=0.8,"A",IF(J47<=0.95,"B","C")) -> A | L47: ='3. Demand Forecast'!H149 -> 0.29 | M47: =IF(L47<=0.25,"X",IF(L47<=0.6,"Y","Z")) -> Y | N47: =K47&M47 -> AY
A48: ='1. Master Data'!A189 -> NT10185 | B48: ='1. Master Data'!B189 -> BassMax Speaker 384 | C48: ='1. Master Data'!C189 -> Audio | D48: ='1. Master Data'!D189 -> Central DC | E48: ='1. Master Data'!F189 -> 190 | F48: ='2. Demand History'!AA189 -> 4975 | G48: =E48*F48 -> 945250 | H48: =RANK(G48,G$5:G$504,0) -> 44 | I48: =SUMPRODUCT((H$5:H$504<=H48)*G$5:G$504) -> 64401122 | J48: =I48/SUM(G$5:G$504) -> 0.3895031 | K48: =IF(J48<=0.8,"A",IF(J48<=0.95,"B","C")) -> A | L48: ='3. Demand Forecast'!H189 -> 0.33 | M48: =IF(L48<=0.25,"X",IF(L48<=0.6,"Y","Z")) -> Y | N48: =K48&M48 -> AY
A49: ='1. Master Data'!A253 -> NT10249 | B49: ='1. Master Data'!B253 -> StepOne Tracker 117 | C49: ='1. Master Data'!C253 -> Wearables | D49: ='1. Master Data'!D253 -> Central DC | E49: ='1. Master Data'!F253 -> 133 | F49: ='2. Demand History'!AA253 -> 7046 | G49: =E49*F49 -> 937118 | H49: =RANK(G49,G$5:G$504,0) -> 45 | I49: =SUMPRODUCT((H$5:H$504<=H49)*G$5:G$504) -> 65338240 | J49: =I49/SUM(G$5:G$504) -> 0.39517086 | K49: =IF(J49<=0.8,"A",IF(J49<=0.95,"B","C")) -> A | L49: ='3. Demand Forecast'!H253 -> 0.26 | M49: =IF(L49<=0.25,"X",IF(L49<=0.6,"Y","Z")) -> Y | N49: =K49&M49 -> AY
A50: ='1. Master Data'!A28 -> NT10024 | B50: ='1. Master Data'!B28 -> Nova Lite 799 64GB | C50: ='1. Master Data'!C28 -> Smartphones | D50: ='1. Master Data'!D28 -> Central DC | E50: ='1. Master Data'!F28 -> 583 | F50: ='2. Demand History'!AA28 -> 1588 | G50: =E50*F50 -> 925804 | H50: =RANK(G50,G$5:G$504,0) -> 46 | I50: =SUMPRODUCT((H$5:H$504<=H50)*G$5:G$504) -> 66264044 | J50: =I50/SUM(G$5:G$504) -> 0.4007702 | K50: =IF(J50<=0.8,"A",IF(J50<=0.95,"B","C")) -> A | L50: ='3. Demand Forecast'!H28 -> 0.3 | M50: =IF(L50<=0.25,"X",IF(L50<=0.6,"Y","Z")) -> Y | N50: =K50&M50 -> AY
A51: ='1. Master Data'!A73 -> NT10069 | B51: ='1. Master Data'!B73 -> CreatorPro 741 i9 16in | C51: ='1. Master Data'!C73 -> Laptops | D51: ='1. Master Data'!D73 -> East DC | E51: ='1. Master Data'!F73 -> 1079 | F51: ='2. Demand History'!AA73 -> 846 | G51: =E51*F51 -> 912834 | H51: =RANK(G51,G$5:G$504,0) -> 47 | I51: =SUMPRODUCT((H$5:H$504<=H51)*G$5:G$504) -> 67176878 | J51: =I51/SUM(G$5:G$504) -> 0.40629109 | K51: =IF(J51<=0.8,"A",IF(J51<=0.95,"B","C")) -> A | L51: ='3. Demand Forecast'!H73 -> 0.27 | M51: =IF(L51<=0.25,"X",IF(L51<=0.6,"Y","Z")) -> Y | N51: =K51&M51 -> AY
A52: ='1. Master Data'!A37 -> NT10033 | B52: ='1. Master Data'!B37 -> Pulse 902 Dual SIM | C52: ='1. Master Data'!C37 -> Smartphones | D52: ='1. Master Data'!D37 -> West DC | E52: ='1. Master Data'!F37 -> 610 | F52: ='2. Demand History'!AA37 -> 1496 | G52: =E52*F52 -> 912560 | H52: =RANK(G52,G$5:G$504,0) -> 48 | I52: =SUMPRODUCT((H$5:H$504<=H52)*G$5:G$504) -> 68089438 | J52: =I52/SUM(G$5:G$504) -> 0.41181032 | K52: =IF(J52<=0.8,"A",IF(J52<=0.95,"B","C")) -> A | L52: ='3. Demand Forecast'!H37 -> 0.31 | M52: =IF(L52<=0.25,"X",IF(L52<=0.6,"Y","Z")) -> Y | N52: =K52&M52 -> AY
A53: ='1. Master Data'!A29 -> NT10025 | B53: ='1. Master Data'!B29 -> Pulse 733 Dual SIM | C53: ='1. Master Data'!C29 -> Smartphones | D53: ='1. Master Data'!D29 -> Central DC | E53: ='1. Master Data'!F29 -> 855 | F53: ='2. Demand History'!AA29 -> 1065 | G53: =E53*F53 -> 910575 | H53: =RANK(G53,G$5:G$504,0) -> 49 | I53: =SUMPRODUCT((H$5:H$504<=H53)*G$5:G$504) -> 69000013 | J53: =I53/SUM(G$5:G$504) -> 0.41731755 | K53: =IF(J53<=0.8,"A",IF(J53<=0.95,"B","C")) -> A | L53: ='3. Demand Forecast'!H29 -> 0.26 | M53: =IF(L53<=0.25,"X",IF(L53<=0.6,"Y","Z")) -> Y | N53: =K53&M53 -> AY
A54: ='1. Master Data'!A46 -> NT10042 | B54: ='1. Master Data'!B46 -> Nova Lite 981 64GB | C54: ='1. Master Data'!C46 -> Smartphones | D54: ='1. Master Data'!D46 -> West DC | E54: ='1. Master Data'!F46 -> 548 | F54: ='2. Demand History'!AA46 -> 1626 | G54: =E54*F54 -> 891048 | H54: =RANK(G54,G$5:G$504,0) -> 50 | I54: =SUMPRODUCT((H$5:H$504<=H54)*G$5:G$504) -> 69891061 | J54: =I54/SUM(G$5:G$504) -> 0.42270668 | K54: =IF(J54<=0.8,"A",IF(J54<=0.95,"B","C")) -> A | L54: ='3. Demand Forecast'!H46 -> 0.4 | M54: =IF(L54<=0.25,"X",IF(L54<=0.6,"Y","Z")) -> Y | N54: =K54&M54 -> AY
A55: ='1. Master Data'!A154 -> NT10150 | B55: ='1. Master Data'!B154 -> VisionLED 977in 4K | C55: ='1. Master Data'!C154 -> TVs | D55: ='1. Master Data'!D154 -> Central DC | E55: ='1. Master Data'!F154 -> 1541 | F55: ='2. Demand History'!AA154 -> 572 | G55: =E55*F55 -> 881452 | H55: =RANK(G55,G$5:G$504,0) -> 51 | I55: =SUMPRODUCT((H$5:H$504<=H55)*G$5:G$504) -> 70772513 | J55: =I55/SUM(G$5:G$504) -> 0.42803777 | K55: =IF(J55<=0.8,"A",IF(J55<=0.95,"B","C")) -> A | L55: ='3. Demand Forecast'!H154 -> 0.29 | M55: =IF(L55<=0.25,"X",IF(L55<=0.6,"Y","Z")) -> Y | N55: =K55&M55 -> AY
A56: ='1. Master Data'!A345 -> NT10341 | B56: ='1. Master Data'!B345 -> ThermoSmart 194 | C56: ='1. Master Data'!C345 -> Smart Home | D56: ='1. Master Data'!D345 -> East DC | E56: ='1. Master Data'!F345 -> 116 | F56: ='2. Demand History'!AA345 -> 7584 | G56: =E56*F56 -> 879744 | H56: =RANK(G56,G$5:G$504,0) -> 52 | I56: =SUMPRODUCT((H$5:H$504<=H56)*G$5:G$504) -> 71652257 | J56: =I56/SUM(G$5:G$504) -> 0.43335854 | K56: =IF(J56<=0.8,"A",IF(J56<=0.95,"B","C")) -> A | L56: ='3. Demand Forecast'!H345 -> 0.05 | M56: =IF(L56<=0.25,"X",IF(L56<=0.6,"Y","Z")) -> X | N56: =K56&M56 -> AX
A57: ='1. Master Data'!A266 -> NT10262 | B57: ='1. Master Data'!B266 -> GameStation Controller 179 | C57: ='1. Master Data'!C266 -> Gaming | D57: ='1. Master Data'!D266 -> East DC | E57: ='1. Master Data'!F266 -> 333 | F57: ='2. Demand History'!AA266 -> 2520 | G57: =E57*F57 -> 839160 | H57: =RANK(G57,G$5:G$504,0) -> 53 | I57: =SUMPRODUCT((H$5:H$504<=H57)*G$5:G$504) -> 72491417 | J57: =I57/SUM(G$5:G$504) -> 0.43843384 | K57: =IF(J57<=0.8,"A",IF(J57<=0.95,"B","C")) -> A | L57: ='3. Demand Forecast'!H266 -> 0.27 | M57: =IF(L57<=0.25,"X",IF(L57<=0.6,"Y","Z")) -> Y | N57: =K57&M57 -> AY
A58: ='1. Master Data'!A258 -> NT10254 | B58: ='1. Master Data'!B258 -> ProMouse G406 | C58: ='1. Master Data'!C258 -> Gaming | D58: ='1. Master Data'!D258 -> East DC | E58: ='1. Master Data'!F258 -> 329 | F58: ='2. Demand History'!AA258 -> 2525 | G58: =E58*F58 -> 830725 | H58: =RANK(G58,G$5:G$504,0) -> 54 | I58: =SUMPRODUCT((H$5:H$504<=H58)*G$5:G$504) -> 73322142 | J58: =I58/SUM(G$5:G$504) -> 0.44345813 | K58: =IF(J58<=0.8,"A",IF(J58<=0.95,"B","C")) -> A | L58: ='3. Demand Forecast'!H258 -> 0.32 | M58: =IF(L58<=0.25,"X",IF(L58<=0.6,"Y","Z")) -> Y | N58: =K58&M58 -> AY
A59: ='1. Master Data'!A120 -> NT10116 | B59: ='1. Master Data'!B120 -> CinemaMax 365in 8K | C59: ='1. Master Data'!C120 -> TVs | D59: ='1. Master Data'!D120 -> West DC | E59: ='1. Master Data'!F120 -> 1790 | F59: ='2. Demand History'!AA120 -> 454 | G59: =E59*F59 -> 812660 | H59: =RANK(G59,G$5:G$504,0) -> 55 | I59: =SUMPRODUCT((H$5:H$504<=H59)*G$5:G$504) -> 74134802 | J59: =I59/SUM(G$5:G$504) -> 0.44837317 | K59: =IF(J59<=0.8,"A",IF(J59<=0.95,"B","C")) -> A | L59: ='3. Demand Forecast'!H120 -> 0.29 | M59: =IF(L59<=0.25,"X",IF(L59<=0.6,"Y","Z")) -> Y | N59: =K59&M59 -> AY
A60: ='1. Master Data'!A88 -> NT10084 | B60: ='1. Master Data'!B88 -> CreatorPro 984 i9 16in | C60: ='1. Master Data'!C88 -> Laptops | D60: ='1. Master Data'!D88 -> East DC | E60: ='1. Master Data'!F88 -> 1481 | F60: ='2. Demand History'!AA88 -> 547 | G60: =E60*F60 -> 810107 | H60: =RANK(G60,G$5:G$504,0) -> 56 | I60: =SUMPRODUCT((H$5:H$504<=H60)*G$5:G$504) -> 74944909 | J60: =I60/SUM(G$5:G$504) -> 0.45327276 | K60: =IF(J60<=0.8,"A",IF(J60<=0.95,"B","C")) -> A | L60: ='3. Demand Forecast'!H88 -> 0.32 | M60: =IF(L60<=0.25,"X",IF(L60<=0.6,"Y","Z")) -> Y | N60: =K60&M60 -> AY
A61: ='1. Master Data'!A118 -> NT10114 | B61: ='1. Master Data'!B118 -> CinemaMax 961in 8K | C61: ='1. Master Data'!C118 -> TVs | D61: ='1. Master Data'!D118 -> Central DC | E61: ='1. Master Data'!F118 -> 1632 | F61: ='2. Demand History'!AA118 -> 496 | G61: =E61*F61 -> 809472 | H61: =RANK(G61,G$5:G$504,0) -> 57 | I61: =SUMPRODUCT((H$5:H$504<=H61)*G$5:G$504) -> 75754381 | J61: =I61/SUM(G$5:G$504) -> 0.45816851 | K61: =IF(J61<=0.8,"A",IF(J61<=0.95,"B","C")) -> A | L61: ='3. Demand Forecast'!H118 -> 0.28 | M61: =IF(L61<=0.25,"X",IF(L61<=0.6,"Y","Z")) -> Y | N61: =K61&M61 -> AY
A62: ='1. Master Data'!A128 -> NT10124 | B62: ='1. Master Data'!B128 -> VisionLED 486in 4K | C62: ='1. Master Data'!C128 -> TVs | D62: ='1. Master Data'!D128 -> West DC | E62: ='1. Master Data'!F128 -> 1517 | F62: ='2. Demand History'!AA128 -> 533 | G62: =E62*F62 -> 808561 | H62: =RANK(G62,G$5:G$504,0) -> 58 | I62: =SUMPRODUCT((H$5:H$504<=H62)*G$5:G$504) -> 76562942 | J62: =I62/SUM(G$5:G$504) -> 0.46305875 | K62: =IF(J62<=0.8,"A",IF(J62<=0.95,"B","C")) -> A | L62: ='3. Demand Forecast'!H128 -> 0.31 | M62: =IF(L62<=0.25,"X",IF(L62<=0.6,"Y","Z")) -> Y | N62: =K62&M62 -> AY
A63: ='1. Master Data'!A142 -> NT10138 | B63: ='1. Master Data'!B142 -> VisionQ 956in QLED | C63: ='1. Master Data'!C142 -> TVs | D63: ='1. Master Data'!D142 -> West DC | E63: ='1. Master Data'!F142 -> 1715 | F63: ='2. Demand History'!AA142 -> 469 | G63: =E63*F63 -> 804335 | H63: =RANK(G63,G$5:G$504,0) -> 59 | I63: =SUMPRODUCT((H$5:H$504<=H63)*G$5:G$504) -> 77367277 | J63: =I63/SUM(G$5:G$504) -> 0.46792343 | K63: =IF(J63<=0.8,"A",IF(J63<=0.95,"B","C")) -> A | L63: ='3. Demand Forecast'!H142 -> 0.33 | M63: =IF(L63<=0.25,"X",IF(L63<=0.6,"Y","Z")) -> Y | N63: =K63&M63 -> AY
A64: ='1. Master Data'!A368 -> NT10364 | B64: ='1. Master Data'!B368 -> MirrorlessM 494 | C64: ='1. Master Data'!C368 -> Cameras | D64: ='1. Master Data'!D368 -> West DC | E64: ='1. Master Data'!F368 -> 1041 | F64: ='2. Demand History'!AA368 -> 770 | G64: =E64*F64 -> 801570 | H64: =RANK(G64,G$5:G$504,0) -> 60 | I64: =SUMPRODUCT((H$5:H$504<=H64)*G$5:G$504) -> 78168847 | J64: =I64/SUM(G$5:G$504) -> 0.47277139 | K64: =IF(J64<=0.8,"A",IF(J64<=0.95,"B","C")) -> A | L64: ='3. Demand Forecast'!H368 -> 0.32 | M64: =IF(L64<=0.25,"X",IF(L64<=0.6,"Y","Z")) -> Y | N64: =K64&M64 -> AY
A65: ='1. Master Data'!A295 -> NT10291 | B65: ='1. Master Data'!B295 -> GameStation Controller 866 | C65: ='1. Master Data'!C295 -> Gaming | D65: ='1. Master Data'!D295 -> West DC | E65: ='1. Master Data'!F295 -> 169 | F65: ='2. Demand History'!AA295 -> 4634 | G65: =E65*F65 -> 783146 | H65: =RANK(G65,G$5:G$504,0) -> 61 | I65: =SUMPRODUCT((H$5:H$504<=H65)*G$5:G$504) -> 78951993 | J65: =I65/SUM(G$5:G$504) -> 0.47750792 | K65: =IF(J65<=0.8,"A",IF(J65<=0.95,"B","C")) -> A | L65: ='3. Demand Forecast'!H295 -> 0.27 | M65: =IF(L65<=0.25,"X",IF(L65<=0.6,"Y","Z")) -> Y | N65: =K65&M65 -> AY
A66: ='1. Master Data'!A334 -> NT10330 | B66: ='1. Master Data'!B334 -> LumiBulb 508 RGB | C66: ='1. Master Data'!C334 -> Smart Home | D66: ='1. Master Data'!D334 -> Central DC | E66: ='1. Master Data'!F334 -> 96 | F66: ='2. Demand History'!AA334 -> 8145 | G66: =E66*F66 -> 781920 | H66: =RANK(G66,G$5:G$504,0) -> 62 | I66: =SUMPRODUCT((H$5:H$504<=H66)*G$5:G$504) -> 79733913 | J66: =I66/SUM(G$5:G$504) -> 0.48223703 | K66: =IF(J66<=0.8,"A",IF(J66<=0.95,"B","C")) -> A | L66: ='3. Demand Forecast'!H334 -> 0.05 | M66: =IF(L66<=0.25,"X",IF(L66<=0.6,"Y","Z")) -> X | N66: =K66&M66 -> AX
A67: ='1. Master Data'!A127 -> NT10123 | B67: ='1. Master Data'!B127 -> VisionQ 624in QLED | C67: ='1. Master Data'!C127 -> TVs | D67: ='1. Master Data'!D127 -> East DC | E67: ='1. Master Data'!F127 -> 1696 | F67: ='2. Demand History'!AA127 -> 454 | G67: =E67*F67 -> 769984 | H67: =RANK(G67,G$5:G$504,0) -> 63 | I67: =SUMPRODUCT((H$5:H$504<=H67)*G$5:G$504) -> 80503897 | J67: =I67/SUM(G$5:G$504) -> 0.48689396 | K67: =IF(J67<=0.8,"A",IF(J67<=0.95,"B","C")) -> A | L67: ='3. Demand Forecast'!H127 -> 0.35 | M67: =IF(L67<=0.25,"X",IF(L67<=0.6,"Y","Z")) -> Y | N67: =K67&M67 -> AY
A68: ='1. Master Data'!A113 -> NT10109 | B68: ='1. Master Data'!B113 -> VisionQ 346in QLED | C68: ='1. Master Data'!C113 -> TVs | D68: ='1. Master Data'!D113 -> Central DC | E68: ='1. Master Data'!F113 -> 1184 | F68: ='2. Demand History'!AA113 -> 643 | G68: =E68*F68 -> 761312 | H68: =RANK(G68,G$5:G$504,0) -> 64 | I68: =SUMPRODUCT((H$5:H$504<=H68)*G$5:G$504) -> 81265209 | J68: =I68/SUM(G$5:G$504) -> 0.49149843 | K68: =IF(J68<=0.8,"A",IF(J68<=0.95,"B","C")) -> A | L68: ='3. Demand Forecast'!H113 -> 0.27 | M68: =IF(L68<=0.25,"X",IF(L68<=0.6,"Y","Z")) -> Y | N68: =K68&M68 -> AY
A69: ='1. Master Data'!A50 -> NT10046 | B69: ='1. Master Data'!B50 -> Nova Lite 711 64GB | C69: ='1. Master Data'!C50 -> Smartphones | D69: ='1. Master Data'!D50 -> Central DC | E69: ='1. Master Data'!F50 -> 684 | F69: ='2. Demand History'!AA50 -> 1072 | G69: =E69*F69 -> 733248 | H69: =RANK(G69,G$5:G$504,0) -> 65 | I69: =SUMPRODUCT((H$5:H$504<=H69)*G$5:G$504) -> 81998457 | J69: =I69/SUM(G$5:G$504) -> 0.49593317 | K69: =IF(J69<=0.8,"A",IF(J69<=0.95,"B","C")) -> A | L69: ='3. Demand Forecast'!H50 -> 0.32 | M69: =IF(L69<=0.25,"X",IF(L69<=0.6,"Y","Z")) -> Y | N69: =K69&M69 -> AY
A70: ='1. Master Data'!A163 -> NT10159 | B70: ='1. Master Data'!B163 -> StudioPods 901 ANC | C70: ='1. Master Data'!C163 -> Audio | D70: ='1. Master Data'!D163 -> West DC | E70: ='1. Master Data'!F163 -> 107 | F70: ='2. Demand History'!AA163 -> 6750 | G70: =E70*F70 -> 722250 | H70: =RANK(G70,G$5:G$504,0) -> 66 | I70: =SUMPRODUCT((H$5:H$504<=H70)*G$5:G$504) -> 82720707 | J70: =I70/SUM(G$5:G$504) -> 0.5003014 | K70: =IF(J70<=0.8,"A",IF(J70<=0.95,"B","C")) -> A | L70: ='3. Demand Forecast'!H163 -> 0.31 | M70: =IF(L70<=0.25,"X",IF(L70<=0.6,"Y","Z")) -> Y | N70: =K70&M70 -> AY
A71: ='1. Master Data'!A117 -> NT10113 | B71: ='1. Master Data'!B117 -> VisionLED 323in 4K | C71: ='1. Master Data'!C117 -> TVs | D71: ='1. Master Data'!D117 -> West DC | E71: ='1. Master Data'!F117 -> 1425 | F71: ='2. Demand History'!AA117 -> 505 | G71: =E71*F71 -> 719625 | H71: =RANK(G71,G$5:G$504,0) -> 67 | I71: =SUMPRODUCT((H$5:H$504<=H71)*G$5:G$504) -> 83440332 | J71: =I71/SUM(G$5:G$504) -> 0.50465375 | K71: =IF(J71<=0.8,"A",IF(J71<=0.95,"B","C")) -> A | L71: ='3. Demand Forecast'!H117 -> 0.3 | M71: =IF(L71<=0.25,"X",IF(L71<=0.6,"Y","Z")) -> Y | N71: =K71&M71 -> AY
A72: ='1. Master Data'!A251 -> NT10247 | B72: ='1. Master Data'!B251 -> StepOne Tracker 687 | C72: ='1. Master Data'!C251 -> Wearables | D72: ='1. Master Data'!D251 -> West DC | E72: ='1. Master Data'!F251 -> 152 | F72: ='2. Demand History'!AA251 -> 4524 | G72: =E72*F72 -> 687648 | H72: =RANK(G72,G$5:G$504,0) -> 68 | I72: =SUMPRODUCT((H$5:H$504<=H72)*G$5:G$504) -> 84127980 | J72: =I72/SUM(G$5:G$504) -> 0.5088127 | K72: =IF(J72<=0.8,"A",IF(J72<=0.95,"B","C")) -> A | L72: ='3. Demand Forecast'!H251 -> 0.24 | M72: =IF(L72<=0.25,"X",IF(L72<=0.6,"Y","Z")) -> X | N72: =K72&M72 -> AX
A73: ='1. Master Data'!A259 -> NT10255 | B73: ='1. Master Data'!B259 -> ProMouse G982 | C73: ='1. Master Data'!C259 -> Gaming | D73: ='1. Master Data'!D259 -> East DC | E73: ='1. Master Data'!F259 -> 292 | F73: ='2. Demand History'!AA259 -> 2338 | G73: =E73*F73 -> 682696 | H73: =RANK(G73,G$5:G$504,0) -> 69 | I73: =SUMPRODUCT((H$5:H$504<=H73)*G$5:G$504) -> 84810676 | J73: =I73/SUM(G$5:G$504) -> 0.5129417 | K73: =IF(J73<=0.8,"A",IF(J73<=0.95,"B","C")) -> A | L73: ='3. Demand Forecast'!H259 -> 0.25 | M73: =IF(L73<=0.25,"X",IF(L73<=0.6,"Y","Z")) -> X | N73: =K73&M73 -> AX
A74: ='1. Master Data'!A84 -> NT10080 | B74: ='1. Master Data'!B84 -> UltraSlim 600 Ryzen 5 | C74: ='1. Master Data'!C84 -> Laptops | D74: ='1. Master Data'!D84 -> Central DC | E74: ='1. Master Data'!F84 -> 475 | F74: ='2. Demand History'!AA84 -> 1409 | G74: =E74*F74 -> 669275 | H74: =RANK(G74,G$5:G$504,0) -> 70 | I74: =SUMPRODUCT((H$5:H$504<=H74)*G$5:G$504) -> 85479951 | J74: =I74/SUM(G$5:G$504) -> 0.51698953 | K74: =IF(J74<=0.8,"A",IF(J74<=0.95,"B","C")) -> A | L74: ='3. Demand Forecast'!H84 -> 0.39 | M74: =IF(L74<=0.25,"X",IF(L74<=0.6,"Y","Z")) -> Y | N74: =K74&M74 -> AY
A75: ='1. Master Data'!A45 -> NT10041 | B75: ='1. Master Data'!B45 -> Nova Lite 722 64GB | C75: ='1. Master Data'!C45 -> Smartphones | D75: ='1. Master Data'!D45 -> East DC | E75: ='1. Master Data'!F45 -> 723 | F75: ='2. Demand History'!AA45 -> 892 | G75: =E75*F75 -> 644916 | H75: =RANK(G75,G$5:G$504,0) -> 71 | I75: =SUMPRODUCT((H$5:H$504<=H75)*G$5:G$504) -> 86124867 | J75: =I75/SUM(G$5:G$504) -> 0.52089003 | K75: =IF(J75<=0.8,"A",IF(J75<=0.95,"B","C")) -> A | L75: ='3. Demand Forecast'!H45 -> 0.27 | M75: =IF(L75<=0.25,"X",IF(L75<=0.6,"Y","Z")) -> Y | N75: =K75&M75 -> AY
A76: ='1. Master Data'!A132 -> NT10128 | B76: ='1. Master Data'!B132 -> VisionQ 120in QLED | C76: ='1. Master Data'!C132 -> TVs | D76: ='1. Master Data'!D132 -> West DC | E76: ='1. Master Data'!F132 -> 905 | F76: ='2. Demand History'!AA132 -> 699 | G76: =E76*F76 -> 632595 | H76: =RANK(G76,G$5:G$504,0) -> 72 | I76: =SUMPRODUCT((H$5:H$504<=H76)*G$5:G$504) -> 86757462 | J76: =I76/SUM(G$5:G$504) -> 0.52471601 | K76: =IF(J76<=0.8,"A",IF(J76<=0.95,"B","C")) -> A | L76: ='3. Demand Forecast'!H132 -> 0.31 | M76: =IF(L76<=0.25,"X",IF(L76<=0.6,"Y","Z")) -> Y | N76: =K76&M76 -> AY
A77: ='1. Master Data'!A145 -> NT10141 | B77: ='1. Master Data'!B145 -> VisionLED 341in 4K | C77: ='1. Master Data'!C145 -> TVs | D77: ='1. Master Data'!D145 -> East DC | E77: ='1. Master Data'!F145 -> 1304 | F77: ='2. Demand History'!AA145 -> 485 | G77: =E77*F77 -> 632440 | H77: =RANK(G77,G$5:G$504,0) -> 73 | I77: =SUMPRODUCT((H$5:H$504<=H77)*G$5:G$504) -> 87389902 | J77: =I77/SUM(G$5:G$504) -> 0.52854106 | K77: =IF(J77<=0.8,"A",IF(J77<=0.95,"B","C")) -> A | L77: ='3. Demand Forecast'!H145 -> 0.39 | M77: =IF(L77<=0.25,"X",IF(L77<=0.6,"Y","Z")) -> Y | N77: =K77&M77 -> AY
A78: ='1. Master Data'!A152 -> NT10148 | B78: ='1. Master Data'!B152 -> CinemaMax 609in 8K | C78: ='1. Master Data'!C152 -> TVs | D78: ='1. Master Data'!D152 -> East DC | E78: ='1. Master Data'!F152 -> 1273 | F78: ='2. Demand History'!AA152 -> 488 | G78: =E78*F78 -> 621224 | H78: =RANK(G78,G$5:G$504,0) -> 74 | I78: =SUMPRODUCT((H$5:H$504<=H78)*G$5:G$504) -> 88011126 | J78: =I78/SUM(G$5:G$504) -> 0.53229827 | K78: =IF(J78<=0.8,"A",IF(J78<=0.95,"B","C")) -> A | L78: ='3. Demand Forecast'!H152 -> 0.23 | M78: =IF(L78<=0.25,"X",IF(L78<=0.6,"Y","Z")) -> X | N78: =K78&M78 -> AX
A79: ='1. Master Data'!A276 -> NT10272 | B79: ='1. Master Data'!B276 -> RGB Keyboard K758 | C79: ='1. Master Data'!C276 -> Gaming | D79: ='1. Master Data'!D276 -> East DC | E79: ='1. Master Data'!F276 -> 309 | F79: ='2. Demand History'!AA276 -> 2009 | G79: =E79*F79 -> 620781 | H79: =RANK(G79,G$5:G$504,0) -> 75 | I79: =SUMPRODUCT((H$5:H$504<=H79)*G$5:G$504) -> 88631907 | J79: =I79/SUM(G$5:G$504) -> 0.53605281 | K79: =IF(J79<=0.8,"A",IF(J79<=0.95,"B","C")) -> A | L79: ='3. Demand Forecast'!H276 -> 0.27 | M79: =IF(L79<=0.25,"X",IF(L79<=0.6,"Y","Z")) -> Y | N79: =K79&M79 -> AY
A80: ='1. Master Data'!A75 -> NT10071 | B80: ='1. Master Data'!B75 -> WorkMate 444 i3 14in | C80: ='1. Master Data'!C75 -> Laptops | D80: ='1. Master Data'!D75 -> West DC | E80: ='1. Master Data'!F75 -> 1413 | F80: ='2. Demand History'!AA75 -> 438 | G80: =E80*F80 -> 618894 | H80: =RANK(G80,G$5:G$504,0) -> 76 | I80: =SUMPRODUCT((H$5:H$504<=H80)*G$5:G$504) -> 89250801 | J80: =I80/SUM(G$5:G$504) -> 0.53979593 | K80: =IF(J80<=0.8,"A",IF(J80<=0.95,"B","C")) -> A | L80: ='3. Demand Forecast'!H75 -> 0.37 | M80: =IF(L80<=0.25,"X",IF(L80<=0.6,"Y","Z")) -> Y | N80: =K80&M80 -> AY
A81: ='1. Master Data'!A87 -> NT10083 | B81: ='1. Master Data'!B87 -> CreatorPro 192 i9 16in | C81: ='1. Master Data'!C87 -> Laptops | D81: ='1. Master Data'!D87 -> East DC | E81: ='1. Master Data'!F87 -> 1051 | F81: ='2. Demand History'!AA87 -> 581 | G81: =E81*F81 -> 610631 | H81: =RANK(G81,G$5:G$504,0) -> 77 | I81: =SUMPRODUCT((H$5:H$504<=H81)*G$5:G$504) -> 89861432 | J81: =I81/SUM(G$5:G$504) -> 0.54348907 | K81: =IF(J81<=0.8,"A",IF(J81<=0.95,"B","C")) -> A | L81: ='3. Demand Forecast'!H87 -> 0.28 | M81: =IF(L81<=0.25,"X",IF(L81<=0.6,"Y","Z")) -> Y | N81: =K81&M81 -> AY
A82: ='1. Master Data'!A184 -> NT10180 | B82: ='1. Master Data'!B184 -> ClipMic 324 Wireless | C82: ='1. Master Data'!C184 -> Audio | D82: ='1. Master Data'!D184 -> West DC | E82: ='1. Master Data'!F184 -> 230 | F82: ='2. Demand History'!AA184 -> 2607 | G82: =E82*F82 -> 599610 | H82: =RANK(G82,G$5:G$504,0) -> 78 | I82: =SUMPRODUCT((H$5:H$504<=H82)*G$5:G$504) -> 90461042 | J82: =I82/SUM(G$5:G$504) -> 0.54711556 | K82: =IF(J82<=0.8,"A",IF(J82<=0.95,"B","C")) -> A | L82: ='3. Demand Forecast'!H184 -> 0.31 | M82: =IF(L82<=0.25,"X",IF(L82<=0.6,"Y","Z")) -> Y | N82: =K82&M82 -> AY
A83: ='1. Master Data'!A451 -> NT10447 | B83: ='1. Master Data'!B451 -> DrawPad 840 12in | C83: ='1. Master Data'!C451 -> Tablets | D83: ='1. Master Data'!D451 -> Central DC | E83: ='1. Master Data'!F451 -> 284 | F83: ='2. Demand History'!AA451 -> 2092 | G83: =E83*F83 -> 594128 | H83: =RANK(G83,G$5:G$504,0) -> 79 | I83: =SUMPRODUCT((H$5:H$504<=H83)*G$5:G$504) -> 91055170 | J83: =I83/SUM(G$5:G$504) -> 0.55070889 | K83: =IF(J83<=0.8,"A",IF(J83<=0.95,"B","C")) -> A | L83: ='3. Demand Forecast'!H451 -> 0.3 | M83: =IF(L83<=0.25,"X",IF(L83<=0.6,"Y","Z")) -> Y | N83: =K83&M83 -> AY
A84: ='1. Master Data'!A296 -> NT10292 | B84: ='1. Master Data'!B296 -> ArenaHeadset H600 | C84: ='1. Master Data'!C296 -> Gaming | D84: ='1. Master Data'!D296 -> East DC | E84: ='1. Master Data'!F296 -> 299 | F84: ='2. Demand History'!AA296 -> 1978 | G84: =E84*F84 -> 591422 | H84: =RANK(G84,G$5:G$504,0) -> 80 | I84: =SUMPRODUCT((H$5:H$504<=H84)*G$5:G$504) -> 91646592 | J84: =I84/SUM(G$5:G$504) -> 0.55428586 | K84: =IF(J84<=0.8,"A",IF(J84<=0.95,"B","C")) -> A | L84: ='3. Demand Forecast'!H296 -> 0.3 | M84: =IF(L84<=0.25,"X",IF(L84<=0.6,"Y","Z")) -> Y | N84: =K84&M84 -> AY
A85: ='1. Master Data'!A99 -> NT10095 | B85: ='1. Master Data'!B99 -> ProBook 648 i7 15in | C85: ='1. Master Data'!C99 -> Laptops | D85: ='1. Master Data'!D99 -> East DC | E85: ='1. Master Data'!F99 -> 1266 | F85: ='2. Demand History'!AA99 -> 467 | G85: =E85*F85 -> 591222 | H85: =RANK(G85,G$5:G$504,0) -> 81 | I85: =SUMPRODUCT((H$5:H$504<=H85)*G$5:G$504) -> 92237814 | J85: =I85/SUM(G$5:G$504) -> 0.55786162 | K85: =IF(J85<=0.8,"A",IF(J85<=0.95,"B","C")) -> A | L85: ='3. Demand Forecast'!H99 -> 0.37 | M85: =IF(L85<=0.25,"X",IF(L85<=0.6,"Y","Z")) -> Y | N85: =K85&M85 -> AY
A86: ='1. Master Data'!A20 -> NT10016 | B86: ='1. Master Data'!B20 -> Nova Lite 610 64GB | C86: ='1. Master Data'!C20 -> Smartphones | D86: ='1. Master Data'!D20 -> Central DC | E86: ='1. Master Data'!F20 -> 449 | F86: ='2. Demand History'!AA20 -> 1314 | G86: =E86*F86 -> 589986 | H86: =RANK(G86,G$5:G$504,0) -> 82 | I86: =SUMPRODUCT((H$5:H$504<=H86)*G$5:G$504) -> 92827800 | J86: =I86/SUM(G$5:G$504) -> 0.5614299 | K86: =IF(J86<=0.8,"A",IF(J86<=0.95,"B","C")) -> A | L86: ='3. Demand Forecast'!H20 -> 0.24 | M86: =IF(L86<=0.25,"X",IF(L86<=0.6,"Y","Z")) -> X | N86: =K86&M86 -> AX
A87: ='1. Master Data'!A53 -> NT10049 | B87: ='1. Master Data'!B53 -> Nova Lite 422 64GB | C87: ='1. Master Data'!C53 -> Smartphones | D87: ='1. Master Data'!D53 -> West DC | E87: ='1. Master Data'!F53 -> 857 | F87: ='2. Demand History'!AA53 -> 680 | G87: =E87*F87 -> 582760 | H87: =RANK(G87,G$5:G$504,0) -> 83 | I87: =SUMPRODUCT((H$5:H$504<=H87)*G$5:G$504) -> 93410560 | J87: =I87/SUM(G$5:G$504) -> 0.56495448 | K87: =IF(J87<=0.8,"A",IF(J87<=0.95,"B","C")) -> A | L87: ='3. Demand Forecast'!H53 -> 0.25 | M87: =IF(L87<=0.25,"X",IF(L87<=0.6,"Y","Z")) -> X | N87: =K87&M87 -> AX
A88: ='1. Master Data'!A281 -> NT10277 | B88: ='1. Master Data'!B281 -> RGB Keyboard K367 | C88: ='1. Master Data'!C281 -> Gaming | D88: ='1. Master Data'!D281 -> Central DC | E88: ='1. Master Data'!F281 -> 196 | F88: ='2. Demand History'!AA281 -> 2906 | G88: =E88*F88 -> 569576 | H88: =RANK(G88,G$5:G$504,0) -> 84 | I88: =SUMPRODUCT((H$5:H$504<=H88)*G$5:G$504) -> 93980136 | J88: =I88/SUM(G$5:G$504) -> 0.56839932 | K88: =IF(J88<=0.8,"A",IF(J88<=0.95,"B","C")) -> A | L88: ='3. Demand Forecast'!H281 -> 0.33 | M88: =IF(L88<=0.25,"X",IF(L88<=0.6,"Y","Z")) -> Y | N88: =K88&M88 -> AY
A89: ='1. Master Data'!A77 -> NT10073 | B89: ='1. Master Data'!B77 -> ProBook 373 i5 14in | C89: ='1. Master Data'!C77 -> Laptops | D89: ='1. Master Data'!D77 -> Central DC | E89: ='1. Master Data'!F77 -> 1084 | F89: ='2. Demand History'!AA77 -> 525 | G89: =E89*F89 -> 569100 | H89: =RANK(G89,G$5:G$504,0) -> 85 | I89: =SUMPRODUCT((H$5:H$504<=H89)*G$5:G$504) -> 94549236 | J89: =I89/SUM(G$5:G$504) -> 0.57184128 | K89: =IF(J89<=0.8,"A",IF(J89<=0.95,"B","C")) -> A | L89: ='3. Demand Forecast'!H77 -> 0.27 | M89: =IF(L89<=0.25,"X",IF(L89<=0.6,"Y","Z")) -> Y | N89: =K89&M89 -> AY
A90: ='1. Master Data'!A213 -> NT10209 | B90: ='1. Master Data'!B213 -> FitTrack Band 624 | C90: ='1. Master Data'!C213 -> Wearables | D90: ='1. Master Data'!D213 -> West DC | E90: ='1. Master Data'!F213 -> 119 | F90: ='2. Demand History'!AA213 -> 4697 | G90: =E90*F90 -> 558943 | H90: =RANK(G90,G$5:G$504,0) -> 86 | I90: =SUMPRODUCT((H$5:H$504<=H90)*G$5:G$504) -> 95108179 | J90: =I90/SUM(G$5:G$504) -> 0.57522181 | K90: =IF(J90<=0.8,"A",IF(J90<=0.95,"B","C")) -> A | L90: ='3. Demand Forecast'!H213 -> 0.21 | M90: =IF(L90<=0.25,"X",IF(L90<=0.6,"Y","Z")) -> X | N90: =K90&M90 -> AX
A91: ='1. Master Data'!A15 -> NT10011 | B91: ='1. Master Data'!B15 -> Edge 790 5G 128GB | C91: ='1. Master Data'!C15 -> Smartphones | D91: ='1. Master Data'!D15 -> Central DC | E91: ='1. Master Data'!F15 -> 507 | F91: ='2. Demand History'!AA15 -> 1094 | G91: =E91*F91 -> 554658 | H91: =RANK(G91,G$5:G$504,0) -> 87 | I91: =SUMPRODUCT((H$5:H$504<=H91)*G$5:G$504) -> 95662837 | J91: =I91/SUM(G$5:G$504) -> 0.57857643 | K91: =IF(J91<=0.8,"A",IF(J91<=0.95,"B","C")) -> A | L91: ='3. Demand Forecast'!H15 -> 0.33 | M91: =IF(L91<=0.25,"X",IF(L91<=0.6,"Y","Z")) -> Y | N91: =K91&M91 -> AY
A92: ='1. Master Data'!A64 -> NT10060 | B92: ='1. Master Data'!B64 -> ProBook 839 i7 15in | C92: ='1. Master Data'!C64 -> Laptops | D92: ='1. Master Data'!D64 -> West DC | E92: ='1. Master Data'!F64 -> 1044 | F92: ='2. Demand History'!AA64 -> 526 | G92: =E92*F92 -> 549144 | H92: =RANK(G92,G$5:G$504,0) -> 88 | I92: =SUMPRODUCT((H$5:H$504<=H92)*G$5:G$504) -> 96211981 | J92: =I92/SUM(G$5:G$504) -> 0.5818977 | K92: =IF(J92<=0.8,"A",IF(J92<=0.95,"B","C")) -> A | L92: ='3. Demand Forecast'!H64 -> 1.04 | M92: =IF(L92<=0.25,"X",IF(L92<=0.6,"Y","Z")) -> Z | N92: =K92&M92 -> AZ
A93: ='1. Master Data'!A264 -> NT10260 | B93: ='1. Master Data'!B264 -> ArenaHeadset H428 | C93: ='1. Master Data'!C264 -> Gaming | D93: ='1. Master Data'!D264 -> East DC | E93: ='1. Master Data'!F264 -> 276 | F93: ='2. Demand History'!AA264 -> 1985 | G93: =E93*F93 -> 547860 | H93: =RANK(G93,G$5:G$504,0) -> 89 | I93: =SUMPRODUCT((H$5:H$504<=H93)*G$5:G$504) -> 96759841 | J93: =I93/SUM(G$5:G$504) -> 0.5852112 | K93: =IF(J93<=0.8,"A",IF(J93<=0.95,"B","C")) -> A | L93: ='3. Demand Forecast'!H264 -> 0.31 | M93: =IF(L93<=0.25,"X",IF(L93<=0.6,"Y","Z")) -> Y | N93: =K93&M93 -> AY
A94: ='1. Master Data'!A293 -> NT10289 | B94: ='1. Master Data'!B293 -> ArenaHeadset H623 | C94: ='1. Master Data'!C293 -> Gaming | D94: ='1. Master Data'!D293 -> West DC | E94: ='1. Master Data'!F293 -> 314 | F94: ='2. Demand History'!AA293 -> 1720 | G94: =E94*F94 -> 540080 | H94: =RANK(G94,G$5:G$504,0) -> 90 | I94: =SUMPRODUCT((H$5:H$504<=H94)*G$5:G$504) -> 97299921 | J94: =I94/SUM(G$5:G$504) -> 0.58847764 | K94: =IF(J94<=0.8,"A",IF(J94<=0.95,"B","C")) -> A | L94: ='3. Demand Forecast'!H293 -> 0.3 | M94: =IF(L94<=0.25,"X",IF(L94<=0.6,"Y","Z")) -> Y | N94: =K94&M94 -> AY
A95: ='1. Master Data'!A194 -> NT10190 | B95: ='1. Master Data'!B194 -> StudioPods 663 ANC | C95: ='1. Master Data'!C194 -> Audio | D95: ='1. Master Data'!D194 -> West DC | E95: ='1. Master Data'!F194 -> 204 | F95: ='2. Demand History'!AA194 -> 2646 | G95: =E95*F95 -> 539784 | H95: =RANK(G95,G$5:G$504,0) -> 91 | I95: =SUMPRODUCT((H$5:H$504<=H95)*G$5:G$504) -> 97839705 | J95: =I95/SUM(G$5:G$504) -> 0.5917423 | K95: =IF(J95<=0.8,"A",IF(J95<=0.95,"B","C")) -> A | L95: ='3. Demand Forecast'!H194 -> 0.33 | M95: =IF(L95<=0.25,"X",IF(L95<=0.6,"Y","Z")) -> Y | N95: =K95&M95 -> AY
A96: ='1. Master Data'!A453 -> NT10449 | B96: ='1. Master Data'!B453 -> NovaTab 443 Kids | C96: ='1. Master Data'!C453 -> Tablets | D96: ='1. Master Data'!D453 -> Central DC | E96: ='1. Master Data'!F453 -> 264 | F96: ='2. Demand History'!AA453 -> 2016 | G96: =E96*F96 -> 532224 | H96: =RANK(G96,G$5:G$504,0) -> 92 | I96: =SUMPRODUCT((H$5:H$504<=H96)*G$5:G$504) -> 98371929 | J96: =I96/SUM(G$5:G$504) -> 0.59496123 | K96: =IF(J96<=0.8,"A",IF(J96<=0.95,"B","C")) -> A | L96: ='3. Demand Forecast'!H453 -> 0.33 | M96: =IF(L96<=0.25,"X",IF(L96<=0.6,"Y","Z")) -> Y | N96: =K96&M96 -> AY
A97: ='1. Master Data'!A409 -> NT10405 | B97: ='1. Master Data'!B409 -> NovaTab 280 10in | C97: ='1. Master Data'!C409 -> Tablets | D97: ='1. Master Data'!D409 -> Central DC | E97: ='1. Master Data'!F409 -> 490 | F97: ='2. Demand History'!AA409 -> 1076 | G97: =E97*F97 -> 527240 | H97: =RANK(G97,G$5:G$504,0) -> 93 | I97: =SUMPRODUCT((H$5:H$504<=H97)*G$5:G$504) -> 98899169 | J97: =I97/SUM(G$5:G$504) -> 0.59815002 | K97: =IF(J97<=0.8,"A",IF(J97<=0.95,"B","C")) -> A | L97: ='3. Demand Forecast'!H409 -> 0.25 | M97: =IF(L97<=0.25,"X",IF(L97<=0.6,"Y","Z")) -> X | N97: =K97&M97 -> AX
A98: ='1. Master Data'!A78 -> NT10074 | B98: ='1. Master Data'!B78 -> WorkMate 446 i3 14in | C98: ='1. Master Data'!C78 -> Laptops | D98: ='1. Master Data'!D78 -> Central DC | E98: ='1. Master Data'!F78 -> 850 | F98: ='2. Demand History'!AA78 -> 618 | G98: =E98*F98 -> 525300 | H98: =RANK(G98,G$5:G$504,0) -> 94 | I98: =SUMPRODUCT((H$5:H$504<=H98)*G$5:G$504) -> 99424469 | J98: =I98/SUM(G$5:G$504) -> 0.60132708 | K98: =IF(J98<=0.8,"A",IF(J98<=0.95,"B","C")) -> A | L98: ='3. Demand Forecast'!H78 -> 0.29 | M98: =IF(L98<=0.25,"X",IF(L98<=0.6,"Y","Z")) -> Y | N98: =K98&M98 -> AY
A99: ='1. Master Data'!A98 -> NT10094 | B99: ='1. Master Data'!B98 -> ProBook 953 i7 15in | C99: ='1. Master Data'!C98 -> Laptops | D99: ='1. Master Data'!D98 -> Central DC | E99: ='1. Master Data'!F98 -> 860 | F99: ='2. Demand History'!AA98 -> 610 | G99: =E99*F99 -> 524600 | H99: =RANK(G99,G$5:G$504,0) -> 95 | I99: =SUMPRODUCT((H$5:H$504<=H99)*G$5:G$504) -> 99949069 | J99: =I99/SUM(G$5:G$504) -> 0.6044999 | K99: =IF(J99<=0.8,"A",IF(J99<=0.95,"B","C")) -> A | L99: ='3. Demand Forecast'!H98 -> 0.28 | M99: =IF(L99<=0.25,"X",IF(L99<=0.6,"Y","Z")) -> Y | N99: =K99&M99 -> AY
A100: ='1. Master Data'!A74 -> NT10070 | B100: ='1. Master Data'!B74 -> UltraSlim 400 Ryzen 5 | C100: ='1. Master Data'!C74 -> Laptops | D100: ='1. Master Data'!D74 -> Central DC | E100: ='1. Master Data'!F74 -> 1221 | F100: ='2. Demand History'!AA74 -> 426 | G100: =E100*F100 -> 520146 | H100: =RANK(G100,G$5:G$504,0) -> 96 | I100: =SUMPRODUCT((H$5:H$504<=H100)*G$5:G$504) -> 100469215 | J100: =I100/SUM(G$5:G$504) -> 0.60764578 | K100: =IF(J100<=0.8,"A",IF(J100<=0.95,"B","C")) -> A | L100: ='3. Demand Forecast'!H74 -> 0.27 | M100: =IF(L100<=0.25,"X",IF(L100<=0.6,"Y","Z")) -> Y | N100: =K100&M100 -> AY
A101: ='1. Master Data'!A54 -> NT10050 | B101: ='1. Master Data'!B54 -> Nova Lite 448 64GB | C101: ='1. Master Data'!C54 -> Smartphones | D101: ='1. Master Data'!D54 -> East DC | E101: ='1. Master Data'!F54 -> 261 | F101: ='2. Demand History'!AA54 -> 1978 | G101: =E101*F101 -> 516258 | H101: =RANK(G101,G$5:G$504,0) -> 97 | I101: =SUMPRODUCT((H$5:H$504<=H101)*G$5:G$504) -> 100985473 | J101: =I101/SUM(G$5:G$504) -> 0.61076815 | K101: =IF(J101<=0.8,"A",IF(J101<=0.95,"B","C")) -> A | L101: ='3. Demand Forecast'!H54 -> 0.25 | M101: =IF(L101<=0.25,"X",IF(L101<=0.6,"Y","Z")) -> X | N101: =K101&M101 -> AX
...

Sheet 5. Replenishment Model
A1: REPLENISHMENT MODEL
A2: Safety stock, reorder point, EOQ and order flags for all 500 SKUs. Service level 95 percent. | S2: Z (95% SL) | T2: Workdays/Mo | U2: Order Cost $ | V2: Holding %
S3: 1.65 | T3: 22 | U3: 50 | V3: 0.25
A4: SKU | B4: Product Name | C4: DC | D4: ABC | E4: XYZ | F4: Unit Cost | G4: Lead Time | H4: Avg Daily | I4: SD Daily | J4: Safety Stock | K4: Reorder Point | L4: EOQ | M4: On Hand | N4: Days of Supply | O4: Flag | P4: Priority | Q4: Policy
A5: ='1. Master Data'!A5 -> NT10001 | B5: ='1. Master Data'!B5 -> Nova X427 128GB | C5: ='1. Master Data'!D5 -> West DC | D5: ='4. ABC XYZ Analysis'!K5 -> A | E5: ='4. ABC XYZ Analysis'!M5 -> Y | F5: ='1. Master Data'!F5 -> 865 | G5: ='1. Master Data'!G5 -> 17 | H5: ='3. Demand Forecast'!F5/$T$3 -> 4.3227273 | I5: ='3. Demand Forecast'!G5/SQRT($T$3) -> 6.8650631 | J5: =ROUNDUP($S$3*I5*SQRT(G5),0) -> 47 | K5: =ROUNDUP(H5*G5+J5,0) -> 121 | L5: =IF(F5=0,0,ROUNDUP(SQRT(2*'4. ABC XYZ Analysis'!F5*$U$3/(F5*$V$3)),0)) -> 38 | M5: ='1. Master Data'!I5 -> 124 | N5: =IF(H5=0,999,ROUND(M5/H5,0)) -> 29 | O5: =IF(M5<=K5,"ORDER NOW",IF(M5<=K5*1.2,"ORDER SOON","OK")) -> ORDER SOON | P5: =IF(O5="ORDER NOW",IF(D5="A","URGENT",IF(D5="B","HIGH","MEDIUM")),IF(O5="ORDER SOON",IF(D5="A","HIGH","MEDIUM"),"LOW")) -> HIGH | Q5: =IF(E5="Z","Min Max","Reorder Point") -> Reorder Point
A6: ='1. Master Data'!A6 -> NT10002 | B6: ='1. Master Data'!B6 -> Pulse 962 Dual SIM | C6: ='1. Master Data'!D6 -> East DC | D6: ='4. ABC XYZ Analysis'!K6 -> A | E6: ='4. ABC XYZ Analysis'!M6 -> Y | F6: ='1. Master Data'!F6 -> 701 | G6: ='1. Master Data'!G6 -> 44 | H6: ='3. Demand Forecast'!F6/$T$3 -> 2.4 | I6: ='3. Demand Forecast'!G6/SQRT($T$3) -> 3.3685713 | J6: =ROUNDUP($S$3*I6*SQRT(G6),0) -> 37 | K6: =ROUNDUP(H6*G6+J6,0) -> 143 | L6: =IF(F6=0,0,ROUNDUP(SQRT(2*'4. ABC XYZ Analysis'!F6*$U$3/(F6*$V$3)),0)) -> 36 | M6: ='1. Master Data'!I6 -> 146 | N6: =IF(H6=0,999,ROUND(M6/H6,0)) -> 61 | O6: =IF(M6<=K6,"ORDER NOW",IF(M6<=K6*1.2,"ORDER SOON","OK")) -> ORDER SOON | P6: =IF(O6="ORDER NOW",IF(D6="A","URGENT",IF(D6="B","HIGH","MEDIUM")),IF(O6="ORDER SOON",IF(D6="A","HIGH","MEDIUM"),"LOW")) -> HIGH | Q6: =IF(E6="Z","Min Max","Reorder Point") -> Reorder Point
A7: ='1. Master Data'!A7 -> NT10003 | B7: ='1. Master Data'!B7 -> Nova Lite 936 64GB | C7: ='1. Master Data'!D7 -> West DC | D7: ='4. ABC XYZ Analysis'!K7 -> A | E7: ='4. ABC XYZ Analysis'!M7 -> Y | F7: ='1. Master Data'!F7 -> 261 | G7: ='1. Master Data'!G7 -> 21 | H7: ='3. Demand Forecast'!F7/$T$3 -> 5.4909091 | I7: ='3. Demand Forecast'!G7/SQRT($T$3) -> 8.1016272 | J7: =ROUNDUP($S$3*I7*SQRT(G7),0) -> 62 | K7: =ROUNDUP(H7*G7+J7,0) -> 178 | L7: =IF(F7=0,0,ROUNDUP(SQRT(2*'4. ABC XYZ Analysis'!F7*$U$3/(F7*$V$3)),0)) -> 78 | M7: ='1. Master Data'!I7 -> 181 | N7: =IF(H7=0,999,ROUND(M7/H7,0)) -> 33 | O7: =IF(M7<=K7,"ORDER NOW",IF(M7<=K7*1.2,"ORDER SOON","OK")) -> ORDER SOON | P7: =IF(O7="ORDER NOW",IF(D7="A","URGENT",IF(D7="B","HIGH","MEDIUM")),IF(O7="ORDER SOON",IF(D7="A","HIGH","MEDIUM"),"LOW")) -> HIGH | Q7: =IF(E7="Z","Min Max","Reorder Point") -> Reorder Point
A8: ='1. Master Data'!A8 -> NT10004 | B8: ='1. Master Data'!B8 -> Nova Lite 315 64GB | C8: ='1. Master Data'!D8 -> West DC | D8: ='4. ABC XYZ Analysis'!K8 -> A | E8: ='4. ABC XYZ Analysis'!M8 -> Y | F8: ='1. Master Data'!F8 -> 606 | G8: ='1. Master Data'!G8 -> 39 | H8: ='3. Demand Forecast'!F8/$T$3 -> 3.0454545 | I8: ='3. Demand Forecast'!G8/SQRT($T$3) -> 5.2447376 | J8: =ROUNDUP($S$3*I8*SQRT(G8),0) -> 55 | K8: =ROUNDUP(H8*G8+J8,0) -> 174 | L8: =IF(F8=0,0,ROUNDUP(SQRT(2*'4. ABC XYZ Analysis'!F8*$U$3/(F8*$V$3)),0)) -> 42 | M8: ='1. Master Data'!I8 -> 177 | N8: =IF(H8=0,999,ROUND(M8/H8,0)) -> 58 | O8: =IF(M8<=K8,"ORDER NOW",IF(M8<=K8*1.2,"ORDER SOON","OK")) -> ORDER SOON | P8: =IF(O8="ORDER NOW",IF(D8="A","URGENT",IF(D8="B","HIGH","MEDIUM")),IF(O8="ORDER SOON",IF(D8="A","HIGH","MEDIUM"),"LOW")) -> HIGH | Q8: =IF(E8="Z","Min Max","Reorder Point") -> Reorder Point
A9: ='1. Master Data'!A9 -> NT10005 | B9: ='1. Master Data'!B9 -> Pulse 753 Dual SIM | C9: ='1. Master Data'!D9 -> Central DC | D9: ='4. ABC XYZ Analysis'!K9 -> A | E9: ='4. ABC XYZ Analysis'!M9 -> Y | F9: ='1. Master Data'!F9 -> 598 | G9: ='1. Master Data'!G9 -> 25 | H9: ='3. Demand Forecast'!F9/$T$3 -> 1.6 | I9: ='3. Demand Forecast'!G9/SQRT($T$3) -> 2.1320072 | J9: =ROUNDUP($S$3*I9*SQRT(G9),0) -> 18 | K9: =ROUNDUP(H9*G9+J9,0) -> 58 | L9: =IF(F9=0,0,ROUNDUP(SQRT(2*'4. ABC XYZ Analysis'!F9*$U$3/(F9*$V$3)),0)) -> 39 | M9: ='1. Master Data'!I9 -> 61 | N9: =IF(H9=0,999,ROUND(M9/H9,0)) -> 38 | O9: =IF(M9<=K9,"ORDER NOW",IF(M9<=K9*1.2,"ORDER SOON","OK")) -> ORDER SOON | P9: =IF(O9="ORDER NOW",IF(D9="A","URGENT",IF(D9="B","HIGH","MEDIUM")),IF(O9="ORDER SOON",IF(D9="A","HIGH","MEDIUM"),"LOW")) -> HIGH | Q9: =IF(E9="Z","Min Max","Reorder Point") -> Reorder Point
A10: ='1. Master Data'!A10 -> NT10006 | B10: ='1. Master Data'!B10 -> Edge 244 5G 128GB | C10: ='1. Master Data'!D10 -> Central DC | D10: ='4. ABC XYZ Analysis'!K10 -> A | E10: ='4. ABC XYZ Analysis'!M10 -> Y | F10: ='1. Master Data'!F10 -> 627 | G10: ='1. Master Data'!G10 -> 35 | H10: ='3. Demand Forecast'!F10/$T$3 -> 3.0090909 | I10: ='3. Demand Forecast'!G10/SQRT($T$3) -> 4.1147738 | J10: =ROUNDUP($S$3*I10*SQRT(G10),0) -> 41 | K10: =ROUNDUP(H10*G10+J10,0) -> 147 | L10: =IF(F10=0,0,ROUNDUP(SQRT(2*'4. ABC XYZ Analysis'!F10*$U$3/(F10*$V$3)),0)) -> 66 | M10: ='1. Master Data'!I10 -> 150 | N10: =IF(H10=0,999,ROUND(M10/H10,0)) -> 50 | O10: =IF(M10<=K10,"ORDER NOW",IF(M10<=K10*1.2,"ORDER SOON","OK")) -> ORDER SOON | P10: =IF(O10="ORDER NOW",IF(D10="A","URGENT",IF(D10="B","HIGH","MEDIUM")),IF(O10="ORDER SOON",IF(D10="A","HIGH","MEDIUM"),"LOW")) -> HIGH | Q10: =IF(E10="Z","Min Max","Reorder Point") -> Reorder Point
A11: ='1. Master Data'!A11 -> NT10007 | B11: ='1. Master Data'!B11 -> Pulse 667 Dual SIM | C11: ='1. Master Data'!D11 -> Central DC | D11: ='4. ABC XYZ Analysis'!K11 -> A | E11: ='4. ABC XYZ Analysis'!M11 -> X | F11: ='1. Master Data'!F11 -> 685 | G11: ='1. Master Data'!G11 -> 36 | H11: ='3. Demand Forecast'!F11/$T$3 -> 1.5636364 | I11: ='3. Demand Forecast'!G11/SQRT($T$3) -> 2.5797287 | J11: =ROUNDUP($S$3*I11*SQRT(G11),0) -> 26 | K11: =ROUNDUP(H11*G11+J11,0) -> 83 | L11: =IF(F11=0,0,ROUNDUP(SQRT(2*'4. ABC XYZ Analysis'!F11*$U$3/(F11*$V$3)),0)) -> 34 | M11: ='1. Master Data'!I11 -> 86 | N11: =IF(H11=0,999,ROUND(M11/H11,0)) -> 55 | O11: =IF(M11<=K11,"ORDER NOW",IF(M11<=K11*1.2,"ORDER SOON","OK")) -> ORDER SOON | P11: =IF(O11="ORDER NOW",IF(D11="A","URGENT",IF(D11="B","HIGH","MEDIUM")),IF(O11="ORDER SOON",IF(D11="A","HIGH","MEDIUM"),"LOW")) -> HIGH | Q11: =IF(E11="Z","Min Max","Reorder Point") -> Reorder Point
A12: ='1. Master Data'!A12 -> NT10008 | B12: ='1. Master Data'!B12 -> Edge 637 5G 128GB | C12: ='1. Master Data'!D12 -> West DC | D12: ='4. ABC XYZ Analysis'!K12 -> A | E12: ='4. ABC XYZ Analysis'!M12 -> Y | F12: ='1. Master Data'!F12 -> 827 | G12: ='1. Master Data'!G12 -> 41 | H12: ='3. Demand Forecast'!F12/$T$3 -> 6.1727273 | I12: ='3. Demand Forecast'!G12/SQRT($T$3) -> 10.787956 | J12: =ROUNDUP($S$3*I12*SQRT(G12),0) -> 114 | K12: =ROUNDUP(H12*G12+J12,0) -> 368 | L12: =IF(F12=0,0,ROUNDUP(SQRT(2*'4. ABC XYZ Analysis'!F12*$U$3/(F12*$V$3)),0)) -> 60 | M12: ='1. Master Data'!I12 -> 370 | N12: =IF(H12=0,999,ROUND(M12/H12,0)) -> 60 | O12: =IF(M12<=K12,"ORDER NOW",IF(M12<=K12*1.2,"ORDER SOON","OK")) -> ORDER SOON | P12: =IF(O12="ORDER NOW",IF(D12="A","URGENT",IF(D12="B","HIGH","MEDIUM")),IF(O12="ORDER SOON",IF(D12="A","HIGH","MEDIUM"),"LOW")) -> HIGH | Q12: =IF(E12="Z","Min Max","Reorder Point") -> Reorder Point
A13: ='1. Master Data'!A13 -> NT10009 | B13: ='1. Master Data'!B13 -> Nova X689 128GB | C13: ='1. Master Data'!D13 -> West DC | D13: ='4. ABC XYZ Analysis'!K13 -> A | E13: ='4. ABC XYZ Analysis'!M13 -> Y | F13: ='1. Master Data'!F13 -> 382 | G13: ='1. Master Data'!G13 -> 26 | H13: ='3. Demand Forecast'!F13/$T$3 -> 2.2454545 | I13: ='3. Demand Forecast'!G13/SQRT($T$3) -> 2.8355695 | J13: =ROUNDUP($S$3*I13*SQRT(G13),0) -> 24 | K13: =ROUNDUP(H13*G13+J13,0) -> 83 | L13: =IF(F13=0,0,ROUNDUP(SQRT(2*'4. ABC XYZ Analysis'!F13*$U$3/(F13*$V$3)),0)) -> 60 | M13: ='1. Master Data'!I13 -> 86 | N13: =IF(H13=0,999,ROUND(M13/H13,0)) -> 38 | O13: =IF(M13<=K13,"ORDER NOW",IF(M13<=K13*1.2,"ORDER SOON","OK")) -> ORDER SOON | P13: =IF(O13="ORDER NOW",IF(D13="A","URGENT",IF(D13="B","HIGH","MEDIUM")),IF(O13="ORDER SOON",IF(D13="A","HIGH","MEDIUM"),"LOW")) -> HIGH | Q13: =IF(E13="Z","Min Max","Reorder Point") -> Reorder Point
A14: ='1. Master Data'!A14 -> NT10010 | B14: ='1. Master Data'!B14 -> Nova X834 128GB | C14: ='1. Master Data'!D14 -> West DC | D14: ='4. ABC XYZ Analysis'!K14 -> A | E14: ='4. ABC XYZ Analysis'!M14 -> X | F14: ='1. Master Data'!F14 -> 395 | G14: ='1. Master Data'!G14 -> 42 | H14: ='3. Demand Forecast'!F14/$T$3 -> 10.445455 | I14: ='3. Demand Forecast'!G14/SQRT($T$3) -> 15.435732 | J14: =ROUNDUP($S$3*I14*SQRT(G14),0) -> 166 | K14: =ROUNDUP(H14*G14+J14,0) -> 605 | L14: =IF(F14=0,0,ROUNDUP(SQRT(2*'4. ABC XYZ Analysis'!F14*$U$3/(F14*$V$3)),0)) -> 143 | M14: ='1. Master Data'!I14 -> 608 | N14: =IF(H14=0,999,ROUND(M14/H14,0)) -> 58 | O14: =IF(M14<=K14,"ORDER NOW",IF(M14<=K14*1.2,"ORDER SOON","OK")) -> ORDER SOON | P14: =IF(O14="ORDER NOW",IF(D14="A","URGENT",IF(D14="B","HIGH","MEDIUM")),IF(O14="ORDER SOON",IF(D14="A","HIGH","MEDIUM"),"LOW")) -> HIGH | Q14: =IF(E14="Z","Min Max","Reorder Point") -> Reorder Point
A15: ='1. Master Data'!A15 -> NT10011 | B15: ='1. Master Data'!B15 -> Edge 790 5G 128GB | C15: ='1. Master Data'!D15 -> Central DC | D15: ='4. ABC XYZ Analysis'!K15 -> A | E15: ='4. ABC XYZ Analysis'!M15 -> X | F15: ='1. Master Data'!F15 -> 507 | G15: ='1. Master Data'!G15 -> 43 | H15: ='3. Demand Forecast'!F15/$T$3 -> 4.1454545 | I15: ='3. Demand Forecast'!G15/SQRT($T$3) -> 6.3320613 | J15: =ROUNDUP($S$3*I15*SQRT(G15),0) -> 69 | K15: =ROUNDUP(H15*G15+J15,0) -> 248 | L15: =IF(F15=0,0,ROUNDUP(SQRT(2*'4. ABC XYZ Analysis'!F15*$U$3/(F15*$V$3)),0)) -> 85 | M15: ='1. Master Data'!I15 -> 251 | N15: =IF(H15=0,999,ROUND(M15/H15,0)) -> 61 | O15: =IF(M15<=K15,"ORDER NOW",IF(M15<=K15*1.2,"ORDER SOON","OK")) -> ORDER SOON | P15: =IF(O15="ORDER NOW",IF(D15="A","URGENT",IF(D15="B","HIGH","MEDIUM")),IF(O15="ORDER SOON",IF(D15="A","HIGH","MEDIUM"),"LOW")) -> HIGH | Q15: =IF(E15="Z","Min Max","Reorder Point") -> Reorder Point
A16: ='1. Master Data'!A16 -> NT10012 | B16: ='1. Master Data'!B16 -> Pulse 918 Dual SIM | C16: ='1. Master Data'!D16 -> East DC | D16: ='4. ABC XYZ Analysis'!K16 -> A | E16: ='4. ABC XYZ Analysis'!M16 -> Y | F16: ='1. Master Data'!F16 -> 693 | G16: ='1. Master Data'!G16 -> 41 | H16: ='3. Demand Forecast'!F16/$T$3 -> 0.45909091 | I16: ='3. Demand Forecast'!G16/SQRT($T$3) -> 0.59696201 | J16: =ROUNDUP($S$3*I16*SQRT(G16),0) -> 7 | K16: =ROUNDUP(H16*G16+J16,0) -> 26 | L16: =IF(F16=0,0,ROUNDUP(SQRT(2*'4. ABC XYZ Analysis'!F16*$U$3/(F16*$V$3)),0)) -> 26 | M16: ='1. Master Data'!I16 -> 29 | N16: =IF(H16=0,999,ROUND(M16/H16,0)) -> 63 | O16: =IF(M16<=K16,"ORDER NOW",IF(M16<=K16*1.2,"ORDER SOON","OK")) -> ORDER SOON | P16: =IF(O16="ORDER NOW",IF(D16="A","URGENT",IF(D16="B","HIGH","MEDIUM")),IF(O16="ORDER SOON",IF(D16="A","HIGH","MEDIUM"),"LOW")) -> HIGH | Q16: =IF(E16="Z","Min Max","Reorder Point") -> Reorder Point
... A504: ='1. Master Data'!A504 -> NT10500 | B504: ='1. Master Data'!B504 -> Phone Case Clear V670 | C504: ='1. Master Data'!D504 -> East DC | D504: ='4. ABC XYZ Analysis'!K504 -> C | E504: ='4. ABC XYZ Analysis'!M504 -> Y | F504: ='1. Master Data'!F504 -> 28 | G504: ='1. Master Data'!G504 -> 22 | H504: ='3. Demand Forecast'!F504/$T$3 -> 11.218182 | I504: ='3. Demand Forecast'!G504/SQRT($T$3) -> 3.3685713 | J504: =ROUNDUP($S$3*I504*SQRT(G504),0) -> 27 | K504: =ROUNDUP(H504*G504+J504,0) -> 274 | L504: =IF(F504=0,0,ROUNDUP(SQRT(2*'4. ABC XYZ Analysis'!F504*$U$3/(F504*$V$3)),0)) -> 32 | M504: ='1. Master Data'!I504 -> 277 | N504: =IF(H504=0,999,ROUND(M504/H504,0)) -> 25 | O504: =IF(M504<=K504,"ORDER NOW",IF(M504<=K504*1.2,"ORDER SOON","OK")) -> ORDER SOON | P504: =IF(O504="ORDER NOW",IF(D504="A","URGENT",IF(D504="B","HIGH","MEDIUM")),IF(O504="ORDER SOON",IF(D504="A","HIGH","MEDIUM"),"LOW")) -> MEDIUM | Q504: =IF(E504="Z","Min Max","Reorder Point") -> Reorder Point
A506: FORMULA REFERENCE
A507: Avg Daily = forecast avg monthly / 22 workdays. SD Daily = monthly std dev / SQRT(22).
A508: Safety Stock = Z x SD Daily x SQRT(Lead Time). Z = 1.65 gives a 95 percent service level.
A509: Reorder Point = Avg Daily x Lead Time + Safety Stock. EOQ = SQRT(2 x Annual x Order Cost / (Unit Cost x Holding Percent)).
A510: Flag: at or below ROP = ORDER NOW. Within 20 percent above = ORDER SOON. Priority is ABC weighted so expensive parts surface first.
A511: Z items get a Min Max policy because erratic demand defeats forecasting. Blue cells S3 to V3 are the model levers: change them and all 500 rows recalculate.

Sheet 6. Inventory Health
A1: INVENTORY HEALTH
A2: Aging, turns, and the excess capital hiding in slow movers and EOL stock.
A4: SKU | B4: Product Name | C4: Category | D4: DC | E4: Status | F4: Unit Cost | G4: On Hand | H4: Tied Up Value | I4: Days Since Move | J4: Aging Bucket | K4: Months of Stock | L4: Turns | M4: Excess Flag | N4: Excess Value | O4: Action | R4: Category | S4: Excess $
A5: ='1. Master Data'!A5 -> NT10001 | B5: ='1. Master Data'!B5 -> Nova X427 128GB | C5: ='1. Master Data'!C5 -> Smartphones | D5: ='1. Master Data'!D5 -> West DC | E5: ='1. Master Data'!H5 -> Active | F5: ='1. Master Data'!F5 -> 865 | G5: ='1. Master Data'!I5 -> 124 | H5: =F5*G5 -> 107260 | I5: ='1. Master Data'!J5 -> 53 | J5: =IF(I5<=30,"Fresh",IF(I5<=90,"Watch",IF(I5<=180,"Aged","Obsolete Risk"))) -> Watch | K5: =IF('3. Demand Forecast'!F5=0,99,ROUND(G5/'3. Demand Forecast'!F5,1)) -> 1.3 | L5: =IF(G5=0,0,ROUND('4. ABC XYZ Analysis'!F5/G5,1)) -> 24.9 | M5: =IF(OR(E5="EOL",I5>90,K5>6),"EXCESS","OK") -> OK | N5: =IF(M5="EXCESS",H5,0) -> 0 | O5: =IF(E5="EOL","Scrap / Liquidate",IF(I5>180,"Disposition Review",IF(M5="EXCESS","Reduce orders and monitor","Healthy"))) -> Healthy | R5: Smartphones | S5: =SUMIF(C$5:C$504,R5,N$5:N$504) -> 204696
A6: ='1. Master Data'!A6 -> NT10002 | B6: ='1. Master Data'!B6 -> Pulse 962 Dual SIM | C6: ='1. Master Data'!C6 -> Smartphones | D6: ='1. Master Data'!D6 -> East DC | E6: ='1. Master Data'!H6 -> Active | F6: ='1. Master Data'!F6 -> 701 | G6: ='1. Master Data'!I6 -> 146 | H6: =F6*G6 -> 102346 | I6: ='1. Master Data'!J6 -> 48 | J6: =IF(I6<=30,"Fresh",IF(I6<=90,"Watch",IF(I6<=180,"Aged","Obsolete Risk"))) -> Watch | K6: =IF('3. Demand Forecast'!F6=0,99,ROUND(G6/'3. Demand Forecast'!F6,1)) -> 2.8 | L6: =IF(G6=0,0,ROUND('4. ABC XYZ Analysis'!F6/G6,1)) -> 15.5 | M6: =IF(OR(E6="EOL",I6>90,K6>6),"EXCESS","OK") -> OK | N6: =IF(M6="EXCESS",H6,0) -> 0 | O6: =IF(E6="EOL","Scrap / Liquidate",IF(I6>180,"Disposition Review",IF(M6="EXCESS","Reduce orders and monitor","Healthy"))) -> Healthy | R6: Laptops | S6: =SUMIF(C$5:C$504,R6,N$5:N$504) -> 161382
A7: ='1. Master Data'!A7 -> NT10003 | B7: ='1. Master Data'!B7 -> Nova Lite 936 64GB | C7: ='1. Master Data'!C7 -> Smartphones | D7: ='1. Master Data'!D7 -> West DC | E7: ='1. Master Data'!H7 -> Active | F7: ='1. Master Data'!F7 -> 261 | G7: ='1. Master Data'!I7 -> 181 | H7: =F7*G7 -> 47241 | I7: ='1. Master Data'!J7 -> 25 | J7: =IF(I7<=30,"Fresh",IF(I7<=90,"Watch",IF(I7<=180,"Aged","Obsolete Risk"))) -> Fresh | K7: =IF('3. Demand Forecast'!F7=0,99,ROUND(G7/'3. Demand Forecast'!F7,1)) -> 1.5 | L7: =IF(G7=0,0,ROUND('4. ABC XYZ Analysis'!F7/G7,1)) -> 21.7 | M7: =IF(OR(E7="EOL",I7>90,K7>6),"EXCESS","OK") -> OK | N7: =IF(M7="EXCESS",H7,0) -> 0 | O7: =IF(E7="EOL","Scrap / Liquidate",IF(I7>180,"Disposition Review",IF(M7="EXCESS","Reduce orders and monitor","Healthy"))) -> Healthy | R7: TVs | S7: =SUMIF(C$5:C$504,R7,N$5:N$504) -> 160608
A8: ='1. Master Data'!A8 -> NT10004 | B8: ='1. Master Data'!B8 -> Nova Lite 315 64GB | C8: ='1. Master Data'!C8 -> Smartphones | D8: ='1. Master Data'!D8 -> West DC | E8: ='1. Master Data'!H8 -> Active | F8: ='1. Master Data'!F8 -> 606 | G8: ='1. Master Data'!I8 -> 177 | H8: =F8*G8 -> 107262 | I8: ='1. Master Data'!J8 -> 29 | J8: =IF(I8<=30,"Fresh",IF(I8<=90,"Watch",IF(I8<=180,"Aged","Obsolete Risk"))) -> Fresh | K8: =IF('3. Demand Forecast'!F8=0,99,ROUND(G8/'3. Demand Forecast'!F8,1)) -> 2.6 | L8: =IF(G8=0,0,ROUND('4. ABC XYZ Analysis'!F8/G8,1)) -> 14.8 | M8: =IF(OR(E8="EOL",I8>90,K8>6),"EXCESS","OK") -> OK | N8: =IF(M8="EXCESS",H8,0) -> 0 | O8: =IF(E8="EOL","Scrap / Liquidate",IF(I8>180,"Disposition Review",IF(M8="EXCESS","Reduce orders and monitor","Healthy"))) -> Healthy | R8: Audio | S8: =SUMIF(C$5:C$504,R8,N$5:N$504) -> 213003
A9: ='1. Master Data'!A9 -> NT10005 | B9: ='1. Master Data'!B9 -> Pulse 753 Dual SIM | C9: ='1. Master Data'!C9 -> Smartphones | D9: ='1. Master Data'!D9 -> Central DC | E9: ='1. Master Data'!H9 -> Active | F9: ='1. Master Data'!F9 -> 598 | G9: ='1. Master Data'!I9 -> 61 | H9: =F9*G9 -> 36478 | I9: ='1. Master Data'!J9 -> 43 | J9: =IF(I9<=30,"Fresh",IF(I9<=90,"Watch",IF(I9<=180,"Aged","Obsolete Risk"))) -> Watch | K9: =IF('3. Demand Forecast'!F9=0,99,ROUND(G9/'3. Demand Forecast'!F9,1)) -> 1.7 | L9: =IF(G9=0,0,ROUND('4. ABC XYZ Analysis'!F9/G9,1)) -> 36 | M9: =IF(OR(E9="EOL",I9>90,K9>6),"EXCESS","OK") -> OK | N9: =IF(M9="EXCESS",H9,0) -> 0 | O9: =IF(E9="EOL","Scrap / Liquidate",IF(I9>180,"Disposition Review",IF(M9="EXCESS","Reduce orders and monitor","Healthy"))) -> Healthy | R9: Wearables | S9: =SUMIF(C$5:C$504,R9,N$5:N$504) -> 353306
A10: ='1. Master Data'!A10 -> NT10006 | B10: ='1. Master Data'!B10 -> Edge 244 5G 128GB | C10: ='1. Master Data'!C10 -> Smartphones | D10: ='1. Master Data'!D10 -> Central DC | E10: ='1. Master Data'!H10 -> Active | F10: ='1. Master Data'!F10 -> 627 | G10: ='1. Master Data'!I10 -> 150 | H10: =F10*G10 -> 94050 | I10: ='1. Master Data'!J10 -> 68 | J10: =IF(I10<=30,"Fresh",IF(I10<=90,"Watch",IF(I10<=180,"Aged","Obsolete Risk"))) -> Watch | K10: =IF('3. Demand Forecast'!F10=0,99,ROUND(G10/'3. Demand Forecast'!F10,1)) -> 2.3 | L10: =IF(G10=0,0,ROUND('4. ABC XYZ Analysis'!F10/G10,1)) -> 45.4 | M10: =IF(OR(E10="EOL",I10>90,K10>6),"EXCESS","OK") -> OK | N10: =IF(M10="EXCESS",H10,0) -> 0 | O10: =IF(E10="EOL","Scrap / Liquidate",IF(I10>180,"Disposition Review",IF(M10="EXCESS","Reduce orders and monitor","Healthy"))) -> Healthy | R10: Gaming | S10: =SUMIF(C$5:C$504,R10,N$5:N$504) -> 223320
A11: ='1. Master Data'!A11 -> NT10007 | B11: ='1. Master Data'!B11 -> Pulse 667 Dual SIM | C11: ='1. Master Data'!C11 -> Smartphones | D11: ='1. Master Data'!D11 -> Central DC | E11: ='1. Master Data'!H11 -> Active | F11: ='1. Master Data'!F11 -> 685 | G11: ='1. Master Data'!I11 -> 86 | H11: =F11*G11 -> 58910 | I11: ='1. Master Data'!J11 -> 16 | J11: =IF(I11<=30,"Fresh",IF(I11<=90,"Watch",IF(I11<=180,"Aged","Obsolete Risk"))) -> Fresh | K11: =IF('3. Demand Forecast'!F11=0,99,ROUND(G11/'3. Demand Forecast'!F11,1)) -> 2.5 | L11: =IF(G11=0,0,ROUND('4. ABC XYZ Analysis'!F11/G11,1)) -> 22.2 | M11: =IF(OR(E11="EOL",I11>90,K11>6),"EXCESS","OK") -> OK | N11: =IF(M11="EXCESS",H11,0) -> 0 | O11: =IF(E11="EOL","Scrap / Liquidate",IF(I11>180,"Disposition Review",IF(M11="EXCESS","Reduce orders and monitor","Healthy"))) -> Healthy | R11: Smart Home | S11: =SUMIF(C$5:C$504,R11,N$5:N$504) -> 246695
A12: ='1. Master Data'!A12 -> NT10008 | B12: ='1. Master Data'!B12 -> Edge 637 5G 128GB | C12: ='1. Master Data'!C12 -> Smartphones | D12: ='1. Master Data'!D12 -> West DC | E12: ='1. Master Data'!H12 -> Active | F12: ='1. Master Data'!F12 -> 827 | G12: ='1. Master Data'!I12 -> 370 | H12: =F12*G12 -> 305990 | I12: ='1. Master Data'!J12 -> 69 | J12: =IF(I12<=30,"Fresh",IF(I12<=90,"Watch",IF(I12<=180,"Aged","Obsolete Risk"))) -> Watch | K12: =IF('3. Demand Forecast'!F12=0,99,ROUND(G12/'3. Demand Forecast'!F12,1)) -> 2.7 | L12: =IF(G12=0,0,ROUND('4. ABC XYZ Analysis'!F12/G12,1)) -> 19.5 | M12: =IF(OR(E12="EOL",I12>90,K12>6),"EXCESS","OK") -> OK | N12: =IF(M12="EXCESS",H12,0) -> 0 | O12: =IF(E12="EOL","Scrap / Liquidate",IF(I12>180,"Disposition Review",IF(M12="EXCESS","Reduce orders and monitor","Healthy"))) -> Healthy | R12: Cameras | S12: =SUMIF(C$5:C$504,R12,N$5:N$504) -> 250872
A13: ='1. Master Data'!A13 -> NT10009 | B13: ='1. Master Data'!B13 -> Nova X689 128GB | C13: ='1. Master Data'!C13 -> Smartphones | D13: ='1. Master Data'!D13 -> West DC | E13: ='1. Master Data'!H13 -> Active | F13: ='1. Master Data'!F13 -> 382 | G13: ='1. Master Data'!I13 -> 86 | H13: =F13*G13 -> 32852 | I13: ='1. Master Data'!J13 -> 53 | J13: =IF(I13<=30,"Fresh",IF(I13<=90,"Watch",IF(I13<=180,"Aged","Obsolete Risk"))) -> Watch | K13: =IF('3. Demand Forecast'!F13=0,99,ROUND(G13/'3. Demand Forecast'!F13,1)) -> 1.7 | L13: =IF(G13=0,0,ROUND('4. ABC XYZ Analysis'!F13/G13,1)) -> 39.5 | M13: =IF(OR(E13="EOL",I13>90,K13>6),"EXCESS","OK") -> OK | N13: =IF(M13="EXCESS",H13,0) -> 0 | O13: =IF(E13="EOL","Scrap / Liquidate",IF(I13>180,"Disposition Review",IF(M13="EXCESS","Reduce orders and monitor","Healthy"))) -> Healthy | R13: Tablets | S13: =SUMIF(C$5:C$504,R13,N$5:N$504) -> 381816
A14: ='1. Master Data'!A14 -> NT10010 | B14: ='1. Master Data'!B14 -> Nova X834 128GB | C14: ='1. Master Data'!C14 -> Smartphones | D14: ='1. Master Data'!D14 -> West DC | E14: ='1. Master Data'!H14 -> Active | F14: ='1. Master Data'!F14 -> 395 | G14: ='1. Master Data'!I14 -> 608 | H14: =F14*G14 -> 240160 | I14: ='1. Master Data'!J14 -> 30 | J14: =IF(I14<=30,"Fresh",IF(I14<=90,"Watch",IF(I14<=180,"Aged","Obsolete Risk"))) -> Fresh | K14: =IF('3. Demand Forecast'!F14=0,99,ROUND(G14/'3. Demand Forecast'!F14,1)) -> 2.6 | L14: =IF(G14=0,0,ROUND('4. ABC XYZ Analysis'!F14/G14,1)) -> 33.1 | M14: =IF(OR(E14="EOL",I14>90,K14>6),"EXCESS","OK") -> OK | N14: =IF(M14="EXCESS",H14,0) -> 0 | O14: =IF(E14="EOL","Scrap / Liquidate",IF(I14>180,"Disposition Review",IF(M14="EXCESS","Reduce orders and monitor","Healthy"))) -> Healthy | R14: Accessories | S14: =SUMIF(C$5:C$504,R14,N$5:N$504) -> 477262
A15: ='1. Master Data'!A15 -> NT10011 | B15: ='1. Master Data'!B15 -> Edge 790 5G 128GB | C15: ='1. Master Data'!C15 -> Smartphones | D15: ='1. Master Data'!D15 -> Central DC | E15: ='1. Master Data'!H15 -> Active | F15: ='1. Master Data'!F15 -> 507 | G15: ='1. Master Data'!I15 -> 251 | H15: =F15*G15 -> 127257 | I15: ='1. Master Data'!J15 -> 53 | J15: =IF(I15<=30,"Fresh",IF(I15<=90,"Watch",IF(I15<=180,"Aged","Obsolete Risk"))) -> Watch | K15: =IF('3. Demand Forecast'!F15=0,99,ROUND(G15/'3. Demand Forecast'!F15,1)) -> 2.8 | L15: =IF(G15=0,0,ROUND('4. ABC XYZ Analysis'!F15/G15,1)) -> 36.5 | M15: =IF(OR(E15="EOL",I15>90,K15>6),"EXCESS","OK") -> OK | N15: =IF(M15="EXCESS",H15,0) -> 0 | O15: =IF(E15="EOL","Scrap / Liquidate",IF(I15>180,"Disposition Review",IF(M15="EXCESS","Reduce orders and monitor","Healthy"))) -> Healthy
A16: ='1. Master Data'!A16 -> NT10012 | B16: ='1. Master Data'!B16 -> Pulse 918 Dual SIM | C16: ='1. Master Data'!C16 -> Smartphones | D16: ='1. Master Data'!D16 -> East DC | E16: ='1. Master Data'!H16 -> Active | F16: ='1. Master Data'!F16 -> 693 | G16: ='1. Master Data'!I16 -> 29 | H16: =F16*G16 -> 20097 | I16: ='1. Master Data'!J16 -> 6 | J16: =IF(I16<=30,"Fresh",IF(I16<=90,"Watch",IF(I16<=180,"Aged","Obsolete Risk"))) -> Fresh | K16: =IF('3. Demand Forecast'!F16=0,99,ROUND(G16/'3. Demand Forecast'!F16,1)) -> 2.9 | L16: =IF(G16=0,0,ROUND('4. ABC XYZ Analysis'!F16/G16,1)) -> 39.1 | M16: =IF(OR(E16="EOL",I16>90,K16>6),"EXCESS","OK") -> OK | N16: =IF(M16="EXCESS",H16,0) -> 0 | O16: =IF(E16="EOL","Scrap / Liquidate",IF(I16>180,"Disposition Review",IF(M16="EXCESS","Reduce orders and monitor","Healthy"))) -> Healthy
A17: ='1. Master Data'!A17 -> NT10013 | B17: ='1. Master Data'!B17 -> Pulse 569 Dual SIM | C17: ='1. Master Data'!C17 -> Smartphones | D17: ='1. Master Data'!D17 -> West DC | E17: ='1. Master Data'!H17 -> EOL | F17: ='1. Master Data'!F17 -> 454 | G17: ='1. Master Data'!I17 -> 24 | H17: =F17*G17 -> 10896 | I17: ='1. Master Data'!J17 -> 202 | J17: =IF(I17<=30,"Fresh",IF(I17<=90,"Watch",IF(I17<=180,"Aged","Obsolete Risk"))) -> Obsolete Risk | K17: =IF('3. Demand Forecast'!F17=0,99,ROUND(G17/'3. Demand Forecast'!F17,1)) -> 5.9 | L17: =IF(G17=0,0,ROUND('4. ABC XYZ Analysis'!F17/G17,1)) -> 55.8 | M17: =IF(OR(E17="EOL",I17>90,K17>6),"EXCESS","OK") -> EXCESS | N17: =IF(M17="EXCESS",H17,0) -> 10896 | O17: =IF(E17="EOL","Scrap / Liquidate",IF(I17>180,"Disposition Review",IF(M17="EXCESS","Reduce orders and monitor","Healthy"))) -> Scrap / Liquidate
A18: ='1. Master Data'!A18 -> NT10014 | B18: ='1. Master Data'!B18 -> Edge 927 5G 128GB | C18: ='1. Master Data'!C18 -> Smartphones | D18: ='1. Master Data'!D18 -> East DC | E18: ='1. Master Data'!H18 -> EOL | F18: ='1. Master Data'!F18 -> 284 | G18: ='1. Master Data'!I18 -> 38 | H18: =F18*G18 -> 10792 | I18: ='1. Master Data'!J18 -> 184 | J18: =IF(I18<=30,"Fresh",IF(I18<=90,"Watch",IF(I18<=180,"Aged","Obsolete Risk"))) -> Obsolete Risk | K18: =IF('3. Demand Forecast'!F18=0,99,ROUND(G18/'3. Demand Forecast'!F18,1)) -> 4.1 | L18: =IF(G18=0,0,ROUND('4. ABC XYZ Analysis'!F18/G18,1)) -> 38.2 | M18: =IF(OR(E18="EOL",I18>90,K18>6),"EXCESS","OK") -> EXCESS | N18: =IF(M18="EXCESS",H18,0) -> 10792 | O18: =IF(E18="EOL","Scrap / Liquidate",IF(I18>180,"Disposition Review",IF(M18="EXCESS","Reduce orders and monitor","Healthy"))) -> Scrap / Liquidate
A19: ='1. Master Data'!A19 -> NT10015 | B19: ='1. Master Data'!B19 -> Edge 805 5G 128GB | C19: ='1. Master Data'!C19 -> Smartphones | D19: ='1. Master Data'!D19 -> East DC | E19: ='1. Master Data'!H19 -> Active | F19: ='1. Master Data'!F19 -> 437 | G19: ='1. Master Data'!I19 -> 133 | H19: =F19*G19 -> 58121 | I19: ='1. Master Data'!J19 -> 26 | J19: =IF(I19<=30,"Fresh",IF(I19<=90,"Watch",IF(I19<=180,"Aged","Obsolete Risk"))) -> Fresh | K19: =IF('3. Demand Forecast'!F19=0,99,ROUND(G19/'3. Demand Forecast'!F19,1)) -> 2.7 | L19: =IF(G19=0,0,ROUND('4. ABC XYZ Analysis'!F19/G19,1)) -> 46 | M19: =IF(OR(E19="EOL",I19>90,K19>6),"EXCESS","OK") -> OK | N19: =IF(M19="EXCESS",H19,0) -> 0 | O19: =IF(E19="EOL","Scrap / Liquidate",IF(I19>180,"Disposition Review",IF(M19="EXCESS","Reduce orders and monitor","Healthy"))) -> Healthy
A20: ='1. Master Data'!A20 -> NT10016 | B20: ='1. Master Data'!B20 -> Nova Lite 610 64GB | C20: ='1. Master Data'!C20 -> Smartphones | D20: ='1. Master Data'!D20 -> Central DC | E20: ='1. Master Data'!H20 -> Active | F20: ='1. Master Data'!F20 -> 449 | G20: ='1. Master Data'!I20 -> 238 | H20: =F20*G20 -> 106862 | I20: ='1. Master Data'!J20 -> 49 | J20: =IF(I20<=30,"Fresh",IF(I20<=90,"Watch",IF(I20<=180,"Aged","Obsolete Risk"))) -> Watch | K20: =IF('3. Demand Forecast'!F20=0,99,ROUND(G20/'3. Demand Forecast'!F20,1)) -> 2.2 | L20: =IF(G20=0,0,ROUND('4. ABC XYZ Analysis'!F20/G20,1)) -> 7.3 | M20: =IF(OR(E20="EOL",I20>90,K20>6),"EXCESS","OK") -> OK | N20: =IF(M20="EXCESS",H20,0) -> 0 | O20: =IF(E20="EOL","Scrap / Liquidate",IF(I20>180,"Disposition Review",IF(M20="EXCESS","Reduce orders and monitor","Healthy"))) -> Healthy
A21: ='1. Master Data'!A21 -> NT10017 | B21: ='1. Master Data'!B21 -> Nova X194 128GB | C21: ='1. Master Data'!C21 -> Smartphones | D21: ='1. Master Data'!D21 -> East DC | E21: ='1. Master Data'!H21 -> Active | F21: ='1. Master Data'!F21 -> 844 | G21: ='1. Master Data'!I21 -> 61 | H21: =F21*G21 -> 51484 | I21: ='1. Master Data'!J21 -> 37 | J21: =IF(I21<=30,"Fresh",IF(I21<=90,"Watch",IF(I21<=180,"Aged","Obsolete Risk"))) -> Watch | K21: =IF('3. Demand Forecast'!F21=0,99,ROUND(G21/'3. Demand Forecast'!F21,1)) -> 1.7 | L21: =IF(G21=0,0,ROUND('4. ABC XYZ Analysis'!F21/G21,1)) -> 26.3 | M21: =IF(OR(E21="EOL",I21>90,K21>6),"EXCESS","OK") -> OK | N21: =IF(M21="EXCESS",H21,0) -> 0 | O21: =IF(E21="EOL","Scrap / Liquidate",IF(I21>180,"Disposition Review",IF(M21="EXCESS","Reduce orders and monitor","Healthy"))) -> Healthy
A22: ='1. Master Data'!A22 -> NT10018 | B22: ='1. Master Data'!B22 -> Nova X223 Pro 256GB | C22: ='1. Master Data'!C22 -> Smartphones | D22: ='1. Master Data'!D22 -> West DC | E22: ='1. Master Data'!H22 -> Active | F22: ='1. Master Data'!F22 -> 809 | G22: ='1. Master Data'!I22 -> 202 | H22: =F22*G22 -> 163418 | I22: ='1. Master Data'!J22 -> 6 | J22: =IF(I22<=30,"Fresh",IF(I22<=90,"Watch",IF(I22<=180,"Aged","Obsolete Risk"))) -> Fresh | K22: =IF('3. Demand Forecast'!F22=0,99,ROUND(G22/'3. Demand Forecast'!F22,1)) -> 1.4 | L22: =IF(G22=0,0,ROUND('4. ABC XYZ Analysis'!F22/G22,1)) -> 8.1 | M22: =IF(OR(E22="EOL",I22>90,K22>6),"EXCESS","OK") -> OK | N22: =IF(M22="EXCESS",H22,0) -> 0 | O22: =IF(E22="EOL","Scrap / Liquidate",IF(I22>180,"Disposition Review",IF(M22="EXCESS","Reduce orders and monitor","Healthy"))) -> Healthy
A23: ='1. Master Data'!A23 -> NT10019 | B23: ='1. Master Data'!B23 -> Nova Lite 258 64GB | C23: ='1. Master Data'!C23 -> Smartphones | D23: ='1. Master Data'!D23 -> West DC | E23: ='1. Master Data'!H23 -> Active | F23: ='1. Master Data'!F23 -> 847 | G23: ='1. Master Data'!I23 -> 71 | H23: =F23*G23 -> 60137 | I23: ='1. Master Data'!J23 -> 42 | J23: =IF(I23<=30,"Fresh",IF(I23<=90,"Watch",IF(I23<=180,"Aged","Obsolete Risk"))) -> Watch | K23: =IF('3. Demand Forecast'!F23=0,99,ROUND(G23/'3. Demand Forecast'!F23,1)) -> 1.5 | L23: =IF(G23=0,0,ROUND('4. ABC XYZ Analysis'!F23/G23,1)) -> 10.7 | M23: =IF(OR(E23="EOL",I23>90,K23>6),"EXCESS","OK") -> OK | N23: =IF(M23="EXCESS",H23,0) -> 0 | O23: =IF(E23="EOL","Scrap / Liquidate",IF(I23>180,"Disposition Review",IF(M23="EXCESS","Reduce orders and monitor","Healthy"))) -> Healthy
A24: ='1. Master Data'!A24 -> NT10020 | B24: ='1. Master Data'!B24 -> Nova X658 Pro 256GB | C24: ='1. Master Data'!C24 -> Smartphones | D24: ='1. Master Data'!D24 -> West DC | E24: ='1. Master Data'!H24 -> Active | F24: ='1. Master Data'!F24 -> 852 | G24: ='1. Master Data'!I24 -> 64 | H24: =F24*G24 -> 54528 | I24: ='1. Master Data'!J24 -> 48 | J24: =IF(I24<=30,"Fresh",IF(I24<=90,"Watch",IF(I24<=180,"Aged","Obsolete Risk"))) -> Watch | K24: =IF('3. Demand Forecast'!F24=0,99,ROUND(G24/'3. Demand Forecast'!F24,1)) -> 1.6 | L24: =IF(G24=0,0,ROUND('4. ABC XYZ Analysis'!F24/G24,1)) -> 23.3 | M24: =IF(OR(E24="EOL",I24>90,K24>6),"EXCESS","OK") -> OK | N24: =IF(M24="EXCESS",H24,0) -> 0 | O24: =IF(E24="EOL","Scrap / Liquidate",IF(I24>180,"Disposition Review",IF(M24="EXCESS","Reduce orders and monitor","Healthy"))) -> Healthy
A25: ='1. Master Data'!A25 -> NT10021 | B25: ='1. Master Data'!B25 -> Pulse 397 Dual SIM | C25: ='1. Master Data'!C25 -> Smartphones | D25: ='1. Master Data'!D25 -> Central DC | E25: ='1. Master Data'!H25 -> Active | F25: ='1. Master Data'!F25 -> 413 | G25: ='1. Master Data'!I25 -> 100 | H25: =F25*G25 -> 41300 | I25: ='1. Master Data'!J25 -> 4 | J25: =IF(I25<=30,"Fresh",IF(I25<=90,"Watch",IF(I25<=180,"Aged","Obsolete Risk"))) -> Fresh | K25: =IF('3. Demand Forecast'!F25=0,99,ROUND(G25/'3. Demand Forecast'!F25,1)) -> 1.5 | L25: =IF(G25=0,0,ROUND('4. ABC XYZ Analysis'!F25/G25,1)) -> 56 | M25: =IF(OR(E25="EOL",I25>90,K25>6),"EXCESS","OK") -> OK | N25: =IF(M25="EXCESS",H25,0) -> 0 | O25: =IF(E25="EOL","Scrap / Liquidate",IF(I25>180,"Disposition Review",IF(M25="EXCESS","Reduce orders and monitor","Healthy"))) -> Healthy
A26: ='1. Master Data'!A26 -> NT10022 | B26: ='1. Master Data'!B26 -> Pulse 521 Dual SIM | C26: ='1. Master Data'!C26 -> Smartphones | D26: ='1. Master Data'!D26 -> East DC | E26: ='1. Master Data'!H26 -> Active | F26: ='1. Master Data'!F26 -> 782 | G26: ='1. Master Data'!I26 -> 281 | H26: =F26*G26 -> 219742 | I26: ='1. Master Data'!J26 -> 49 | J26: =IF(I26<=30,"Fresh",IF(I26<=90,"Watch",IF(I26<=180,"Aged","Obsolete Risk"))) -> Watch | K26: =IF('3. Demand Forecast'!F26=0,99,ROUND(G26/'3. Demand Forecast'!F26,1)) -> 2.4 | L26: =IF(G26=0,0,ROUND('4. ABC XYZ Analysis'!F26/G26,1)) -> 39.8 | M26: =IF(OR(E26="EOL",I26>90,K26>6),"EXCESS","OK") -> OK | N26: =IF(M26="EXCESS",H26,0) -> 0 | O26: =IF(E26="EOL","Scrap / Liquidate",IF(I26>180,"Disposition Review",IF(M26="EXCESS","Reduce orders and monitor","Healthy"))) -> Healthy
... A504: ='1. Master Data'!A504 -> NT10500 | B504: ='1. Master Data'!B504 -> Phone Case Clear V670 | C504: ='1. Master Data'!C504 -> Accessories | D504: ='1. Master Data'!D504 -> East DC | E504: ='1. Master Data'!H504 -> Active | F504: ='1. Master Data'!F504 -> 28 | G504: ='1. Master Data'!I504 -> 277 | H504: =F504*G504 -> 7756 | I504: ='1. Master Data'!J504 -> 10 | J504: =IF(I504<=30,"Fresh",IF(I504<=90,"Watch",IF(I504<=180,"Aged","Obsolete Risk"))) -> Fresh | K504: =IF('3. Demand Forecast'!F504=0,99,ROUND(G504/'3. Demand Forecast'!F504,1)) -> 1.1 | L504: =IF(G504=0,0,ROUND('4. ABC XYZ Analysis'!F504/G504,1)) -> 0.2 | M504: =IF(OR(E504="EOL",I504>90,K504>6),"EXCESS","OK") -> OK | N504: =IF(M504="EXCESS",H504,0) -> 0 | O504: =IF(E504="EOL","Scrap / Liquidate",IF(I504>180,"Disposition Review",IF(M504="EXCESS","Reduce orders and monitor","Healthy"))) -> Healthy
A506: FORMULA REFERENCE
A507: Tied Up Value = Unit Cost x On Hand. Months of Stock = On Hand / forecast avg monthly demand.
A508: Excess = EOL status, OR no movement in 90 plus days, OR more than 6 months of stock on hand.
A509: Action chain: EOL goes to scrap or liquidation, 180 plus days to disposition review, other excess gets order reduction and monitoring.

Sheet 7. Supplier Performance
A1: SUPPLIER PERFORMANCE
A2: Lead times, delivery reliability, and spend concentration across the supplier base.
A4: Supplier | B4: SKUs | C4: Avg Lead Time | D4: OTD % | E4: Annual Spend | F4: Spend Share | G4: Risk Flag | H4: Recommended Action
A5: Shenzhen Onyx Electronics | B5: =COUNTIF('1. Master Data'!E$5:E$504,A5) -> 73 | C5: =ROUND(AVERAGEIF('1. Master Data'!E$5:E$504,A5,'1. Master Data'!G$5:G$504),0) -> 21 | D5: 0.96 | E5: =SUMPRODUCT(('1. Master Data'!E$5:E$504=A5)*'1. Master Data'!F$5:F$504*'1. Master Data'!K$5:K$504) -> 22888171 | F5: =E5/SUM(E$5:E$14) -> 0.13842947 | G5: =IF(OR(D5<0.88,C5>35),"HIGH RISK",IF(OR(D5<0.93,C5>28),"WATCH","OK")) -> OK | H5: =IF(G5="HIGH RISK","Qualify a second source and raise safety stock on affected SKUs",IF(G5="WATCH","Review quarterly, track OTD trend","Maintain relationship")) -> Maintain relationship
A6: Pacific Semis | B6: =COUNTIF('1. Master Data'!E$5:E$504,A6) -> 77 | C6: =ROUND(AVERAGEIF('1. Master Data'!E$5:E$504,A6,'1. Master Data'!G$5:G$504),0) -> 40 | D6: 0.86 | E6: =SUMPRODUCT(('1. Master Data'!E$5:E$504=A6)*'1. Master Data'!F$5:F$504*'1. Master Data'!K$5:K$504) -> 39266161 | F6: =E6/SUM(E$5:E$14) -> 0.23748486 | G6: =IF(OR(D6<0.88,C6>35),"HIGH RISK",IF(OR(D6<0.93,C6>28),"WATCH","OK")) -> HIGH RISK | H6: =IF(G6="HIGH RISK","Qualify a second source and raise safety stock on affected SKUs",IF(G6="WATCH","Review quarterly, track OTD trend","Maintain relationship")) -> Qualify a second source and raise safety stock on affected SKUs
A7: Taipei MicroParts | B7: =COUNTIF('1. Master Data'!E$5:E$504,A7) -> 68 | C7: =ROUND(AVERAGEIF('1. Master Data'!E$5:E$504,A7,'1. Master Data'!G$5:G$504),0) -> 24 | D7: 0.94 | E7: =SUMPRODUCT(('1. Master Data'!E$5:E$504=A7)*'1. Master Data'!F$5:F$504*'1. Master Data'!K$5:K$504) -> 24412633 | F7: =E7/SUM(E$5:E$14) -> 0.14764954 | G7: =IF(OR(D7<0.88,C7>35),"HIGH RISK",IF(OR(D7<0.93,C7>28),"WATCH","OK")) -> OK | H7: =IF(G7="HIGH RISK","Qualify a second source and raise safety stock on affected SKUs",IF(G7="WATCH","Review quarterly, track OTD trend","Maintain relationship")) -> Maintain relationship
A8: Foxlink Components | B8: =COUNTIF('1. Master Data'!E$5:E$504,A8) -> 53 | C8: =ROUND(AVERAGEIF('1. Master Data'!E$5:E$504,A8,'1. Master Data'!G$5:G$504),0) -> 16 | D8: 0.97 | E8: =SUMPRODUCT(('1. Master Data'!E$5:E$504=A8)*'1. Master Data'!F$5:F$504*'1. Master Data'!K$5:K$504) -> 17578472 | F8: =E8/SUM(E$5:E$14) -> 0.10631599 | G8: =IF(OR(D8<0.88,C8>35),"HIGH RISK",IF(OR(D8<0.93,C8>28),"WATCH","OK")) -> OK | H8: =IF(G8="HIGH RISK","Qualify a second source and raise safety stock on affected SKUs",IF(G8="WATCH","Review quarterly, track OTD trend","Maintain relationship")) -> Maintain relationship
A9: Hanoi Assembly Works | B9: =COUNTIF('1. Master Data'!E$5:E$504,A9) -> 45 | C9: =ROUND(AVERAGEIF('1. Master Data'!E$5:E$504,A9,'1. Master Data'!G$5:G$504),0) -> 18 | D9: 0.92 | E9: =SUMPRODUCT(('1. Master Data'!E$5:E$504=A9)*'1. Master Data'!F$5:F$504*'1. Master Data'!K$5:K$504) -> 6413469 | F9: =E9/SUM(E$5:E$14) -> 0.038789169 | G9: =IF(OR(D9<0.88,C9>35),"HIGH RISK",IF(OR(D9<0.93,C9>28),"WATCH","OK")) -> WATCH | H9: =IF(G9="HIGH RISK","Qualify a second source and raise safety stock on affected SKUs",IF(G9="WATCH","Review quarterly, track OTD trend","Maintain relationship")) -> Review quarterly, track OTD trend
A10: Busan Display Tech | B10: =COUNTIF('1. Master Data'!E$5:E$504,A10) -> 77 | C10: =ROUND(AVERAGEIF('1. Master Data'!E$5:E$504,A10,'1. Master Data'!G$5:G$504),0) -> 38 | D10: 0.84 | E10: =SUMPRODUCT(('1. Master Data'!E$5:E$504=A10)*'1. Master Data'!F$5:F$504*'1. Master Data'!K$5:K$504) -> 31133068 | F10: =E10/SUM(E$5:E$14) -> 0.18829527 | G10: =IF(OR(D10<0.88,C10>35),"HIGH RISK",IF(OR(D10<0.93,C10>28),"WATCH","OK")) -> HIGH RISK | H10: =IF(G10="HIGH RISK","Qualify a second source and raise safety stock on affected SKUs",IF(G10="WATCH","Review quarterly, track OTD trend","Maintain relationship")) -> Qualify a second source and raise safety stock on affected SKUs
A11: Mumbai Cable Works | B11: =COUNTIF('1. Master Data'!E$5:E$504,A11) -> 19 | C11: =ROUND(AVERAGEIF('1. Master Data'!E$5:E$504,A11,'1. Master Data'!G$5:G$504),0) -> 9 | D11: 0.95 | E11: =SUMPRODUCT(('1. Master Data'!E$5:E$504=A11)*'1. Master Data'!F$5:F$504*'1. Master Data'!K$5:K$504) -> 2423196 | F11: =E11/SUM(E$5:E$14) -> 0.014655682 | G11: =IF(OR(D11<0.88,C11>35),"HIGH RISK",IF(OR(D11<0.93,C11>28),"WATCH","OK")) -> OK | H11: =IF(G11="HIGH RISK","Qualify a second source and raise safety stock on affected SKUs",IF(G11="WATCH","Review quarterly, track OTD trend","Maintain relationship")) -> Maintain relationship
A12: Dongguan Audio Labs | B12: =COUNTIF('1. Master Data'!E$5:E$504,A12) -> 23 | C12: =ROUND(AVERAGEIF('1. Master Data'!E$5:E$504,A12,'1. Master Data'!G$5:G$504),0) -> 19 | D12: 0.93 | E12: =SUMPRODUCT(('1. Master Data'!E$5:E$504=A12)*'1. Master Data'!F$5:F$504*'1. Master Data'!K$5:K$504) -> 6049393 | F12: =E12/SUM(E$5:E$14) -> 0.036587209 | G12: =IF(OR(D12<0.88,C12>35),"HIGH RISK",IF(OR(D12<0.93,C12>28),"WATCH","OK")) -> OK | H12: =IF(G12="HIGH RISK","Qualify a second source and raise safety stock on affected SKUs",IF(G12="WATCH","Review quarterly, track OTD trend","Maintain relationship")) -> Maintain relationship
A13: Penang Circuits | B13: =COUNTIF('1. Master Data'!E$5:E$504,A13) -> 54 | C13: =ROUND(AVERAGEIF('1. Master Data'!E$5:E$504,A13,'1. Master Data'!G$5:G$504),0) -> 21 | D13: 0.91 | E13: =SUMPRODUCT(('1. Master Data'!E$5:E$504=A13)*'1. Master Data'!F$5:F$504*'1. Master Data'!K$5:K$504) -> 13907032 | F13: =E13/SUM(E$5:E$14) -> 0.084110833 | G13: =IF(OR(D13<0.88,C13>35),"HIGH RISK",IF(OR(D13<0.93,C13>28),"WATCH","OK")) -> WATCH | H13: =IF(G13="HIGH RISK","Qualify a second source and raise safety stock on affected SKUs",IF(G13="WATCH","Review quarterly, track OTD trend","Maintain relationship")) -> Review quarterly, track OTD trend
A14: EuroParts Distribution | B14: =COUNTIF('1. Master Data'!E$5:E$504,A14) -> 11 | C14: =ROUND(AVERAGEIF('1. Master Data'!E$5:E$504,A14,'1. Master Data'!G$5:G$504),0) -> 10 | D14: 0.98 | E14: =SUMPRODUCT(('1. Master Data'!E$5:E$504=A14)*'1. Master Data'!F$5:F$504*'1. Master Data'!K$5:K$504) -> 1270151 | F14: =E14/SUM(E$5:E$14) -> 0.007681974 | G14: =IF(OR(D14<0.88,C14>35),"HIGH RISK",IF(OR(D14<0.93,C14>28),"WATCH","OK")) -> OK | H14: =IF(G14="HIGH RISK","Qualify a second source and raise safety stock on affected SKUs",IF(G14="WATCH","Review quarterly, track OTD trend","Maintain relationship")) -> Maintain relationship
A36: FORMULA REFERENCE
A37: SKUs, Avg Lead Time, and Annual Spend all calculate live from Master Data with COUNTIF, AVERAGEIF, and SUMPRODUCT.
A38: Risk: OTD under 88 percent or lead time over 35 days = HIGH RISK. OTD under 93 or lead time over 28 = WATCH.
A39: The exposure to watch: when one supplier carries a large spend share AND a risk flag at the same time.

Sheet 8. Executive Dashboard
A1: NOVATECH ELECTRONICS | SUPPLY CHAIN ANALYTICS DASHBOARD
A2: 500 SKUs | 3 Distribution Centers | 10 Suppliers | 24 Months of Demand | Analysis by Kavish Shah
A4: TOTAL INVENTORY | C4: EXCESS IDENTIFIED | E4: SKUs AT STOCKOUT RISK | G4: FORECAST MAPE (X,Y) | I4: HIGH RISK SUPPLIERS
A5: =SUM('6. Inventory Health'!H5:H504) -> 25852107 | C5: =SUM('6. Inventory Health'!N5:N504) -> 2672960 | E5: =COUNTIF('5. Replenishment Model'!O5:O504,"ORDER NOW") -> 30 | G5: =AVERAGEIF('4. ABC XYZ Analysis'!M5:M504,"<>Z",'3. Demand Forecast'!K5:K504) -> 0.32356769 | I5: =COUNTIF('7. Supplier Performance'!G5:G14,"HIGH RISK") -> 2
A8: KEY FINDINGS
A9: 1. $2.7M of excess capital identified across 85 SKUs: slow movers, aged stock, and $216K locked in EOL products awaiting disposition.
A10: 2. 30 SKUs are at or below reorder point right now, including high value A items inside their lead time window: immediate purchase orders required.
A11: 3. Forecast MAPE on forecastable items is 15 percent; stable X items run under 10. Erratic Z items were moved to a Min Max policy instead of forecasting.
A12: 4. Two suppliers (Pacific Semis and Busan Display Tech) carry roughly 43 percent of annual spend while flagging HIGH RISK on delivery and lead time: a concentration problem.
A13: 5. Seasonality is the forecasting story: Q4 demand runs nearly double the baseline, so seasonal SKUs need seasonal methods, not moving averages.
A15: NETWORK VIEW BY DC
A16: DC | B16: Inventory Value | C16: Excess Value | D16: SKUs to Order
A17: East DC | B17: =SUMIF('6. Inventory Health'!D$5:D$504,A17,'6. Inventory Health'!H$5:H$504) -> 8925451 | C17: =SUMIF('6. Inventory Health'!D$5:D$504,A17,'6. Inventory Health'!N$5:N$504) -> 972673 | D17: =COUNTIFS('5. Replenishment Model'!C$5:C$504,A17,'5. Replenishment Model'!O$5:O$504,"ORDER NOW") -> 12
A18: Central DC | B18: =SUMIF('6. Inventory Health'!D$5:D$504,A18,'6. Inventory Health'!H$5:H$504) -> 8508650 | C18: =SUMIF('6. Inventory Health'!D$5:D$504,A18,'6. Inventory Health'!N$5:N$504) -> 1178378 | D18: =COUNTIFS('5. Replenishment Model'!C$5:C$504,A18,'5. Replenishment Model'!O$5:O$504,"ORDER NOW") -> 8
A19: West DC | B19: =SUMIF('6. Inventory Health'!D$5:D$504,A19,'6. Inventory Health'!H$5:H$504) -> 8418006 | C19: =SUMIF('6. Inventory Health'!D$5:D$504,A19,'6. Inventory Health'!N$5:N$504) -> 521909 | D19: =COUNTIFS('5. Replenishment Model'!C$5:C$504,A19,'5. Replenishment Model'!O$5:O$504,"ORDER NOW") -> 10
A21: TOP 10 ACTIONS THIS WEEK
A22: # | B22: SKU | C22: Product | D22: Issue | E22: Impact $ | F22: Priority | R22: Category | S22: Value
A23: 1 | B23: NT10104 | C23: VisionLED 501in 4K | D23: At or below reorder point, 34 day lead time, A item | E23: 262608 | F23: URGENT | R23: Smartphones | S23: =SUMIF('6. Inventory Health'!C$5:C$504,R23,'6. Inventory Health'!H$5:H$504) -> 5390767
A24: 2 | B24: NT10139 | C24: VisionQ 920in QLED | D24: At or below reorder point, 37 day lead time, A item | E24: 240151 | F24: URGENT | R24: Laptops | S24: =SUMIF('6. Inventory Health'!C$5:C$504,R24,'6. Inventory Health'!H$5:H$504) -> 5114799
A25: 3 | B25: NT10396 | C25: MirrorlessM 229 | D25: At or below reorder point, 27 day lead time, A item | E25: 178360 | F25: URGENT | R25: TVs | S25: =SUMIF('6. Inventory Health'!C$5:C$504,R25,'6. Inventory Health'!H$5:H$504) -> 5280777
A26: 4 | B26: NT10035 | C26: Nova X683 Pro 256GB | D26: At or below reorder point, 44 day lead time, A item | E26: 148466 | F26: URGENT | R26: Audio | S26: =SUMIF('6. Inventory Health'!C$5:C$504,R26,'6. Inventory Health'!H$5:H$504) -> 1883120
A27: 5 | B27: NT10066 | C27: UltraSlim 542 Ryzen 5 | D27: At or below reorder point, 23 day lead time, A item | E27: 133245 | F27: URGENT | R27: Wearables | S27: =SUMIF('6. Inventory Health'!C$5:C$504,R27,'6. Inventory Health'!H$5:H$504) -> 1233929
A28: 6 | B28: NT10232 | C28: FitTrack Band 981 | D28: 200 days no movement, excess stock | E28: 83266 | F28: HIGH | R28: Gaming | S28: =SUMIF('6. Inventory Health'!C$5:C$504,R28,'6. Inventory Health'!H$5:H$504) -> 1746839
A29: 7 | B29: NT10089 | C29: UltraSlim 908 Ryzen 5 | D29: 130 days no movement, excess stock | E29: 79460 | F29: HIGH | R29: Smart Home | S29: =SUMIF('6. Inventory Health'!C$5:C$504,R29,'6. Inventory Health'!H$5:H$504) -> 933765
A30: 8 | B30: NT10154 | C30: StudioPods 523 ANC | D30: 198 days no movement, excess stock | E30: 78008 | F30: HIGH | R30: Cameras | S30: =SUMIF('6. Inventory Health'!C$5:C$504,R30,'6. Inventory Health'!H$5:H$504) -> 1591026
A31: 9 | B31: NT10237 | C31: NovaWatch 728 GPS | D31: 125 days no movement, excess stock | E31: 75780 | F31: HIGH | R31: Tablets | S31: =SUMIF('6. Inventory Health'!C$5:C$504,R31,'6. Inventory Health'!H$5:H$504) -> 1954147
A32: 10 | B32: NT10348 | C32: HomeCam 160 1080p | D32: 97 days no movement, excess stock | E32: 75152 | F32: HIGH | R32: Accessories | S32: =SUMIF('6. Inventory Health'!C$5:C$504,R32,'6. Inventory Health'!H$5:H$504) -> 722938
B56: file:///Users/kavishshah/Downloads/NovaTech_Analytics_Dashboard_3.html
